Workbook

Sheet Readme
A1: Workbook purpose:
A2: Places a number of restrictions on model behavior for reference case development, as follows:
A4: Data source/modifiable?
A5: Cap decay limits: unbounds steps 12 and 21 of fossil supply curves; limits decay of existing fossil capacity. User assumptions. May be modified.
A6: monetize ILED: despite the sheet name, ILED is no longer monetized. It is set here by user assumption. May be modified.
A7: Remaining sheets: defines the steps of the build rate constraints, based on historical seed values written in the HistoricalBuilds sheet and capital costs popluated by the fill table on sheet togetInvCosts. Users should contact Amit to modify the structure of these constraints.
A9: The build rate constraints will apply at the WEPS region levels irrespective of the regional aggregation in the model
A10: in fact, they should be based more on geograpical location than even WEPS reg definitions. I have put Colombia and Chile in CSA, for example.

Sheet Cap decay limits
A1: Trans - Update
B2: ~TFM_UPD
B3: TimeSlice | C3: LimType | D3: Attribute | E3: Year | F3: Pset_PN | G3: AllRegions
D4: ACT_BND | E4: =HistoricalBuilds!R3 -> 2017,2018 | F4: MIN*10,-*bio* | G4: 99999
D5: ACT_BND | F5: MIN*12,-*bio* | G5: 99999
D6: ACT_BND | F6: MinBio-21 | G6: 99999
D7: *ACT_COST | F7: MinBio-21 | G7: *2
B9: ~TFM_INS
B10: TimeSlice | C10: LimType | D10: Attribute | E10: Year | F10: Attrib_Cond | G10: Val_Cond | H10: CHI | I10: Pset_Set | J10: Pset_PN
C11: LO | D11: AFA | H11: 0.2 | I11: ELECOA,ELEGAS | J11: -*CT*,-*GT*
C12: LO | D12: AFA | E12: 0 | H12: 3 | I12: ELECOA,ELEGAS | J12: -*CT*,-*GT*
B15: ~UC_Sets: R_E: AllRegions
F17: ="~UC_T: "&HistoricalBuilds!$N$1-1 -> ~UC_T: 2018
A18: CSET_CN | B18: UC_N | C18: *UC_ATTR | D18: PSET_SET | E18: PSET_CI | F18: LimType | G18: UC_CAP | H18: UC_CAP~RHS | I18: UC_RHSRT | J18: UC_RHSRT~0 | K18: UC_Desc | L18: UC_FLO | M18: UC_FLO~RHS | N18: UC_DYNBND
B19: UC_Capdecay-OIL | C19: CAP, GROWTH | D19: ELE,CHP | E19: ELCOIL* | F19: LO | G19: 0.925 | H19: -0.2 | J19: 5 | K19: =RIGHT(B19,3)&" capacity annual decay limit - "&TEXT(1-G19,"0.0%") -> OIL capacity annual decay limit - 7.5% | N19: 1
B20: UC_Capdecay-Coa | C20: CAP, GROWTH | D20: ELE,CHP | E20: ELCCOA | F20: LO | G20: 0.925 | H20: -0.6 | J20: 5 | K20: =RIGHT(B20,3)&" capacity annual decay limit - "&TEXT(1-G20,"0.0%") -> Coa capacity annual decay limit - 7.5% | N20: 1
B21: UC_Capdecay-Gas | C21: CAP, GROWTH | D21: ELE,CHP | E21: ELCGAS | F21: LO | G21: 0.98 | H21: -0.1 | J21: 5 | K21: =RIGHT(B21,3)&" capacity annual decay limit - "&TEXT(1-G21,"0.0%") -> Gas capacity annual decay limit - 2.0% | N21: 1
A22: HET | B22: *UC_HeatProddecay | C22: FLO, GROWTH | D22: CHP | F22: N | I22: 0 | J22: 5 | K22: heat production annual decay limit - 0.0% | L22: 1 | M22: 1
F25: deactivated
B26: UC_N | C26: UC_ATTR | D26: PSET_SET | E26: PSET_CI | F26: LimType | G26: UC_ACT | H26: UC_ACT~RHS | I26: UC_RHSRT | J26: UC_RHSRT~0 | K26: UC_Desc
B27: Non-Decreasing_Wind | C27: ACT, GROWTH | D27: ELE | E27: ELCWIN | F27: UP | G27: 1 | H27: 1 | I27: 0 | J27: 5 | K27: non-decreasing wind generation
B28: Non-Decreasing_Solar | C28: ACT, GROWTH | D28: ELE | E28: ELCSOL | F28: UP | G28: 1 | H28: 1 | I28: 0 | J28: 5 | K28: non-decreasing solar generation

Sheet monetize ILED
A2: Technology | B2: ILED | E2: Attribute | F2: PSET_PN | G2: AllRegions | K2: 0.07 | L2: discount rate
A3: EN_COAPUL | B3: 3 | E3: INVCOST | F3: =A3 -> EN_COAPUL | G3: ="*"&(1+$K$2)^B3 -> *1.225043
A4: EN_COAIGCC | B4: 4 | E4: INVCOST | F4: =A4 -> EN_COAIGCC | G4: ="*"&(1+$K$2)^B4 -> *1.31079601
A5: EN_ZCOAIGCC | B5: 4 | E5: INVCOST | F5: =A5 -> EN_ZCOAIGCC | G5: ="*"&(1+$K$2)^B5 -> *1.31079601
A6: EN_ZGasCCAdv | B6: 3 | E6: INVCOST | F6: =A6 -> EN_ZGasCCAdv | G6: ="*"&(1+$K$2)^B6 -> *1.225043
A7: EN_GasCCAdv | B7: 3 | E7: INVCOST | F7: =A7 -> EN_GasCCAdv | G7: ="*"&(1+$K$2)^B7 -> *1.225043
A8: EN_GasCC | B8: 3 | E8: INVCOST | F8: =A8 -> EN_GasCC | G8: ="*"&(1+$K$2)^B8 -> *1.225043
A9: EN_GasCTAdv | B9: 2 | E9: INVCOST | F9: =A9 -> EN_GasCTAdv | G9: ="*"&(1+$K$2)^B9 -> *1.1449
A10: EN_GasCT | B10: 2 | E10: INVCOST | F10: =A10 -> EN_GasCT | G10: ="*"&(1+$K$2)^B10 -> *1.1449
A11: EN_Biomass* | B11: 4 | E11: INVCOST | F11: =A11 -> EN_Biomass* | G11: ="*"&(1+$K$2)^B11 -> *1.31079601
A12: EN_Zbiomass* | B12: 4 | E12: INVCOST | F12: =A12 -> EN_Zbiomass* | G12: ="*"&(1+$K$2)^B12 -> *1.31079601
A13: EN_OilCCAdv | B13: 3 | E13: INVCOST | F13: =A13 -> EN_OilCCAdv | G13: ="*"&(1+$K$2)^B13 -> *1.225043
A14: EN_NuclearAdv | B14: 6 | E14: INVCOST | F14: =A14 -> EN_NuclearAdv | G14: ="*"&(1+$K$2)^B14 -> *1.500730351849
... A19: E[_]WON* | B19: 3 | E19: INVCOST | F19: =A19 -> E[_]WON* | G19: ="*"&(1+$K$2)^B19 -> *1.225043
E22: ~TFM_INS-TS
E23: Attribute | F23: PSET_PN | G23: 2017 | H23: 2018 | I23: 2019 | J23: 0
E24: ILED | F24: =A3 -> EN_COAPUL | I24: =B3 -> 3 | J24: 3
E25: ILED | F25: =A4 -> EN_COAIGCC | I25: =B4 -> 4 | J25: 3
E26: ILED | F26: =A5 -> EN_ZCOAIGCC | I26: =B5 -> 4 | J26: 3
E27: ILED | F27: =A6 -> EN_ZGasCCAdv | I27: =B6 -> 3 | J27: 3
E28: ILED | F28: =A7 -> EN_GasCCAdv | I28: =B7 -> 3 | J28: 3
E29: ILED | F29: =A8 -> EN_GasCC | I29: =B8 -> 3 | J29: 3
E30: ILED | F30: =A9 -> EN_GasCTAdv | I30: =B9 -> 2 | J30: 3
E31: ILED | F31: =A10 -> EN_GasCT | I31: =B10 -> 2 | J31: 3
E32: ILED | F32: =A11 -> EN_Biomass* | G32: 0 | H32: 0 | I32: =B11 -> 4 | J32: 5
E33: ILED | F33: =A12 -> EN_Zbiomass* | I33: =B12 -> 4 | J33: 3
E34: * | F34: =A13 -> EN_OilCCAdv | I34: =B13 -> 3 | J34: 3
E35: ILED | F35: =A14 -> EN_NuclearAdv | I35: =B14 -> 6 | J35: 3
E36: ILED | F36: =A15 -> EN_GeoThermal* | I36: =B15 -> 6 | J36: 3
E37: ILED | F37: =A16 -> EN_Hydro* | I37: =B16 -> 4 | J37: 3
E38: ILED | F38: =A17 -> E_SPV* | I38: =B17 -> 2 | J38: 3
E39: ILED | F39: =A19 -> E[_]WON* | I39: =B19 -> 3 | J39: 3

Sheet AFR
A1: =MID(CELL( "filename",A1),FIND("]",CELL( "filename",A1))+1,10) -> AFR | L1: 1 | M1: scaling
C2: ~UC_Sets: R_S: AllRegions
C3: ~UC_Sets: T_E:
H5: ="~UC_T: UC_RHST~LO~"&HistoricalBuilds!$N$1 -> ~UC_T: UC_RHST~LO~2019
C6: UC_N | D6: PSET_PN | E6: Pset_CI | F6: UC_ATTR | G6: LimType | H6: Attribute | I6: LHS | J6: UC_NCAP | K6: UC_NCAP~RHS | L6: UC_RHST | M6: UC_RHST~0 | N6: UC_Desc
C7: ="UELC-Bld_ELEWIN_"&$A$1 -> UELC-Bld_ELEWIN_AFR | D7: =VLOOKUP("1"&$A$1,'WEPSReg-Countrymap'!$D$2:$E$232,2,FALSE) -> *[_]AGO*,*[_]BDI*,*[_]BEN*,*[_]BFA*,*[_]BWA*,*[_]CAF*,*[_]CIV*,*[_]CMR*,*[_]COG*,*[_]COM*,*[_]CPV*,*[_]DJI*,*[_]DZA*,*[_]EGY*,*[_]ERI*,*[_]ETH*,*[_]GAB*,*[_]GHA*,*[_]GIN*,*[_]GMB*,*[_]GNB*,*[_]GNQ*,*[_]KEN*,*[_]LBR*,*[_]LBY*,*[_]LSO*,*[_]MAR*,*[_]MDG*,*[_]MLI*,*[_]MOZ*,*[_]MRT*,*[_]MUS*,*[_]MWI*,*[_]NAM*,*[_]NER*,*[_]NGA*,*[_]RWA*,*[_]SDN*,*[_]SEN*,*[_]SLE*,*[_]SOM*,*[_]SSD*,*[_]STP*,*[_]SWZ*,*[_]SYC*,*[_]TCD*,*[_]TGO*,*[_]TUN*,*[_]TZA*,*[_]UGA*,*[_]ZAF*,*[_]ZAR*,*[_]ZMB*,*[_]ZWE* | E7: ELCWIN | F7: NCAP,GROWTH | J7: 1.15 | K7: 1 | L7: 0 | M7: 5 | N7: ="Annual build rate (GW/Year) of ELEWIN_"&$A$1 -> Annual build rate (GW/Year) of ELEWIN_AFR
D8: ="EBldRateStep_Win_2_"&$A$1&",EBldRateStep_Win_3_"&$A$1 -> EBldRateStep_Win_2_AFR,EBldRateStep_Win_3_AFR | F8: ACT,NEWFLO | H8: UC_ACT | I8: 1
C9: ="UELC-Bld_ELEWIN-step2_"&$A$1 -> UELC-Bld_ELEWIN-step2_AFR | D9: =$D$7 -> *[_]AGO*,*[_]BDI*,*[_]BEN*,*[_]BFA*,*[_]BWA*,*[_]CAF*,*[_]CIV*,*[_]CMR*,*[_]COG*,*[_]COM*,*[_]CPV*,*[_]DJI*,*[_]DZA*,*[_]EGY*,*[_]ERI*,*[_]ETH*,*[_]GAB*,*[_]GHA*,*[_]GIN*,*[_]GMB*,*[_]GNB*,*[_]GNQ*,*[_]KEN*,*[_]LBR*,*[_]LBY*,*[_]LSO*,*[_]MAR*,*[_]MDG*,*[_]MLI*,*[_]MOZ*,*[_]MRT*,*[_]MUS*,*[_]MWI*,*[_]NAM*,*[_]NER*,*[_]NGA*,*[_]RWA*,*[_]SDN*,*[_]SEN*,*[_]SLE*,*[_]SOM*,*[_]SSD*,*[_]STP*,*[_]SWZ*,*[_]SYC*,*[_]TCD*,*[_]TGO*,*[_]TUN*,*[_]TZA*,*[_]UGA*,*[_]ZAF*,*[_]ZAR*,*[_]ZMB*,*[_]ZWE* | E9: ELCWIN | H9: UC_NCAP | I9: 0.85 | N9: ="step 2 relaxation of build rate - ELEWIN_"&$A$1 -> step 2 relaxation of build rate - ELEWIN_AFR
D10: ="EBldRateStep_Win_2_"&$A$1 -> EBldRateStep_Win_2_AFR | F10: ACT,NEWFLO | H10: UC_ACT | I10: -1 | L10: 0 | M10: 5
C11: ="UELC-Bld_ELEWIN-step3_"&$A$1 -> UELC-Bld_ELEWIN-step3_AFR | D11: =$D$7 -> *[_]AGO*,*[_]BDI*,*[_]BEN*,*[_]BFA*,*[_]BWA*,*[_]CAF*,*[_]CIV*,*[_]CMR*,*[_]COG*,*[_]COM*,*[_]CPV*,*[_]DJI*,*[_]DZA*,*[_]EGY*,*[_]ERI*,*[_]ETH*,*[_]GAB*,*[_]GHA*,*[_]GIN*,*[_]GMB*,*[_]GNB*,*[_]GNQ*,*[_]KEN*,*[_]LBR*,*[_]LBY*,*[_]LSO*,*[_]MAR*,*[_]MDG*,*[_]MLI*,*[_]MOZ*,*[_]MRT*,*[_]MUS*,*[_]MWI*,*[_]NAM*,*[_]NER*,*[_]NGA*,*[_]RWA*,*[_]SDN*,*[_]SEN*,*[_]SLE*,*[_]SOM*,*[_]SSD*,*[_]STP*,*[_]SWZ*,*[_]SYC*,*[_]TCD*,*[_]TGO*,*[_]TUN*,*[_]TZA*,*[_]UGA*,*[_]ZAF*,*[_]ZAR*,*[_]ZMB*,*[_]ZWE* | E11: ELCWIN | H11: UC_NCAP | I11: 1 | N11: ="step 3 relaxation of build rate - ELEWIN_"&$A$1 -> step 3 relaxation of build rate - ELEWIN_AFR
D12: ="EBldRateStep_Win_3_"&$A$1 -> EBldRateStep_Win_3_AFR | F12: ACT,NEWFLO | H12: UC_ACT | I12: -1 | L12: 0 | M12: 5
C13: ="UELC-Bld_ELESOL_"&$A$1 -> UELC-Bld_ELESOL_AFR | D13: =$D$7 -> *[_]AGO*,*[_]BDI*,*[_]BEN*,*[_]BFA*,*[_]BWA*,*[_]CAF*,*[_]CIV*,*[_]CMR*,*[_]COG*,*[_]COM*,*[_]CPV*,*[_]DJI*,*[_]DZA*,*[_]EGY*,*[_]ERI*,*[_]ETH*,*[_]GAB*,*[_]GHA*,*[_]GIN*,*[_]GMB*,*[_]GNB*,*[_]GNQ*,*[_]KEN*,*[_]LBR*,*[_]LBY*,*[_]LSO*,*[_]MAR*,*[_]MDG*,*[_]MLI*,*[_]MOZ*,*[_]MRT*,*[_]MUS*,*[_]MWI*,*[_]NAM*,*[_]NER*,*[_]NGA*,*[_]RWA*,*[_]SDN*,*[_]SEN*,*[_]SLE*,*[_]SOM*,*[_]SSD*,*[_]STP*,*[_]SWZ*,*[_]SYC*,*[_]TCD*,*[_]TGO*,*[_]TUN*,*[_]TZA*,*[_]UGA*,*[_]ZAF*,*[_]ZAR*,*[_]ZMB*,*[_]ZWE* | E13: ELCSOL | F13: NCAP,GROWTH | J13: 1.15 | K13: 1 | L13: 0 | M13: 5 | N13: ="Annual build rate (GW/Year) of ELESOL_"&$A$1 -> Annual build rate (GW/Year) of ELESOL_AFR
D14: ="EBldRateStep_Sol_2_"&$A$1&",EBldRateStep_Sol_3_"&$A$1 -> EBldRateStep_Sol_2_AFR,EBldRateStep_Sol_3_AFR | F14: ACT,NEWFLO | H14: UC_ACT | I14: 1
C15: ="UELC-Bld_ELESOL-step2_"&$A$1 -> UELC-Bld_ELESOL-step2_AFR | D15: =$D$7 -> *[_]AGO*,*[_]BDI*,*[_]BEN*,*[_]BFA*,*[_]BWA*,*[_]CAF*,*[_]CIV*,*[_]CMR*,*[_]COG*,*[_]COM*,*[_]CPV*,*[_]DJI*,*[_]DZA*,*[_]EGY*,*[_]ERI*,*[_]ETH*,*[_]GAB*,*[_]GHA*,*[_]GIN*,*[_]GMB*,*[_]GNB*,*[_]GNQ*,*[_]KEN*,*[_]LBR*,*[_]LBY*,*[_]LSO*,*[_]MAR*,*[_]MDG*,*[_]MLI*,*[_]MOZ*,*[_]MRT*,*[_]MUS*,*[_]MWI*,*[_]NAM*,*[_]NER*,*[_]NGA*,*[_]RWA*,*[_]SDN*,*[_]SEN*,*[_]SLE*,*[_]SOM*,*[_]SSD*,*[_]STP*,*[_]SWZ*,*[_]SYC*,*[_]TCD*,*[_]TGO*,*[_]TUN*,*[_]TZA*,*[_]UGA*,*[_]ZAF*,*[_]ZAR*,*[_]ZMB*,*[_]ZWE* | E15: ELCSOL | H15: UC_NCAP | I15: =I9 -> 0.85 | N15: ="step 2 relaxation of build rate - ELESOL_"&$A$1 -> step 2 relaxation of build rate - ELESOL_AFR
D16: ="EBldRateStep_Sol_2_"&$A$1 -> EBldRateStep_Sol_2_AFR | F16: ACT,NEWFLO | H16: UC_ACT | I16: -1 | L16: 0 | M16: 5
C17: ="UELC-Bld_ELESOL-step3_"&$A$1 -> UELC-Bld_ELESOL-step3_AFR | D17: =$D$7 -> *[_]AGO*,*[_]BDI*,*[_]BEN*,*[_]BFA*,*[_]BWA*,*[_]CAF*,*[_]CIV*,*[_]CMR*,*[_]COG*,*[_]COM*,*[_]CPV*,*[_]DJI*,*[_]DZA*,*[_]EGY*,*[_]ERI*,*[_]ETH*,*[_]GAB*,*[_]GHA*,*[_]GIN*,*[_]GMB*,*[_]GNB*,*[_]GNQ*,*[_]KEN*,*[_]LBR*,*[_]LBY*,*[_]LSO*,*[_]MAR*,*[_]MDG*,*[_]MLI*,*[_]MOZ*,*[_]MRT*,*[_]MUS*,*[_]MWI*,*[_]NAM*,*[_]NER*,*[_]NGA*,*[_]RWA*,*[_]SDN*,*[_]SEN*,*[_]SLE*,*[_]SOM*,*[_]SSD*,*[_]STP*,*[_]SWZ*,*[_]SYC*,*[_]TCD*,*[_]TGO*,*[_]TUN*,*[_]TZA*,*[_]UGA*,*[_]ZAF*,*[_]ZAR*,*[_]ZMB*,*[_]ZWE* | E17: ELCSOL | H17: UC_NCAP | I17: =I11 -> 1 | N17: ="step 3 relaxation of build rate - ELESOL_"&$A$1 -> step 3 relaxation of build rate - ELESOL_AFR
D18: ="EBldRateStep_Sol_3_"&$A$1 -> EBldRateStep_Sol_3_AFR | F18: ACT,NEWFLO | H18: UC_ACT | I18: -1 | L18: 0 | M18: 5
C19: ="UELC-Bld_ELEHYD_"&$A$1 -> UELC-Bld_ELEHYD_AFR | D19: =$D$7 -> *[_]AGO*,*[_]BDI*,*[_]BEN*,*[_]BFA*,*[_]BWA*,*[_]CAF*,*[_]CIV*,*[_]CMR*,*[_]COG*,*[_]COM*,*[_]CPV*,*[_]DJI*,*[_]DZA*,*[_]EGY*,*[_]ERI*,*[_]ETH*,*[_]GAB*,*[_]GHA*,*[_]GIN*,*[_]GMB*,*[_]GNB*,*[_]GNQ*,*[_]KEN*,*[_]LBR*,*[_]LBY*,*[_]LSO*,*[_]MAR*,*[_]MDG*,*[_]MLI*,*[_]MOZ*,*[_]MRT*,*[_]MUS*,*[_]MWI*,*[_]NAM*,*[_]NER*,*[_]NGA*,*[_]RWA*,*[_]SDN*,*[_]SEN*,*[_]SLE*,*[_]SOM*,*[_]SSD*,*[_]STP*,*[_]SWZ*,*[_]SYC*,*[_]TCD*,*[_]TGO*,*[_]TUN*,*[_]TZA*,*[_]UGA*,*[_]ZAF*,*[_]ZAR*,*[_]ZMB*,*[_]ZWE* | E19: ELCHYD | F19: NCAP,GROWTH | J19: 1.15 | K19: 1 | L19: 0 | M19: 5 | N19: ="Annual build rate (GW/Year) of ELEHYD_"&$A$1 -> Annual build rate (GW/Year) of ELEHYD_AFR
D20: ="EBldRateStep_Hyd_2_"&$A$1&",EBldRateStep_Hyd_3_"&$A$1 -> EBldRateStep_Hyd_2_AFR,EBldRateStep_Hyd_3_AFR | F20: ACT,NEWFLO | H20: UC_ACT | I20: 1
C21: ="UELC-Bld_ELEHYD-step2_"&$A$1 -> UELC-Bld_ELEHYD-step2_AFR | D21: =$D$7 -> *[_]AGO*,*[_]BDI*,*[_]BEN*,*[_]BFA*,*[_]BWA*,*[_]CAF*,*[_]CIV*,*[_]CMR*,*[_]COG*,*[_]COM*,*[_]CPV*,*[_]DJI*,*[_]DZA*,*[_]EGY*,*[_]ERI*,*[_]ETH*,*[_]GAB*,*[_]GHA*,*[_]GIN*,*[_]GMB*,*[_]GNB*,*[_]GNQ*,*[_]KEN*,*[_]LBR*,*[_]LBY*,*[_]LSO*,*[_]MAR*,*[_]MDG*,*[_]MLI*,*[_]MOZ*,*[_]MRT*,*[_]MUS*,*[_]MWI*,*[_]NAM*,*[_]NER*,*[_]NGA*,*[_]RWA*,*[_]SDN*,*[_]SEN*,*[_]SLE*,*[_]SOM*,*[_]SSD*,*[_]STP*,*[_]SWZ*,*[_]SYC*,*[_]TCD*,*[_]TGO*,*[_]TUN*,*[_]TZA*,*[_]UGA*,*[_]ZAF*,*[_]ZAR*,*[_]ZMB*,*[_]ZWE* | E21: ELCHYD | H21: UC_NCAP | I21: =I15 -> 0.85 | N21: ="step 2 relaxation of build rate - ELEHYD_"&$A$1 -> step 2 relaxation of build rate - ELEHYD_AFR
D22: ="EBldRateStep_Hyd_2_"&$A$1 -> EBldRateStep_Hyd_2_AFR | F22: ACT,NEWFLO | H22: UC_ACT | I22: -1 | L22: 0 | M22: 5
C23: ="UELC-Bld_ELEHYD-step3_"&$A$1 -> UELC-Bld_ELEHYD-step3_AFR | D23: =$D$7 -> *[_]AGO*,*[_]BDI*,*[_]BEN*,*[_]BFA*,*[_]BWA*,*[_]CAF*,*[_]CIV*,*[_]CMR*,*[_]COG*,*[_]COM*,*[_]CPV*,*[_]DJI*,*[_]DZA*,*[_]EGY*,*[_]ERI*,*[_]ETH*,*[_]GAB*,*[_]GHA*,*[_]GIN*,*[_]GMB*,*[_]GNB*,*[_]GNQ*,*[_]KEN*,*[_]LBR*,*[_]LBY*,*[_]LSO*,*[_]MAR*,*[_]MDG*,*[_]MLI*,*[_]MOZ*,*[_]MRT*,*[_]MUS*,*[_]MWI*,*[_]NAM*,*[_]NER*,*[_]NGA*,*[_]RWA*,*[_]SDN*,*[_]SEN*,*[_]SLE*,*[_]SOM*,*[_]SSD*,*[_]STP*,*[_]SWZ*,*[_]SYC*,*[_]TCD*,*[_]TGO*,*[_]TUN*,*[_]TZA*,*[_]UGA*,*[_]ZAF*,*[_]ZAR*,*[_]ZMB*,*[_]ZWE* | E23: ELCHYD | H23: UC_NCAP | I23: =I17 -> 1 | N23: ="step 3 relaxation of build rate - ELEHYD_"&$A$1 -> step 3 relaxation of build rate - ELEHYD_AFR
D24: ="EBldRateStep_Hyd_3_"&$A$1 -> EBldRateStep_Hyd_3_AFR | F24: ACT,NEWFLO | H24: UC_ACT | I24: -1 | L24: 0 | M24: 5
A25: wn | C25: ="UELC-Inv"&RIGHT(HistoricalBuilds!$N$1,2)&"_"&A25&"_"&$A$1 -> UELC-Inv19_wn_AFR | D25: =$D$7 -> *[_]AGO*,*[_]BDI*,*[_]BEN*,*[_]BFA*,*[_]BWA*,*[_]CAF*,*[_]CIV*,*[_]CMR*,*[_]COG*,*[_]COM*,*[_]CPV*,*[_]DJI*,*[_]DZA*,*[_]EGY*,*[_]ERI*,*[_]ETH*,*[_]GAB*,*[_]GHA*,*[_]GIN*,*[_]GMB*,*[_]GNB*,*[_]GNQ*,*[_]KEN*,*[_]LBR*,*[_]LBY*,*[_]LSO*,*[_]MAR*,*[_]MDG*,*[_]MLI*,*[_]MOZ*,*[_]MRT*,*[_]MUS*,*[_]MWI*,*[_]NAM*,*[_]NER*,*[_]NGA*,*[_]RWA*,*[_]SDN*,*[_]SEN*,*[_]SLE*,*[_]SOM*,*[_]SSD*,*[_]STP*,*[_]SWZ*,*[_]SYC*,*[_]TCD*,*[_]TGO*,*[_]TUN*,*[_]TZA*,*[_]UGA*,*[_]ZAF*,*[_]ZAR*,*[_]ZMB*,*[_]ZWE* | E25: ELCWIN | G25: UP | J25: 1 | L25: =SUMIFS(HistoricalBuilds!$C$2:$C$300,HistoricalBuilds!$A$2:$A$300,AFR!A$1,HistoricalBuilds!$B$2:$B$300,AFR!$A25)*$L$1 -> 0.920831 | M25: 4
A26: sl | C26: ="UELC-Inv"&RIGHT(HistoricalBuilds!$N$1,2)&"_"&A26&"_"&$A$1 -> UELC-Inv19_sl_AFR | D26: =$D$7 -> *[_]AGO*,*[_]BDI*,*[_]BEN*,*[_]BFA*,*[_]BWA*,*[_]CAF*,*[_]CIV*,*[_]CMR*,*[_]COG*,*[_]COM*,*[_]CPV*,*[_]DJI*,*[_]DZA*,*[_]EGY*,*[_]ERI*,*[_]ETH*,*[_]GAB*,*[_]GHA*,*[_]GIN*,*[_]GMB*,*[_]GNB*,*[_]GNQ*,*[_]KEN*,*[_]LBR*,*[_]LBY*,*[_]LSO*,*[_]MAR*,*[_]MDG*,*[_]MLI*,*[_]MOZ*,*[_]MRT*,*[_]MUS*,*[_]MWI*,*[_]NAM*,*[_]NER*,*[_]NGA*,*[_]RWA*,*[_]SDN*,*[_]SEN*,*[_]SLE*,*[_]SOM*,*[_]SSD*,*[_]STP*,*[_]SWZ*,*[_]SYC*,*[_]TCD*,*[_]TGO*,*[_]TUN*,*[_]TZA*,*[_]UGA*,*[_]ZAF*,*[_]ZAR*,*[_]ZMB*,*[_]ZWE* | E26: ELCSOL | G26: UP | J26: 1 | L26: =SUMIFS(HistoricalBuilds!$C$2:$C$300,HistoricalBuilds!$A$2:$A$300,AFR!A$1,HistoricalBuilds!$B$2:$B$300,AFR!$A26)*$L$1 -> 1.872644 | M26: 4
A27: he | C27: ="UELC-Inv"&RIGHT(HistoricalBuilds!$N$1,2)&"_"&A27&"_"&$A$1 -> UELC-Inv19_he_AFR | D27: =$D$7 -> *[_]AGO*,*[_]BDI*,*[_]BEN*,*[_]BFA*,*[_]BWA*,*[_]CAF*,*[_]CIV*,*[_]CMR*,*[_]COG*,*[_]COM*,*[_]CPV*,*[_]DJI*,*[_]DZA*,*[_]EGY*,*[_]ERI*,*[_]ETH*,*[_]GAB*,*[_]GHA*,*[_]GIN*,*[_]GMB*,*[_]GNB*,*[_]GNQ*,*[_]KEN*,*[_]LBR*,*[_]LBY*,*[_]LSO*,*[_]MAR*,*[_]MDG*,*[_]MLI*,*[_]MOZ*,*[_]MRT*,*[_]MUS*,*[_]MWI*,*[_]NAM*,*[_]NER*,*[_]NGA*,*[_]RWA*,*[_]SDN*,*[_]SEN*,*[_]SLE*,*[_]SOM*,*[_]SSD*,*[_]STP*,*[_]SWZ*,*[_]SYC*,*[_]TCD*,*[_]TGO*,*[_]TUN*,*[_]TZA*,*[_]UGA*,*[_]ZAF*,*[_]ZAR*,*[_]ZMB*,*[_]ZWE* | E27: ELCHYD | G27: UP | J27: 1 | L27: =SUMIFS(HistoricalBuilds!$C$2:$C$300,HistoricalBuilds!$A$2:$A$300,AFR!A$1,HistoricalBuilds!$B$2:$B$300,AFR!$A27)*$L$1 -> 4.125 | M27: 4

Sheet CSA
A1: =MID(CELL( "filename",A1),FIND("]",CELL( "filename",A1))+1,10) -> CSA | L1: =AFR!$L$1 -> 1
C2: ~UC_Sets: R_S: AllRegions
C3: ~UC_Sets: T_E:
H5: ="~UC_T: UC_RHST~LO~"&HistoricalBuilds!$N$1 -> ~UC_T: UC_RHST~LO~2019
C6: UC_N | D6: PSET_PN | E6: Pset_CI | F6: UC_ATTR | G6: LimType | H6: Attribute | I6: LHS | J6: UC_NCAP | K6: UC_NCAP~RHS | L6: UC_RHST | M6: UC_RHST~0 | N6: UC_Desc
C7: ="UELC-Bld_ELEWIN_"&$A$1 -> UELC-Bld_ELEWIN_CSA | D7: =VLOOKUP("1"&$A$1,'WEPSReg-Countrymap'!$D$2:$E$232,2,FALSE) -> *[_]ABW*,*[_]ANT*,*[_]ARG*,*[_]ATG*,*[_]BHS*,*[_]BLZ*,*[_]BMU*,*[_]BOL*,*[_]BRB*,*[_]CHL*,*[_]CRI*,*[_]CUB*,*[_]CUW*,*[_]CYM*,*[_]DMA*,*[_]DOM*,*[_]ECU*,*[_]GRD*,*[_]GTM*,*[_]GUF*,*[_]GUY*,*[_]HND*,*[_]HTI*,*[_]JAM*,*[_]KNA*,*[_]LCA*,*[_]MAF*,*[_]MSR*,*[_]NIC*,*[_]PAN*,*[_]PER*,*[_]PRY*,*[_]SLV*,*[_]SUR*,*[_]SXM*,*[_]TCA*,*[_]TTO*,*[_]URY*,*[_]VCT*,*[_]VEN*,*[_]PRI*,*[_]VIR*,*[_]CHL*,*[_]COL* | E7: ELCWIN | F7: NCAP,GROWTH | J7: 1.15 | K7: 1 | L7: 0 | M7: 5 | N7: ="Annual build rate (GW/Year) of ELEWIN_"&$A$1 -> Annual build rate (GW/Year) of ELEWIN_CSA
D8: ="EBldRateStep_Win_2_"&$A$1&",EBldRateStep_Win_3_"&$A$1 -> EBldRateStep_Win_2_CSA,EBldRateStep_Win_3_CSA | F8: ACT,NEWFLO | H8: UC_ACT | I8: 1
C9: ="UELC-Bld_ELEWIN-step2_"&$A$1 -> UELC-Bld_ELEWIN-step2_CSA | D9: =$D$7 -> *[_]ABW*,*[_]ANT*,*[_]ARG*,*[_]ATG*,*[_]BHS*,*[_]BLZ*,*[_]BMU*,*[_]BOL*,*[_]BRB*,*[_]CHL*,*[_]CRI*,*[_]CUB*,*[_]CUW*,*[_]CYM*,*[_]DMA*,*[_]DOM*,*[_]ECU*,*[_]GRD*,*[_]GTM*,*[_]GUF*,*[_]GUY*,*[_]HND*,*[_]HTI*,*[_]JAM*,*[_]KNA*,*[_]LCA*,*[_]MAF*,*[_]MSR*,*[_]NIC*,*[_]PAN*,*[_]PER*,*[_]PRY*,*[_]SLV*,*[_]SUR*,*[_]SXM*,*[_]TCA*,*[_]TTO*,*[_]URY*,*[_]VCT*,*[_]VEN*,*[_]PRI*,*[_]VIR*,*[_]CHL*,*[_]COL* | E9: ELCWIN | H9: UC_NCAP | I9: 0.85 | N9: ="step 2 relaxation of build rate - ELEWIN_"&$A$1 -> step 2 relaxation of build rate - ELEWIN_CSA
D10: ="EBldRateStep_Win_2_"&$A$1 -> EBldRateStep_Win_2_CSA | F10: ACT,NEWFLO | H10: UC_ACT | I10: -1 | L10: 0 | M10: 5
C11: ="UELC-Bld_ELEWIN-step3_"&$A$1 -> UELC-Bld_ELEWIN-step3_CSA | D11: =$D$7 -> *[_]ABW*,*[_]ANT*,*[_]ARG*,*[_]ATG*,*[_]BHS*,*[_]BLZ*,*[_]BMU*,*[_]BOL*,*[_]BRB*,*[_]CHL*,*[_]CRI*,*[_]CUB*,*[_]CUW*,*[_]CYM*,*[_]DMA*,*[_]DOM*,*[_]ECU*,*[_]GRD*,*[_]GTM*,*[_]GUF*,*[_]GUY*,*[_]HND*,*[_]HTI*,*[_]JAM*,*[_]KNA*,*[_]LCA*,*[_]MAF*,*[_]MSR*,*[_]NIC*,*[_]PAN*,*[_]PER*,*[_]PRY*,*[_]SLV*,*[_]SUR*,*[_]SXM*,*[_]TCA*,*[_]TTO*,*[_]URY*,*[_]VCT*,*[_]VEN*,*[_]PRI*,*[_]VIR*,*[_]CHL*,*[_]COL* | E11: ELCWIN | H11: UC_NCAP | I11: 1 | N11: ="step 3 relaxation of build rate - ELEWIN_"&$A$1 -> step 3 relaxation of build rate - ELEWIN_CSA
D12: ="EBldRateStep_Win_3_"&$A$1 -> EBldRateStep_Win_3_CSA | F12: ACT,NEWFLO | H12: UC_ACT | I12: -1 | L12: 0 | M12: 5
C13: ="UELC-Bld_ELESOL_"&$A$1 -> UELC-Bld_ELESOL_CSA | D13: =$D$7 -> *[_]ABW*,*[_]ANT*,*[_]ARG*,*[_]ATG*,*[_]BHS*,*[_]BLZ*,*[_]BMU*,*[_]BOL*,*[_]BRB*,*[_]CHL*,*[_]CRI*,*[_]CUB*,*[_]CUW*,*[_]CYM*,*[_]DMA*,*[_]DOM*,*[_]ECU*,*[_]GRD*,*[_]GTM*,*[_]GUF*,*[_]GUY*,*[_]HND*,*[_]HTI*,*[_]JAM*,*[_]KNA*,*[_]LCA*,*[_]MAF*,*[_]MSR*,*[_]NIC*,*[_]PAN*,*[_]PER*,*[_]PRY*,*[_]SLV*,*[_]SUR*,*[_]SXM*,*[_]TCA*,*[_]TTO*,*[_]URY*,*[_]VCT*,*[_]VEN*,*[_]PRI*,*[_]VIR*,*[_]CHL*,*[_]COL* | E13: ELCSOL | F13: NCAP,GROWTH | J13: 1.15 | K13: 1 | L13: 0 | M13: 5 | N13: ="Annual build rate (GW/Year) of ELESOL_"&$A$1 -> Annual build rate (GW/Year) of ELESOL_CSA
D14: ="EBldRateStep_Sol_2_"&$A$1&",EBldRateStep_Sol_3_"&$A$1 -> EBldRateStep_Sol_2_CSA,EBldRateStep_Sol_3_CSA | F14: ACT,NEWFLO | H14: UC_ACT | I14: 1
C15: ="UELC-Bld_ELESOL-step2_"&$A$1 -> UELC-Bld_ELESOL-step2_CSA | D15: =$D$7 -> *[_]ABW*,*[_]ANT*,*[_]ARG*,*[_]ATG*,*[_]BHS*,*[_]BLZ*,*[_]BMU*,*[_]BOL*,*[_]BRB*,*[_]CHL*,*[_]CRI*,*[_]CUB*,*[_]CUW*,*[_]CYM*,*[_]DMA*,*[_]DOM*,*[_]ECU*,*[_]GRD*,*[_]GTM*,*[_]GUF*,*[_]GUY*,*[_]HND*,*[_]HTI*,*[_]JAM*,*[_]KNA*,*[_]LCA*,*[_]MAF*,*[_]MSR*,*[_]NIC*,*[_]PAN*,*[_]PER*,*[_]PRY*,*[_]SLV*,*[_]SUR*,*[_]SXM*,*[_]TCA*,*[_]TTO*,*[_]URY*,*[_]VCT*,*[_]VEN*,*[_]PRI*,*[_]VIR*,*[_]CHL*,*[_]COL* | E15: ELCSOL | H15: UC_NCAP | I15: =I9 -> 0.85 | N15: ="step 2 relaxation of build rate - ELESOL_"&$A$1 -> step 2 relaxation of build rate - ELESOL_CSA
D16: ="EBldRateStep_Sol_2_"&$A$1 -> EBldRateStep_Sol_2_CSA | F16: ACT,NEWFLO | H16: UC_ACT | I16: -1 | L16: 0 | M16: 5
C17: ="UELC-Bld_ELESOL-step3_"&$A$1 -> UELC-Bld_ELESOL-step3_CSA | D17: =$D$7 -> *[_]ABW*,*[_]ANT*,*[_]ARG*,*[_]ATG*,*[_]BHS*,*[_]BLZ*,*[_]BMU*,*[_]BOL*,*[_]BRB*,*[_]CHL*,*[_]CRI*,*[_]CUB*,*[_]CUW*,*[_]CYM*,*[_]DMA*,*[_]DOM*,*[_]ECU*,*[_]GRD*,*[_]GTM*,*[_]GUF*,*[_]GUY*,*[_]HND*,*[_]HTI*,*[_]JAM*,*[_]KNA*,*[_]LCA*,*[_]MAF*,*[_]MSR*,*[_]NIC*,*[_]PAN*,*[_]PER*,*[_]PRY*,*[_]SLV*,*[_]SUR*,*[_]SXM*,*[_]TCA*,*[_]TTO*,*[_]URY*,*[_]VCT*,*[_]VEN*,*[_]PRI*,*[_]VIR*,*[_]CHL*,*[_]COL* | E17: ELCSOL | H17: UC_NCAP | I17: =I11 -> 1 | N17: ="step 3 relaxation of build rate - ELESOL_"&$A$1 -> step 3 relaxation of build rate - ELESOL_CSA
D18: ="EBldRateStep_Sol_3_"&$A$1 -> EBldRateStep_Sol_3_CSA | F18: ACT,NEWFLO | H18: UC_ACT | I18: -1 | L18: 0 | M18: 5
C19: ="UELC-Bld_ELEHYD_"&$A$1 -> UELC-Bld_ELEHYD_CSA | D19: =$D$7 -> *[_]ABW*,*[_]ANT*,*[_]ARG*,*[_]ATG*,*[_]BHS*,*[_]BLZ*,*[_]BMU*,*[_]BOL*,*[_]BRB*,*[_]CHL*,*[_]CRI*,*[_]CUB*,*[_]CUW*,*[_]CYM*,*[_]DMA*,*[_]DOM*,*[_]ECU*,*[_]GRD*,*[_]GTM*,*[_]GUF*,*[_]GUY*,*[_]HND*,*[_]HTI*,*[_]JAM*,*[_]KNA*,*[_]LCA*,*[_]MAF*,*[_]MSR*,*[_]NIC*,*[_]PAN*,*[_]PER*,*[_]PRY*,*[_]SLV*,*[_]SUR*,*[_]SXM*,*[_]TCA*,*[_]TTO*,*[_]URY*,*[_]VCT*,*[_]VEN*,*[_]PRI*,*[_]VIR*,*[_]CHL*,*[_]COL* | E19: ELCHYD | F19: NCAP,GROWTH | J19: 1.15 | K19: 1 | L19: 0 | M19: 5 | N19: ="Annual build rate (GW/Year) of ELEHYD_"&$A$1 -> Annual build rate (GW/Year) of ELEHYD_CSA
D20: ="EBldRateStep_Hyd_2_"&$A$1&",EBldRateStep_Hyd_3_"&$A$1 -> EBldRateStep_Hyd_2_CSA,EBldRateStep_Hyd_3_CSA | F20: ACT,NEWFLO | H20: UC_ACT | I20: 1
C21: ="UELC-Bld_ELEHYD-step2_"&$A$1 -> UELC-Bld_ELEHYD-step2_CSA | D21: =$D$7 -> *[_]ABW*,*[_]ANT*,*[_]ARG*,*[_]ATG*,*[_]BHS*,*[_]BLZ*,*[_]BMU*,*[_]BOL*,*[_]BRB*,*[_]CHL*,*[_]CRI*,*[_]CUB*,*[_]CUW*,*[_]CYM*,*[_]DMA*,*[_]DOM*,*[_]ECU*,*[_]GRD*,*[_]GTM*,*[_]GUF*,*[_]GUY*,*[_]HND*,*[_]HTI*,*[_]JAM*,*[_]KNA*,*[_]LCA*,*[_]MAF*,*[_]MSR*,*[_]NIC*,*[_]PAN*,*[_]PER*,*[_]PRY*,*[_]SLV*,*[_]SUR*,*[_]SXM*,*[_]TCA*,*[_]TTO*,*[_]URY*,*[_]VCT*,*[_]VEN*,*[_]PRI*,*[_]VIR*,*[_]CHL*,*[_]COL* | E21: ELCHYD | H21: UC_NCAP | I21: =I15 -> 0.85 | N21: ="step 2 relaxation of build rate - ELEHYD_"&$A$1 -> step 2 relaxation of build rate - ELEHYD_CSA
D22: ="EBldRateStep_Hyd_2_"&$A$1 -> EBldRateStep_Hyd_2_CSA | F22: ACT,NEWFLO | H22: UC_ACT | I22: -1 | L22: 0 | M22: 5
C23: ="UELC-Bld_ELEHYD-step3_"&$A$1 -> UELC-Bld_ELEHYD-step3_CSA | D23: =$D$7 -> *[_]ABW*,*[_]ANT*,*[_]ARG*,*[_]ATG*,*[_]BHS*,*[_]BLZ*,*[_]BMU*,*[_]BOL*,*[_]BRB*,*[_]CHL*,*[_]CRI*,*[_]CUB*,*[_]CUW*,*[_]CYM*,*[_]DMA*,*[_]DOM*,*[_]ECU*,*[_]GRD*,*[_]GTM*,*[_]GUF*,*[_]GUY*,*[_]HND*,*[_]HTI*,*[_]JAM*,*[_]KNA*,*[_]LCA*,*[_]MAF*,*[_]MSR*,*[_]NIC*,*[_]PAN*,*[_]PER*,*[_]PRY*,*[_]SLV*,*[_]SUR*,*[_]SXM*,*[_]TCA*,*[_]TTO*,*[_]URY*,*[_]VCT*,*[_]VEN*,*[_]PRI*,*[_]VIR*,*[_]CHL*,*[_]COL* | E23: ELCHYD | H23: UC_NCAP | I23: =I17 -> 1 | N23: ="step 3 relaxation of build rate - ELEHYD_"&$A$1 -> step 3 relaxation of build rate - ELEHYD_CSA
D24: ="EBldRateStep_Hyd_3_"&$A$1 -> EBldRateStep_Hyd_3_CSA | F24: ACT,NEWFLO | H24: UC_ACT | I24: -1 | L24: 0 | M24: 5
A25: wn | C25: ="UELC-Inv"&RIGHT(HistoricalBuilds!$N$1,2)&"_"&A25&"_"&$A$1 -> UELC-Inv19_wn_CSA | D25: =$D$7 -> *[_]ABW*,*[_]ANT*,*[_]ARG*,*[_]ATG*,*[_]BHS*,*[_]BLZ*,*[_]BMU*,*[_]BOL*,*[_]BRB*,*[_]CHL*,*[_]CRI*,*[_]CUB*,*[_]CUW*,*[_]CYM*,*[_]DMA*,*[_]DOM*,*[_]ECU*,*[_]GRD*,*[_]GTM*,*[_]GUF*,*[_]GUY*,*[_]HND*,*[_]HTI*,*[_]JAM*,*[_]KNA*,*[_]LCA*,*[_]MAF*,*[_]MSR*,*[_]NIC*,*[_]PAN*,*[_]PER*,*[_]PRY*,*[_]SLV*,*[_]SUR*,*[_]SXM*,*[_]TCA*,*[_]TTO*,*[_]URY*,*[_]VCT*,*[_]VEN*,*[_]PRI*,*[_]VIR*,*[_]CHL*,*[_]COL* | E25: ELCWIN | G25: UP | J25: 1 | L25: =SUMIFS(HistoricalBuilds!$C$2:$C$300,HistoricalBuilds!$A$2:$A$300,CSA!A$1,HistoricalBuilds!$B$2:$B$300,CSA!$A25)*$L$1 -> 0.8457 | M25: 4
A26: sl | C26: ="UELC-Inv"&RIGHT(HistoricalBuilds!$N$1,2)&"_"&A26&"_"&$A$1 -> UELC-Inv19_sl_CSA | D26: =$D$7 -> *[_]ABW*,*[_]ANT*,*[_]ARG*,*[_]ATG*,*[_]BHS*,*[_]BLZ*,*[_]BMU*,*[_]BOL*,*[_]BRB*,*[_]CHL*,*[_]CRI*,*[_]CUB*,*[_]CUW*,*[_]CYM*,*[_]DMA*,*[_]DOM*,*[_]ECU*,*[_]GRD*,*[_]GTM*,*[_]GUF*,*[_]GUY*,*[_]HND*,*[_]HTI*,*[_]JAM*,*[_]KNA*,*[_]LCA*,*[_]MAF*,*[_]MSR*,*[_]NIC*,*[_]PAN*,*[_]PER*,*[_]PRY*,*[_]SLV*,*[_]SUR*,*[_]SXM*,*[_]TCA*,*[_]TTO*,*[_]URY*,*[_]VCT*,*[_]VEN*,*[_]PRI*,*[_]VIR*,*[_]CHL*,*[_]COL* | E26: ELCSOL | G26: UP | J26: 1 | L26: =SUMIFS(HistoricalBuilds!$C$2:$C$300,HistoricalBuilds!$A$2:$A$300,CSA!A$1,HistoricalBuilds!$B$2:$B$300,CSA!$A26)*$L$1 -> 0.724019 | M26: 4
A27: he | C27: ="UELC-Inv"&RIGHT(HistoricalBuilds!$N$1,2)&"_"&A27&"_"&$A$1 -> UELC-Inv19_he_CSA | D27: =$D$7 -> *[_]ABW*,*[_]ANT*,*[_]ARG*,*[_]ATG*,*[_]BHS*,*[_]BLZ*,*[_]BMU*,*[_]BOL*,*[_]BRB*,*[_]CHL*,*[_]CRI*,*[_]CUB*,*[_]CUW*,*[_]CYM*,*[_]DMA*,*[_]DOM*,*[_]ECU*,*[_]GRD*,*[_]GTM*,*[_]GUF*,*[_]GUY*,*[_]HND*,*[_]HTI*,*[_]JAM*,*[_]KNA*,*[_]LCA*,*[_]MAF*,*[_]MSR*,*[_]NIC*,*[_]PAN*,*[_]PER*,*[_]PRY*,*[_]SLV*,*[_]SUR*,*[_]SXM*,*[_]TCA*,*[_]TTO*,*[_]URY*,*[_]VCT*,*[_]VEN*,*[_]PRI*,*[_]VIR*,*[_]CHL*,*[_]COL* | E27: ELCHYD | G27: UP | J27: 1 | L27: =SUMIFS(HistoricalBuilds!$C$2:$C$300,HistoricalBuilds!$A$2:$A$300,CSA!A$1,HistoricalBuilds!$B$2:$B$300,CSA!$A27)*$L$1 -> 4.403 | M27: 4

Sheet EUR
A1: =MID(CELL( "filename",A1),FIND("]",CELL( "filename",A1))+1,10) -> EUR | L1: =AFR!$L$1 -> 1
C2: ~UC_Sets: R_S: AllRegions
C3: ~UC_Sets: T_E:
H5: ="~UC_T: UC_RHST~LO~"&HistoricalBuilds!$N$1 -> ~UC_T: UC_RHST~LO~2019
C6: UC_N | D6: PSET_PN | E6: Pset_CI | F6: UC_ATTR | G6: LimType | H6: Attribute | I6: LHS | J6: UC_NCAP | K6: UC_NCAP~RHS | L6: UC_RHST | M6: UC_RHST~0 | N6: UC_Desc
C7: ="UELC-Bld_ELEWIN_"&$A$1 -> UELC-Bld_ELEWIN_EUR | D7: =VLOOKUP("1"&$A$1,'WEPSReg-Countrymap'!$D$2:$E$232,2,FALSE) -> *[_]ADO*,*[_]AUT*,*[_]BEL*,*[_]CHE*,*[_]CZE*,*[_]DEU*,*[_]DNK*,*[_]ESP*,*[_]EST*,*[_]FIN*,*[_]FRA*,*[_]GBR*,*[_]GIB*,*[_]GRC*,*[_]GRL*,*[_]HUN*,*[_]IMY*,*[_]IRL*,*[_]ISL*,*[_]ISR*,*[_]ITA*,*[_]LUX*,*[_]MCO*,*[_]NLD*,*[_]NOR*,*[_]POL*,*[_]PRT*,*[_]SMR*,*[_]SVK*,*[_]SVN*,*[_]SWE*,*[_]TUR*,*[_]VAT* | E7: ELCWIN | F7: NCAP,GROWTH | J7: 1.15 | K7: 1 | L7: 0 | M7: 5 | N7: ="Annual build rate (GW/Year) of ELEWIN_"&$A$1 -> Annual build rate (GW/Year) of ELEWIN_EUR
D8: ="EBldRateStep_Win_2_"&$A$1&",EBldRateStep_Win_3_"&$A$1 -> EBldRateStep_Win_2_EUR,EBldRateStep_Win_3_EUR | F8: ACT,NEWFLO | H8: UC_ACT | I8: 1
C9: ="UELC-Bld_ELEWIN-step2_"&$A$1 -> UELC-Bld_ELEWIN-step2_EUR | D9: =$D$7 -> *[_]ADO*,*[_]AUT*,*[_]BEL*,*[_]CHE*,*[_]CZE*,*[_]DEU*,*[_]DNK*,*[_]ESP*,*[_]EST*,*[_]FIN*,*[_]FRA*,*[_]GBR*,*[_]GIB*,*[_]GRC*,*[_]GRL*,*[_]HUN*,*[_]IMY*,*[_]IRL*,*[_]ISL*,*[_]ISR*,*[_]ITA*,*[_]LUX*,*[_]MCO*,*[_]NLD*,*[_]NOR*,*[_]POL*,*[_]PRT*,*[_]SMR*,*[_]SVK*,*[_]SVN*,*[_]SWE*,*[_]TUR*,*[_]VAT* | E9: ELCWIN | H9: UC_NCAP | I9: 0.85 | N9: ="step 2 relaxation of build rate - ELEWIN_"&$A$1 -> step 2 relaxation of build rate - ELEWIN_EUR
D10: ="EBldRateStep_Win_2_"&$A$1 -> EBldRateStep_Win_2_EUR | F10: ACT,NEWFLO | H10: UC_ACT | I10: -1 | L10: 0 | M10: 5
C11: ="UELC-Bld_ELEWIN-step3_"&$A$1 -> UELC-Bld_ELEWIN-step3_EUR | D11: =$D$7 -> *[_]ADO*,*[_]AUT*,*[_]BEL*,*[_]CHE*,*[_]CZE*,*[_]DEU*,*[_]DNK*,*[_]ESP*,*[_]EST*,*[_]FIN*,*[_]FRA*,*[_]GBR*,*[_]GIB*,*[_]GRC*,*[_]GRL*,*[_]HUN*,*[_]IMY*,*[_]IRL*,*[_]ISL*,*[_]ISR*,*[_]ITA*,*[_]LUX*,*[_]MCO*,*[_]NLD*,*[_]NOR*,*[_]POL*,*[_]PRT*,*[_]SMR*,*[_]SVK*,*[_]SVN*,*[_]SWE*,*[_]TUR*,*[_]VAT* | E11: ELCWIN | H11: UC_NCAP | I11: 1 | N11: ="step 3 relaxation of build rate - ELEWIN_"&$A$1 -> step 3 relaxation of build rate - ELEWIN_EUR
D12: ="EBldRateStep_Win_3_"&$A$1 -> EBldRateStep_Win_3_EUR | F12: ACT,NEWFLO | H12: UC_ACT | I12: -1 | L12: 0 | M12: 5
C13: ="UELC-Bld_ELESOL_"&$A$1 -> UELC-Bld_ELESOL_EUR | D13: =$D$7 -> *[_]ADO*,*[_]AUT*,*[_]BEL*,*[_]CHE*,*[_]CZE*,*[_]DEU*,*[_]DNK*,*[_]ESP*,*[_]EST*,*[_]FIN*,*[_]FRA*,*[_]GBR*,*[_]GIB*,*[_]GRC*,*[_]GRL*,*[_]HUN*,*[_]IMY*,*[_]IRL*,*[_]ISL*,*[_]ISR*,*[_]ITA*,*[_]LUX*,*[_]MCO*,*[_]NLD*,*[_]NOR*,*[_]POL*,*[_]PRT*,*[_]SMR*,*[_]SVK*,*[_]SVN*,*[_]SWE*,*[_]TUR*,*[_]VAT* | E13: ELCSOL | F13: NCAP,GROWTH | J13: 1.15 | K13: 1 | L13: 0 | M13: 5 | N13: ="Annual build rate (GW/Year) of ELESOL_"&$A$1 -> Annual build rate (GW/Year) of ELESOL_EUR
D14: ="EBldRateStep_Sol_2_"&$A$1&",EBldRateStep_Sol_3_"&$A$1 -> EBldRateStep_Sol_2_EUR,EBldRateStep_Sol_3_EUR | F14: ACT,NEWFLO | H14: UC_ACT | I14: 1
C15: ="UELC-Bld_ELESOL-step2_"&$A$1 -> UELC-Bld_ELESOL-step2_EUR | D15: =$D$7 -> *[_]ADO*,*[_]AUT*,*[_]BEL*,*[_]CHE*,*[_]CZE*,*[_]DEU*,*[_]DNK*,*[_]ESP*,*[_]EST*,*[_]FIN*,*[_]FRA*,*[_]GBR*,*[_]GIB*,*[_]GRC*,*[_]GRL*,*[_]HUN*,*[_]IMY*,*[_]IRL*,*[_]ISL*,*[_]ISR*,*[_]ITA*,*[_]LUX*,*[_]MCO*,*[_]NLD*,*[_]NOR*,*[_]POL*,*[_]PRT*,*[_]SMR*,*[_]SVK*,*[_]SVN*,*[_]SWE*,*[_]TUR*,*[_]VAT* | E15: ELCSOL | H15: UC_NCAP | I15: =I9 -> 0.85 | N15: ="step 2 relaxation of build rate - ELESOL_"&$A$1 -> step 2 relaxation of build rate - ELESOL_EUR
D16: ="EBldRateStep_Sol_2_"&$A$1 -> EBldRateStep_Sol_2_EUR | F16: ACT,NEWFLO | H16: UC_ACT | I16: -1 | L16: 0 | M16: 5
C17: ="UELC-Bld_ELESOL-step3_"&$A$1 -> UELC-Bld_ELESOL-step3_EUR | D17: =$D$7 -> *[_]ADO*,*[_]AUT*,*[_]BEL*,*[_]CHE*,*[_]CZE*,*[_]DEU*,*[_]DNK*,*[_]ESP*,*[_]EST*,*[_]FIN*,*[_]FRA*,*[_]GBR*,*[_]GIB*,*[_]GRC*,*[_]GRL*,*[_]HUN*,*[_]IMY*,*[_]IRL*,*[_]ISL*,*[_]ISR*,*[_]ITA*,*[_]LUX*,*[_]MCO*,*[_]NLD*,*[_]NOR*,*[_]POL*,*[_]PRT*,*[_]SMR*,*[_]SVK*,*[_]SVN*,*[_]SWE*,*[_]TUR*,*[_]VAT* | E17: ELCSOL | H17: UC_NCAP | I17: =I11 -> 1 | N17: ="step 3 relaxation of build rate - ELESOL_"&$A$1 -> step 3 relaxation of build rate - ELESOL_EUR
D18: ="EBldRateStep_Sol_3_"&$A$1 -> EBldRateStep_Sol_3_EUR | F18: ACT,NEWFLO | H18: UC_ACT | I18: -1 | L18: 0 | M18: 5
C19: ="UELC-Bld_ELEHYD_"&$A$1 -> UELC-Bld_ELEHYD_EUR | D19: =$D$7 -> *[_]ADO*,*[_]AUT*,*[_]BEL*,*[_]CHE*,*[_]CZE*,*[_]DEU*,*[_]DNK*,*[_]ESP*,*[_]EST*,*[_]FIN*,*[_]FRA*,*[_]GBR*,*[_]GIB*,*[_]GRC*,*[_]GRL*,*[_]HUN*,*[_]IMY*,*[_]IRL*,*[_]ISL*,*[_]ISR*,*[_]ITA*,*[_]LUX*,*[_]MCO*,*[_]NLD*,*[_]NOR*,*[_]POL*,*[_]PRT*,*[_]SMR*,*[_]SVK*,*[_]SVN*,*[_]SWE*,*[_]TUR*,*[_]VAT* | E19: ELCHYD | F19: NCAP,GROWTH | J19: 1.15 | K19: 1 | L19: 0 | M19: 5 | N19: ="Annual build rate (GW/Year) of ELEHYD_"&$A$1 -> Annual build rate (GW/Year) of ELEHYD_EUR
D20: ="EBldRateStep_Hyd_2_"&$A$1&",EBldRateStep_Hyd_3_"&$A$1 -> EBldRateStep_Hyd_2_EUR,EBldRateStep_Hyd_3_EUR | F20: ACT,NEWFLO | H20: UC_ACT | I20: 1
C21: ="UELC-Bld_ELEHYD-step2_"&$A$1 -> UELC-Bld_ELEHYD-step2_EUR | D21: =$D$7 -> *[_]ADO*,*[_]AUT*,*[_]BEL*,*[_]CHE*,*[_]CZE*,*[_]DEU*,*[_]DNK*,*[_]ESP*,*[_]EST*,*[_]FIN*,*[_]FRA*,*[_]GBR*,*[_]GIB*,*[_]GRC*,*[_]GRL*,*[_]HUN*,*[_]IMY*,*[_]IRL*,*[_]ISL*,*[_]ISR*,*[_]ITA*,*[_]LUX*,*[_]MCO*,*[_]NLD*,*[_]NOR*,*[_]POL*,*[_]PRT*,*[_]SMR*,*[_]SVK*,*[_]SVN*,*[_]SWE*,*[_]TUR*,*[_]VAT* | E21: ELCHYD | H21: UC_NCAP | I21: =I15 -> 0.85 | N21: ="step 2 relaxation of build rate - ELEHYD_"&$A$1 -> step 2 relaxation of build rate - ELEHYD_EUR
D22: ="EBldRateStep_Hyd_2_"&$A$1 -> EBldRateStep_Hyd_2_EUR | F22: ACT,NEWFLO | H22: UC_ACT | I22: -1 | L22: 0 | M22: 5
C23: ="UELC-Bld_ELEHYD-step3_"&$A$1 -> UELC-Bld_ELEHYD-step3_EUR | D23: =$D$7 -> *[_]ADO*,*[_]AUT*,*[_]BEL*,*[_]CHE*,*[_]CZE*,*[_]DEU*,*[_]DNK*,*[_]ESP*,*[_]EST*,*[_]FIN*,*[_]FRA*,*[_]GBR*,*[_]GIB*,*[_]GRC*,*[_]GRL*,*[_]HUN*,*[_]IMY*,*[_]IRL*,*[_]ISL*,*[_]ISR*,*[_]ITA*,*[_]LUX*,*[_]MCO*,*[_]NLD*,*[_]NOR*,*[_]POL*,*[_]PRT*,*[_]SMR*,*[_]SVK*,*[_]SVN*,*[_]SWE*,*[_]TUR*,*[_]VAT* | E23: ELCHYD | H23: UC_NCAP | I23: =I17 -> 1 | N23: ="step 3 relaxation of build rate - ELEHYD_"&$A$1 -> step 3 relaxation of build rate - ELEHYD_EUR
D24: ="EBldRateStep_Hyd_3_"&$A$1 -> EBldRateStep_Hyd_3_EUR | F24: ACT,NEWFLO | H24: UC_ACT | I24: -1 | L24: 0 | M24: 5
A25: wn | C25: ="UELC-Inv"&RIGHT(HistoricalBuilds!$N$1,2)&"_"&A25&"_"&$A$1 -> UELC-Inv19_wn_EUR | D25: =$D$7 -> *[_]ADO*,*[_]AUT*,*[_]BEL*,*[_]CHE*,*[_]CZE*,*[_]DEU*,*[_]DNK*,*[_]ESP*,*[_]EST*,*[_]FIN*,*[_]FRA*,*[_]GBR*,*[_]GIB*,*[_]GRC*,*[_]GRL*,*[_]HUN*,*[_]IMY*,*[_]IRL*,*[_]ISL*,*[_]ISR*,*[_]ITA*,*[_]LUX*,*[_]MCO*,*[_]NLD*,*[_]NOR*,*[_]POL*,*[_]PRT*,*[_]SMR*,*[_]SVK*,*[_]SVN*,*[_]SWE*,*[_]TUR*,*[_]VAT* | E25: ELCWIN | G25: UP | J25: 1 | L25: =SUMIFS(HistoricalBuilds!$C$2:$C$300,HistoricalBuilds!$A$2:$A$300,EUR!A$1,HistoricalBuilds!$B$2:$B$300,EUR!$A25)*$L$1 -> 15.383 | M25: 4
A26: sl | C26: ="UELC-Inv"&RIGHT(HistoricalBuilds!$N$1,2)&"_"&A26&"_"&$A$1 -> UELC-Inv19_sl_EUR | D26: =$D$7 -> *[_]ADO*,*[_]AUT*,*[_]BEL*,*[_]CHE*,*[_]CZE*,*[_]DEU*,*[_]DNK*,*[_]ESP*,*[_]EST*,*[_]FIN*,*[_]FRA*,*[_]GBR*,*[_]GIB*,*[_]GRC*,*[_]GRL*,*[_]HUN*,*[_]IMY*,*[_]IRL*,*[_]ISL*,*[_]ISR*,*[_]ITA*,*[_]LUX*,*[_]MCO*,*[_]NLD*,*[_]NOR*,*[_]POL*,*[_]PRT*,*[_]SMR*,*[_]SVK*,*[_]SVN*,*[_]SWE*,*[_]TUR*,*[_]VAT* | E26: ELCSOL | G26: UP | J26: 1 | L26: =SUMIFS(HistoricalBuilds!$C$2:$C$300,HistoricalBuilds!$A$2:$A$300,EUR!A$1,HistoricalBuilds!$B$2:$B$300,EUR!$A26)*$L$1 -> 23.0605 | M26: 4
A27: he | C27: ="UELC-Inv"&RIGHT(HistoricalBuilds!$N$1,2)&"_"&A27&"_"&$A$1 -> UELC-Inv19_he_EUR | D27: =$D$7 -> *[_]ADO*,*[_]AUT*,*[_]BEL*,*[_]CHE*,*[_]CZE*,*[_]DEU*,*[_]DNK*,*[_]ESP*,*[_]EST*,*[_]FIN*,*[_]FRA*,*[_]GBR*,*[_]GIB*,*[_]GRC*,*[_]GRL*,*[_]HUN*,*[_]IMY*,*[_]IRL*,*[_]ISL*,*[_]ISR*,*[_]ITA*,*[_]LUX*,*[_]MCO*,*[_]NLD*,*[_]NOR*,*[_]POL*,*[_]PRT*,*[_]SMR*,*[_]SVK*,*[_]SVN*,*[_]SWE*,*[_]TUR*,*[_]VAT* | E27: ELCHYD | G27: UP | J27: 1 | L27: =SUMIFS(HistoricalBuilds!$C$2:$C$300,HistoricalBuilds!$A$2:$A$300,EUR!A$1,HistoricalBuilds!$B$2:$B$300,EUR!$A27)*$L$1 -> 4.711 | M27: 4

Sheet OAS
A1: =MID(CELL( "filename",A1),FIND("]",CELL( "filename",A1))+1,10) -> OAS | L1: =AFR!$L$1 -> 1
C2: ~UC_Sets: R_S: AllRegions
C3: ~UC_Sets: T_E:
H5: ="~UC_T: UC_RHST~LO~"&HistoricalBuilds!$N$1 -> ~UC_T: UC_RHST~LO~2019
C6: UC_N | D6: PSET_PN | E6: Pset_CI | F6: UC_ATTR | G6: LimType | H6: Attribute | I6: LHS | J6: UC_NCAP | K6: UC_NCAP~RHS | L6: UC_RHST | M6: UC_RHST~0 | N6: UC_Desc
C7: ="UELC-Bld_ELEWIN_"&$A$1 -> UELC-Bld_ELEWIN_OAS | D7: =VLOOKUP("1"&$A$1,'WEPSReg-Countrymap'!$D$2:$E$232,2,FALSE) -> *[_]AFG*,*[_]BGD*,*[_]BRN*,*[_]BTN*,*[_]COK*,*[_]FJI*,*[_]HKG*,*[_]IDN*,*[_]KHM*,*[_]KIR*,*[_]LAO*,*[_]LKA*,*[_]MAC*,*[_]MDV*,*[_]MHL*,*[_]MMR*,*[_]MNG*,*[_]MNP*,*[_]MYS*,*[_]NCL*,*[_]NIU*,*[_]NPL*,*[_]NRU*,*[_]PAK*,*[_]PHL*,*[_]PLW*,*[_]PNG*,*[_]PRK*,*[_]PYF*,*[_]SGP*,*[_]SLB*,*[_]THA*,*[_]TMP*,*[_]TON*,*[_]TUV*,*[_]TWN*,*[_]VNM*,*[_]VUT*,*[_]WSM*,*[_]ASM*,*[_]GUM* | E7: ELCWIN | F7: NCAP,GROWTH | J7: 1.15 | K7: 1 | L7: 0 | M7: 5 | N7: ="Annual build rate (GW/Year) of ELEWIN_"&$A$1 -> Annual build rate (GW/Year) of ELEWIN_OAS
D8: ="EBldRateStep_Win_2_"&$A$1&",EBldRateStep_Win_3_"&$A$1 -> EBldRateStep_Win_2_OAS,EBldRateStep_Win_3_OAS | F8: ACT,NEWFLO | H8: UC_ACT | I8: 1
C9: ="UELC-Bld_ELEWIN-step2_"&$A$1 -> UELC-Bld_ELEWIN-step2_OAS | D9: =$D$7 -> *[_]AFG*,*[_]BGD*,*[_]BRN*,*[_]BTN*,*[_]COK*,*[_]FJI*,*[_]HKG*,*[_]IDN*,*[_]KHM*,*[_]KIR*,*[_]LAO*,*[_]LKA*,*[_]MAC*,*[_]MDV*,*[_]MHL*,*[_]MMR*,*[_]MNG*,*[_]MNP*,*[_]MYS*,*[_]NCL*,*[_]NIU*,*[_]NPL*,*[_]NRU*,*[_]PAK*,*[_]PHL*,*[_]PLW*,*[_]PNG*,*[_]PRK*,*[_]PYF*,*[_]SGP*,*[_]SLB*,*[_]THA*,*[_]TMP*,*[_]TON*,*[_]TUV*,*[_]TWN*,*[_]VNM*,*[_]VUT*,*[_]WSM*,*[_]ASM*,*[_]GUM* | E9: ELCWIN | H9: UC_NCAP | I9: 0.85 | N9: ="step 2 relaxation of build rate - ELEWIN_"&$A$1 -> step 2 relaxation of build rate - ELEWIN_OAS
D10: ="EBldRateStep_Win_2_"&$A$1 -> EBldRateStep_Win_2_OAS | F10: ACT,NEWFLO | H10: UC_ACT | I10: -1 | L10: 0 | M10: 5
C11: ="UELC-Bld_ELEWIN-step3_"&$A$1 -> UELC-Bld_ELEWIN-step3_OAS | D11: =$D$7 -> *[_]AFG*,*[_]BGD*,*[_]BRN*,*[_]BTN*,*[_]COK*,*[_]FJI*,*[_]HKG*,*[_]IDN*,*[_]KHM*,*[_]KIR*,*[_]LAO*,*[_]LKA*,*[_]MAC*,*[_]MDV*,*[_]MHL*,*[_]MMR*,*[_]MNG*,*[_]MNP*,*[_]MYS*,*[_]NCL*,*[_]NIU*,*[_]NPL*,*[_]NRU*,*[_]PAK*,*[_]PHL*,*[_]PLW*,*[_]PNG*,*[_]PRK*,*[_]PYF*,*[_]SGP*,*[_]SLB*,*[_]THA*,*[_]TMP*,*[_]TON*,*[_]TUV*,*[_]TWN*,*[_]VNM*,*[_]VUT*,*[_]WSM*,*[_]ASM*,*[_]GUM* | E11: ELCWIN | H11: UC_NCAP | I11: 1 | N11: ="step 3 relaxation of build rate - ELEWIN_"&$A$1 -> step 3 relaxation of build rate - ELEWIN_OAS
D12: ="EBldRateStep_Win_3_"&$A$1 -> EBldRateStep_Win_3_OAS | F12: ACT,NEWFLO | H12: UC_ACT | I12: -1 | L12: 0 | M12: 5
C13: ="UELC-Bld_ELESOL_"&$A$1 -> UELC-Bld_ELESOL_OAS | D13: =$D$7 -> *[_]AFG*,*[_]BGD*,*[_]BRN*,*[_]BTN*,*[_]COK*,*[_]FJI*,*[_]HKG*,*[_]IDN*,*[_]KHM*,*[_]KIR*,*[_]LAO*,*[_]LKA*,*[_]MAC*,*[_]MDV*,*[_]MHL*,*[_]MMR*,*[_]MNG*,*[_]MNP*,*[_]MYS*,*[_]NCL*,*[_]NIU*,*[_]NPL*,*[_]NRU*,*[_]PAK*,*[_]PHL*,*[_]PLW*,*[_]PNG*,*[_]PRK*,*[_]PYF*,*[_]SGP*,*[_]SLB*,*[_]THA*,*[_]TMP*,*[_]TON*,*[_]TUV*,*[_]TWN*,*[_]VNM*,*[_]VUT*,*[_]WSM*,*[_]ASM*,*[_]GUM* | E13: ELCSOL | F13: NCAP,GROWTH | J13: 1.15 | K13: 1 | L13: 0 | M13: 5 | N13: ="Annual build rate (GW/Year) of ELESOL_"&$A$1 -> Annual build rate (GW/Year) of ELESOL_OAS
D14: ="EBldRateStep_Sol_2_"&$A$1&",EBldRateStep_Sol_3_"&$A$1 -> EBldRateStep_Sol_2_OAS,EBldRateStep_Sol_3_OAS | F14: ACT,NEWFLO | H14: UC_ACT | I14: 1
C15: ="UELC-Bld_ELESOL-step2_"&$A$1 -> UELC-Bld_ELESOL-step2_OAS | D15: =$D$7 -> *[_]AFG*,*[_]BGD*,*[_]BRN*,*[_]BTN*,*[_]COK*,*[_]FJI*,*[_]HKG*,*[_]IDN*,*[_]KHM*,*[_]KIR*,*[_]LAO*,*[_]LKA*,*[_]MAC*,*[_]MDV*,*[_]MHL*,*[_]MMR*,*[_]MNG*,*[_]MNP*,*[_]MYS*,*[_]NCL*,*[_]NIU*,*[_]NPL*,*[_]NRU*,*[_]PAK*,*[_]PHL*,*[_]PLW*,*[_]PNG*,*[_]PRK*,*[_]PYF*,*[_]SGP*,*[_]SLB*,*[_]THA*,*[_]TMP*,*[_]TON*,*[_]TUV*,*[_]TWN*,*[_]VNM*,*[_]VUT*,*[_]WSM*,*[_]ASM*,*[_]GUM* | E15: ELCSOL | H15: UC_NCAP | I15: =I9 -> 0.85 | N15: ="step 2 relaxation of build rate - ELESOL_"&$A$1 -> step 2 relaxation of build rate - ELESOL_OAS
D16: ="EBldRateStep_Sol_2_"&$A$1 -> EBldRateStep_Sol_2_OAS | F16: ACT,NEWFLO | H16: UC_ACT | I16: -1 | L16: 0 | M16: 5
C17: ="UELC-Bld_ELESOL-step3_"&$A$1 -> UELC-Bld_ELESOL-step3_OAS | D17: =$D$7 -> *[_]AFG*,*[_]BGD*,*[_]BRN*,*[_]BTN*,*[_]COK*,*[_]FJI*,*[_]HKG*,*[_]IDN*,*[_]KHM*,*[_]KIR*,*[_]LAO*,*[_]LKA*,*[_]MAC*,*[_]MDV*,*[_]MHL*,*[_]MMR*,*[_]MNG*,*[_]MNP*,*[_]MYS*,*[_]NCL*,*[_]NIU*,*[_]NPL*,*[_]NRU*,*[_]PAK*,*[_]PHL*,*[_]PLW*,*[_]PNG*,*[_]PRK*,*[_]PYF*,*[_]SGP*,*[_]SLB*,*[_]THA*,*[_]TMP*,*[_]TON*,*[_]TUV*,*[_]TWN*,*[_]VNM*,*[_]VUT*,*[_]WSM*,*[_]ASM*,*[_]GUM* | E17: ELCSOL | H17: UC_NCAP | I17: =I11 -> 1 | N17: ="step 3 relaxation of build rate - ELESOL_"&$A$1 -> step 3 relaxation of build rate - ELESOL_OAS
D18: ="EBldRateStep_Sol_3_"&$A$1 -> EBldRateStep_Sol_3_OAS | F18: ACT,NEWFLO | H18: UC_ACT | I18: -1 | L18: 0 | M18: 5
C19: ="UELC-Bld_ELEHYD_"&$A$1 -> UELC-Bld_ELEHYD_OAS | D19: =$D$7 -> *[_]AFG*,*[_]BGD*,*[_]BRN*,*[_]BTN*,*[_]COK*,*[_]FJI*,*[_]HKG*,*[_]IDN*,*[_]KHM*,*[_]KIR*,*[_]LAO*,*[_]LKA*,*[_]MAC*,*[_]MDV*,*[_]MHL*,*[_]MMR*,*[_]MNG*,*[_]MNP*,*[_]MYS*,*[_]NCL*,*[_]NIU*,*[_]NPL*,*[_]NRU*,*[_]PAK*,*[_]PHL*,*[_]PLW*,*[_]PNG*,*[_]PRK*,*[_]PYF*,*[_]SGP*,*[_]SLB*,*[_]THA*,*[_]TMP*,*[_]TON*,*[_]TUV*,*[_]TWN*,*[_]VNM*,*[_]VUT*,*[_]WSM*,*[_]ASM*,*[_]GUM* | E19: ELCHYD | F19: NCAP,GROWTH | J19: 1.15 | K19: 1 | L19: 0 | M19: 5 | N19: ="Annual build rate (GW/Year) of ELEHYD_"&$A$1 -> Annual build rate (GW/Year) of ELEHYD_OAS
D20: ="EBldRateStep_Hyd_2_"&$A$1&",EBldRateStep_Hyd_3_"&$A$1 -> EBldRateStep_Hyd_2_OAS,EBldRateStep_Hyd_3_OAS | F20: ACT,NEWFLO | H20: UC_ACT | I20: 1
C21: ="UELC-Bld_ELEHYD-step2_"&$A$1 -> UELC-Bld_ELEHYD-step2_OAS | D21: =$D$7 -> *[_]AFG*,*[_]BGD*,*[_]BRN*,*[_]BTN*,*[_]COK*,*[_]FJI*,*[_]HKG*,*[_]IDN*,*[_]KHM*,*[_]KIR*,*[_]LAO*,*[_]LKA*,*[_]MAC*,*[_]MDV*,*[_]MHL*,*[_]MMR*,*[_]MNG*,*[_]MNP*,*[_]MYS*,*[_]NCL*,*[_]NIU*,*[_]NPL*,*[_]NRU*,*[_]PAK*,*[_]PHL*,*[_]PLW*,*[_]PNG*,*[_]PRK*,*[_]PYF*,*[_]SGP*,*[_]SLB*,*[_]THA*,*[_]TMP*,*[_]TON*,*[_]TUV*,*[_]TWN*,*[_]VNM*,*[_]VUT*,*[_]WSM*,*[_]ASM*,*[_]GUM* | E21: ELCHYD | H21: UC_NCAP | I21: =I15 -> 0.85 | N21: ="step 2 relaxation of build rate - ELEHYD_"&$A$1 -> step 2 relaxation of build rate - ELEHYD_OAS
D22: ="EBldRateStep_Hyd_2_"&$A$1 -> EBldRateStep_Hyd_2_OAS | F22: ACT,NEWFLO | H22: UC_ACT | I22: -1 | L22: 0 | M22: 5
C23: ="UELC-Bld_ELEHYD-step3_"&$A$1 -> UELC-Bld_ELEHYD-step3_OAS | D23: =$D$7 -> *[_]AFG*,*[_]BGD*,*[_]BRN*,*[_]BTN*,*[_]COK*,*[_]FJI*,*[_]HKG*,*[_]IDN*,*[_]KHM*,*[_]KIR*,*[_]LAO*,*[_]LKA*,*[_]MAC*,*[_]MDV*,*[_]MHL*,*[_]MMR*,*[_]MNG*,*[_]MNP*,*[_]MYS*,*[_]NCL*,*[_]NIU*,*[_]NPL*,*[_]NRU*,*[_]PAK*,*[_]PHL*,*[_]PLW*,*[_]PNG*,*[_]PRK*,*[_]PYF*,*[_]SGP*,*[_]SLB*,*[_]THA*,*[_]TMP*,*[_]TON*,*[_]TUV*,*[_]TWN*,*[_]VNM*,*[_]VUT*,*[_]WSM*,*[_]ASM*,*[_]GUM* | E23: ELCHYD | H23: UC_NCAP | I23: =I17 -> 1 | N23: ="step 3 relaxation of build rate - ELEHYD_"&$A$1 -> step 3 relaxation of build rate - ELEHYD_OAS
D24: ="EBldRateStep_Hyd_3_"&$A$1 -> EBldRateStep_Hyd_3_OAS | F24: ACT,NEWFLO | H24: UC_ACT | I24: -1 | L24: 0 | M24: 5
A25: wn | C25: ="UELC-Inv"&RIGHT(HistoricalBuilds!$N$1,2)&"_"&A25&"_"&$A$1 -> UELC-Inv19_wn_OAS | D25: =$D$7 -> *[_]AFG*,*[_]BGD*,*[_]BRN*,*[_]BTN*,*[_]COK*,*[_]FJI*,*[_]HKG*,*[_]IDN*,*[_]KHM*,*[_]KIR*,*[_]LAO*,*[_]LKA*,*[_]MAC*,*[_]MDV*,*[_]MHL*,*[_]MMR*,*[_]MNG*,*[_]MNP*,*[_]MYS*,*[_]NCL*,*[_]NIU*,*[_]NPL*,*[_]NRU*,*[_]PAK*,*[_]PHL*,*[_]PLW*,*[_]PNG*,*[_]PRK*,*[_]PYF*,*[_]SGP*,*[_]SLB*,*[_]THA*,*[_]TMP*,*[_]TON*,*[_]TUV*,*[_]TWN*,*[_]VNM*,*[_]VUT*,*[_]WSM*,*[_]ASM*,*[_]GUM* | E25: ELCWIN | G25: UP | J25: 1 | L25: =SUMIFS(HistoricalBuilds!$C$2:$C$300,HistoricalBuilds!$A$2:$A$300,OAS!A$1,HistoricalBuilds!$B$2:$B$300,OAS!$A25)*$L$1 -> 1.0759 | M25: 4
A26: sl | C26: ="UELC-Inv"&RIGHT(HistoricalBuilds!$N$1,2)&"_"&A26&"_"&$A$1 -> UELC-Inv19_sl_OAS | D26: =$D$7 -> *[_]AFG*,*[_]BGD*,*[_]BRN*,*[_]BTN*,*[_]COK*,*[_]FJI*,*[_]HKG*,*[_]IDN*,*[_]KHM*,*[_]KIR*,*[_]LAO*,*[_]LKA*,*[_]MAC*,*[_]MDV*,*[_]MHL*,*[_]MMR*,*[_]MNG*,*[_]MNP*,*[_]MYS*,*[_]NCL*,*[_]NIU*,*[_]NPL*,*[_]NRU*,*[_]PAK*,*[_]PHL*,*[_]PLW*,*[_]PNG*,*[_]PRK*,*[_]PYF*,*[_]SGP*,*[_]SLB*,*[_]THA*,*[_]TMP*,*[_]TON*,*[_]TUV*,*[_]TWN*,*[_]VNM*,*[_]VUT*,*[_]WSM*,*[_]ASM*,*[_]GUM* | E26: ELCSOL | G26: UP | J26: 1 | L26: =SUMIFS(HistoricalBuilds!$C$2:$C$300,HistoricalBuilds!$A$2:$A$300,OAS!A$1,HistoricalBuilds!$B$2:$B$300,OAS!$A26)*$L$1 -> 3.00672 | M26: 4
A27: he | C27: ="UELC-Inv"&RIGHT(HistoricalBuilds!$N$1,2)&"_"&A27&"_"&$A$1 -> UELC-Inv19_he_OAS | D27: =$D$7 -> *[_]AFG*,*[_]BGD*,*[_]BRN*,*[_]BTN*,*[_]COK*,*[_]FJI*,*[_]HKG*,*[_]IDN*,*[_]KHM*,*[_]KIR*,*[_]LAO*,*[_]LKA*,*[_]MAC*,*[_]MDV*,*[_]MHL*,*[_]MMR*,*[_]MNG*,*[_]MNP*,*[_]MYS*,*[_]NCL*,*[_]NIU*,*[_]NPL*,*[_]NRU*,*[_]PAK*,*[_]PHL*,*[_]PLW*,*[_]PNG*,*[_]PRK*,*[_]PYF*,*[_]SGP*,*[_]SLB*,*[_]THA*,*[_]TMP*,*[_]TON*,*[_]TUV*,*[_]TWN*,*[_]VNM*,*[_]VUT*,*[_]WSM*,*[_]ASM*,*[_]GUM* | E27: ELCHYD | G27: UP | J27: 1 | L27: =SUMIFS(HistoricalBuilds!$C$2:$C$300,HistoricalBuilds!$A$2:$A$300,OAS!A$1,HistoricalBuilds!$B$2:$B$300,OAS!$A27)*$L$1 -> 5.13697 | M27: 4

Sheet ANZ
A1: =MID(CELL( "filename",A1),FIND("]",CELL( "filename",A1))+1,10) -> ANZ | L1: =AFR!$L$1 -> 1
C2: ~UC_Sets: R_S: AllRegions
C3: ~UC_Sets: T_E:
H5: ="~UC_T: UC_RHST~LO~"&HistoricalBuilds!$N$1 -> ~UC_T: UC_RHST~LO~2019
C6: UC_N | D6: PSET_PN | E6: Pset_CI | F6: UC_ATTR | G6: LimType | H6: Attribute | I6: LHS | J6: UC_NCAP | K6: UC_NCAP~RHS | L6: UC_RHST | M6: UC_RHST~0 | N6: UC_Desc
C7: ="UELC-Bld_ELEWIN_"&$A$1 -> UELC-Bld_ELEWIN_ANZ | D7: =VLOOKUP("1"&$A$1,'WEPSReg-Countrymap'!$D$2:$E$232,2,FALSE) -> *[_]AUS*,*[_]NZL* | E7: ELCWIN | F7: NCAP,GROWTH | J7: 1.15 | K7: 1 | L7: 0 | M7: 5 | N7: ="Annual build rate (GW/Year) of ELEWIN_"&$A$1 -> Annual build rate (GW/Year) of ELEWIN_ANZ
D8: ="EBldRateStep_Win_2_"&$A$1&",EBldRateStep_Win_3_"&$A$1 -> EBldRateStep_Win_2_ANZ,EBldRateStep_Win_3_ANZ | F8: ACT,NEWFLO | H8: UC_ACT | I8: 1
C9: ="UELC-Bld_ELEWIN-step2_"&$A$1 -> UELC-Bld_ELEWIN-step2_ANZ | D9: =$D$7 -> *[_]AUS*,*[_]NZL* | E9: ELCWIN | H9: UC_NCAP | I9: 0.85 | N9: ="step 2 relaxation of build rate - ELEWIN_"&$A$1 -> step 2 relaxation of build rate - ELEWIN_ANZ
D10: ="EBldRateStep_Win_2_"&$A$1 -> EBldRateStep_Win_2_ANZ | F10: ACT,NEWFLO | H10: UC_ACT | I10: -1 | L10: 0 | M10: 5
C11: ="UELC-Bld_ELEWIN-step3_"&$A$1 -> UELC-Bld_ELEWIN-step3_ANZ | D11: =$D$7 -> *[_]AUS*,*[_]NZL* | E11: ELCWIN | H11: UC_NCAP | I11: 1 | N11: ="step 3 relaxation of build rate - ELEWIN_"&$A$1 -> step 3 relaxation of build rate - ELEWIN_ANZ
D12: ="EBldRateStep_Win_3_"&$A$1 -> EBldRateStep_Win_3_ANZ | F12: ACT,NEWFLO | H12: UC_ACT | I12: -1 | L12: 0 | M12: 5
C13: ="UELC-Bld_ELESOL_"&$A$1 -> UELC-Bld_ELESOL_ANZ | D13: =$D$7 -> *[_]AUS*,*[_]NZL* | E13: ELCSOL | F13: NCAP,GROWTH | J13: 1.15 | K13: 1 | L13: 0 | M13: 5 | N13: ="Annual build rate (GW/Year) of ELESOL_"&$A$1 -> Annual build rate (GW/Year) of ELESOL_ANZ
D14: ="EBldRateStep_Sol_2_"&$A$1&",EBldRateStep_Sol_3_"&$A$1 -> EBldRateStep_Sol_2_ANZ,EBldRateStep_Sol_3_ANZ | F14: ACT,NEWFLO | H14: UC_ACT | I14: 1
C15: ="UELC-Bld_ELESOL-step2_"&$A$1 -> UELC-Bld_ELESOL-step2_ANZ | D15: =$D$7 -> *[_]AUS*,*[_]NZL* | E15: ELCSOL | H15: UC_NCAP | I15: =I9 -> 0.85 | N15: ="step 2 relaxation of build rate - ELESOL_"&$A$1 -> step 2 relaxation of build rate - ELESOL_ANZ
D16: ="EBldRateStep_Sol_2_"&$A$1 -> EBldRateStep_Sol_2_ANZ | F16: ACT,NEWFLO | H16: UC_ACT | I16: -1 | L16: 0 | M16: 5
C17: ="UELC-Bld_ELESOL-step3_"&$A$1 -> UELC-Bld_ELESOL-step3_ANZ | D17: =$D$7 -> *[_]AUS*,*[_]NZL* | E17: ELCSOL | H17: UC_NCAP | I17: =I11 -> 1 | N17: ="step 3 relaxation of build rate - ELESOL_"&$A$1 -> step 3 relaxation of build rate - ELESOL_ANZ
D18: ="EBldRateStep_Sol_3_"&$A$1 -> EBldRateStep_Sol_3_ANZ | F18: ACT,NEWFLO | H18: UC_ACT | I18: -1 | L18: 0 | M18: 5
C19: ="UELC-Bld_ELEHYD_"&$A$1 -> UELC-Bld_ELEHYD_ANZ | D19: =$D$7 -> *[_]AUS*,*[_]NZL* | E19: ELCHYD | F19: NCAP,GROWTH | J19: 1.15 | K19: 1 | L19: 0 | M19: 5 | N19: ="Annual build rate (GW/Year) of ELEHYD_"&$A$1 -> Annual build rate (GW/Year) of ELEHYD_ANZ
D20: ="EBldRateStep_Hyd_2_"&$A$1&",EBldRateStep_Hyd_3_"&$A$1 -> EBldRateStep_Hyd_2_ANZ,EBldRateStep_Hyd_3_ANZ | F20: ACT,NEWFLO | H20: UC_ACT | I20: 1
C21: ="UELC-Bld_ELEHYD-step2_"&$A$1 -> UELC-Bld_ELEHYD-step2_ANZ | D21: =$D$7 -> *[_]AUS*,*[_]NZL* | E21: ELCHYD | H21: UC_NCAP | I21: =I15 -> 0.85 | N21: ="step 2 relaxation of build rate - ELEHYD_"&$A$1 -> step 2 relaxation of build rate - ELEHYD_ANZ
D22: ="EBldRateStep_Hyd_2_"&$A$1 -> EBldRateStep_Hyd_2_ANZ | F22: ACT,NEWFLO | H22: UC_ACT | I22: -1 | L22: 0 | M22: 5
C23: ="UELC-Bld_ELEHYD-step3_"&$A$1 -> UELC-Bld_ELEHYD-step3_ANZ | D23: =$D$7 -> *[_]AUS*,*[_]NZL* | E23: ELCHYD | H23: UC_NCAP | I23: =I17 -> 1 | N23: ="step 3 relaxation of build rate - ELEHYD_"&$A$1 -> step 3 relaxation of build rate - ELEHYD_ANZ
D24: ="EBldRateStep_Hyd_3_"&$A$1 -> EBldRateStep_Hyd_3_ANZ | F24: ACT,NEWFLO | H24: UC_ACT | I24: -1 | L24: 0 | M24: 5
A25: wn | C25: ="UELC-Inv"&RIGHT(HistoricalBuilds!$N$1,2)&"_"&A25&"_"&$A$1 -> UELC-Inv19_wn_ANZ | D25: =$D$7 -> *[_]AUS*,*[_]NZL* | E25: ELCWIN | G25: UP | J25: 1 | L25: =SUMIFS(HistoricalBuilds!$C$2:$C$300,HistoricalBuilds!$A$2:$A$300,ANZ!A$1,HistoricalBuilds!$B$2:$B$300,ANZ!$A25)*$L$1 -> 3.1827 | M25: 4
A26: sl | C26: ="UELC-Inv"&RIGHT(HistoricalBuilds!$N$1,2)&"_"&A26&"_"&$A$1 -> UELC-Inv19_sl_ANZ | D26: =$D$7 -> *[_]AUS*,*[_]NZL* | E26: ELCSOL | G26: UP | J26: 1 | L26: =SUMIFS(HistoricalBuilds!$C$2:$C$300,HistoricalBuilds!$A$2:$A$300,ANZ!A$1,HistoricalBuilds!$B$2:$B$300,ANZ!$A26)*$L$1 -> 3.971 | M26: 4
A27: he | C27: ="UELC-Inv"&RIGHT(HistoricalBuilds!$N$1,2)&"_"&A27&"_"&$A$1 -> UELC-Inv19_he_ANZ | D27: =$D$7 -> *[_]AUS*,*[_]NZL* | E27: ELCHYD | G27: UP | J27: 1 | L27: =SUMIFS(HistoricalBuilds!$C$2:$C$300,HistoricalBuilds!$A$2:$A$300,ANZ!A$1,HistoricalBuilds!$B$2:$B$300,ANZ!$A27)*$L$1 -> 1.02765 | M27: 4

Sheet BRZ
A1: =MID(CELL( "filename",A1),FIND("]",CELL( "filename",A1))+1,10) -> BRZ | L1: =AFR!$L$1 -> 1
C2: ~UC_Sets: R_S: AllRegions
C3: ~UC_Sets: T_E:
H5: ="~UC_T: UC_RHST~LO~"&HistoricalBuilds!$N$1 -> ~UC_T: UC_RHST~LO~2019
C6: UC_N | D6: PSET_PN | E6: Pset_CI | F6: UC_ATTR | G6: LimType | H6: Attribute | I6: LHS | J6: UC_NCAP | K6: UC_NCAP~RHS | L6: UC_RHST | M6: UC_RHST~0 | N6: UC_Desc
C7: ="UELC-Bld_ELEWIN_"&$A$1 -> UELC-Bld_ELEWIN_BRZ | D7: =VLOOKUP("1"&$A$1,'WEPSReg-Countrymap'!$D$2:$E$232,2,FALSE) -> *[_]BRA* | E7: ELCWIN | F7: NCAP,GROWTH | J7: 1.15 | K7: 1 | L7: 0 | M7: 5 | N7: ="Annual build rate (GW/Year) of ELEWIN_"&$A$1 -> Annual build rate (GW/Year) of ELEWIN_BRZ
D8: ="EBldRateStep_Win_2_"&$A$1&",EBldRateStep_Win_3_"&$A$1 -> EBldRateStep_Win_2_BRZ,EBldRateStep_Win_3_BRZ | F8: ACT,NEWFLO | H8: UC_ACT | I8: 1
C9: ="UELC-Bld_ELEWIN-step2_"&$A$1 -> UELC-Bld_ELEWIN-step2_BRZ | D9: =$D$7 -> *[_]BRA* | E9: ELCWIN | H9: UC_NCAP | I9: 0.85 | N9: ="step 2 relaxation of build rate - ELEWIN_"&$A$1 -> step 2 relaxation of build rate - ELEWIN_BRZ
D10: ="EBldRateStep_Win_2_"&$A$1 -> EBldRateStep_Win_2_BRZ | F10: ACT,NEWFLO | H10: UC_ACT | I10: -1 | L10: 0 | M10: 5
C11: ="UELC-Bld_ELEWIN-step3_"&$A$1 -> UELC-Bld_ELEWIN-step3_BRZ | D11: =$D$7 -> *[_]BRA* | E11: ELCWIN | H11: UC_NCAP | I11: 1 | N11: ="step 3 relaxation of build rate - ELEWIN_"&$A$1 -> step 3 relaxation of build rate - ELEWIN_BRZ
D12: ="EBldRateStep_Win_3_"&$A$1 -> EBldRateStep_Win_3_BRZ | F12: ACT,NEWFLO | H12: UC_ACT | I12: -1 | L12: 0 | M12: 5
C13: ="UELC-Bld_ELESOL_"&$A$1 -> UELC-Bld_ELESOL_BRZ | D13: =$D$7 -> *[_]BRA* | E13: ELCSOL | F13: NCAP,GROWTH | J13: 1.15 | K13: 1 | L13: 0 | M13: 5 | N13: ="Annual build rate (GW/Year) of ELESOL_"&$A$1 -> Annual build rate (GW/Year) of ELESOL_BRZ
D14: ="EBldRateStep_Sol_2_"&$A$1&",EBldRateStep_Sol_3_"&$A$1 -> EBldRateStep_Sol_2_BRZ,EBldRateStep_Sol_3_BRZ | F14: ACT,NEWFLO | H14: UC_ACT | I14: 1
C15: ="UELC-Bld_ELESOL-step2_"&$A$1 -> UELC-Bld_ELESOL-step2_BRZ | D15: =$D$7 -> *[_]BRA* | E15: ELCSOL | H15: UC_NCAP | I15: =I9 -> 0.85 | N15: ="step 2 relaxation of build rate - ELESOL_"&$A$1 -> step 2 relaxation of build rate - ELESOL_BRZ
D16: ="EBldRateStep_Sol_2_"&$A$1 -> EBldRateStep_Sol_2_BRZ | F16: ACT,NEWFLO | H16: UC_ACT | I16: -1 | L16: 0 | M16: 5
C17: ="UELC-Bld_ELESOL-step3_"&$A$1 -> UELC-Bld_ELESOL-step3_BRZ | D17: =$D$7 -> *[_]BRA* | E17: ELCSOL | H17: UC_NCAP | I17: =I11 -> 1 | N17: ="step 3 relaxation of build rate - ELESOL_"&$A$1 -> step 3 relaxation of build rate - ELESOL_BRZ
D18: ="EBldRateStep_Sol_3_"&$A$1 -> EBldRateStep_Sol_3_BRZ | F18: ACT,NEWFLO | H18: UC_ACT | I18: -1 | L18: 0 | M18: 5
C19: ="UELC-Bld_ELEHYD_"&$A$1 -> UELC-Bld_ELEHYD_BRZ | D19: =$D$7 -> *[_]BRA* | E19: ELCHYD | F19: NCAP,GROWTH | J19: 1.15 | K19: 1 | L19: 0 | M19: 5 | N19: ="Annual build rate (GW/Year) of ELEHYD_"&$A$1 -> Annual build rate (GW/Year) of ELEHYD_BRZ
D20: ="EBldRateStep_Hyd_2_"&$A$1&",EBldRateStep_Hyd_3_"&$A$1 -> EBldRateStep_Hyd_2_BRZ,EBldRateStep_Hyd_3_BRZ | F20: ACT,NEWFLO | H20: UC_ACT | I20: 1
C21: ="UELC-Bld_ELEHYD-step2_"&$A$1 -> UELC-Bld_ELEHYD-step2_BRZ | D21: =$D$7 -> *[_]BRA* | E21: ELCHYD | H21: UC_NCAP | I21: =I15 -> 0.85 | N21: ="step 2 relaxation of build rate - ELEHYD_"&$A$1 -> step 2 relaxation of build rate - ELEHYD_BRZ
D22: ="EBldRateStep_Hyd_2_"&$A$1 -> EBldRateStep_Hyd_2_BRZ | F22: ACT,NEWFLO | H22: UC_ACT | I22: -1 | L22: 0 | M22: 5
C23: ="UELC-Bld_ELEHYD-step3_"&$A$1 -> UELC-Bld_ELEHYD-step3_BRZ | D23: =$D$7 -> *[_]BRA* | E23: ELCHYD | H23: UC_NCAP | I23: =I17 -> 1 | N23: ="step 3 relaxation of build rate - ELEHYD_"&$A$1 -> step 3 relaxation of build rate - ELEHYD_BRZ
D24: ="EBldRateStep_Hyd_3_"&$A$1 -> EBldRateStep_Hyd_3_BRZ | F24: ACT,NEWFLO | H24: UC_ACT | I24: -1 | L24: 0 | M24: 5
A25: wn | C25: ="UELC-Inv"&RIGHT(HistoricalBuilds!$N$1,2)&"_"&A25&"_"&$A$1 -> UELC-Inv19_wn_BRZ | D25: =$D$7 -> *[_]BRA* | E25: ELCWIN | G25: UP | J25: 1 | L25: =SUMIFS(HistoricalBuilds!$C$2:$C$300,HistoricalBuilds!$A$2:$A$300,BRZ!A$1,HistoricalBuilds!$B$2:$B$300,BRZ!$A25)*$L$1 -> 3.10861 | M25: 4
A26: sl | C26: ="UELC-Inv"&RIGHT(HistoricalBuilds!$N$1,2)&"_"&A26&"_"&$A$1 -> UELC-Inv19_sl_BRZ | D26: =$D$7 -> *[_]BRA* | E26: ELCSOL | G26: UP | J26: 1 | L26: =SUMIFS(HistoricalBuilds!$C$2:$C$300,HistoricalBuilds!$A$2:$A$300,BRZ!A$1,HistoricalBuilds!$B$2:$B$300,BRZ!$A26)*$L$1 -> 1.200921 | M26: 4
A27: he | C27: ="UELC-Inv"&RIGHT(HistoricalBuilds!$N$1,2)&"_"&A27&"_"&$A$1 -> UELC-Inv19_he_BRZ | D27: =$D$7 -> *[_]BRA* | E27: ELCHYD | G27: UP | J27: 1 | L27: =SUMIFS(HistoricalBuilds!$C$2:$C$300,HistoricalBuilds!$A$2:$A$300,BRZ!A$1,HistoricalBuilds!$B$2:$B$300,BRZ!$A27)*$L$1 -> 5.28 | M27: 4

Sheet CAN
A1: =MID(CELL( "filename",A1),FIND("]",CELL( "filename",A1))+1,10) -> CAN | L1: =#REF! -> #REF!
C2: ~UC_Sets: R_S: AllRegions
C3: ~UC_Sets: T_E:
H5: ="~UC_T: UC_RHST~LO~"&HistoricalBuilds!$N$1 -> ~UC_T: UC_RHST~LO~2019
C6: UC_N | D6: PSET_PN | E6: Pset_CI | F6: UC_ATTR | G6: LimType | H6: Attribute | I6: LHS | J6: UC_NCAP | K6: UC_NCAP~RHS | L6: UC_RHST | M6: UC_RHST~0 | N6: UC_Desc
C7: ="UELC-Bld_ELEWIN_"&$A$1 -> UELC-Bld_ELEWIN_CAN | D7: =VLOOKUP("1"&$A$1,'WEPSReg-Countrymap'!$D$2:$E$232,2,FALSE) -> *[_]CAN* | E7: ELCWIN | F7: NCAP,GROWTH | J7: 1.15 | K7: 1 | L7: 0 | M7: 5 | N7: ="Annual build rate (GW/Year) of ELEWIN_"&$A$1 -> Annual build rate (GW/Year) of ELEWIN_CAN
D8: ="EBldRateStep_Win_2_"&$A$1&",EBldRateStep_Win_3_"&$A$1 -> EBldRateStep_Win_2_CAN,EBldRateStep_Win_3_CAN | F8: ACT,NEWFLO | H8: UC_ACT | I8: 1
C9: ="UELC-Bld_ELEWIN-step2_"&$A$1 -> UELC-Bld_ELEWIN-step2_CAN | D9: =$D$7 -> *[_]CAN* | E9: ELCWIN | H9: UC_NCAP | I9: 0.85 | N9: ="step 2 relaxation of build rate - ELEWIN_"&$A$1 -> step 2 relaxation of build rate - ELEWIN_CAN
D10: ="EBldRateStep_Win_2_"&$A$1 -> EBldRateStep_Win_2_CAN | F10: ACT,NEWFLO | H10: UC_ACT | I10: -1 | L10: 0 | M10: 5
C11: ="UELC-Bld_ELEWIN-step3_"&$A$1 -> UELC-Bld_ELEWIN-step3_CAN | D11: =$D$7 -> *[_]CAN* | E11: ELCWIN | H11: UC_NCAP | I11: 1 | N11: ="step 3 relaxation of build rate - ELEWIN_"&$A$1 -> step 3 relaxation of build rate - ELEWIN_CAN
D12: ="EBldRateStep_Win_3_"&$A$1 -> EBldRateStep_Win_3_CAN | F12: ACT,NEWFLO | H12: UC_ACT | I12: -1 | L12: 0 | M12: 5
C13: ="UELC-Bld_ELESOL_"&$A$1 -> UELC-Bld_ELESOL_CAN | D13: =$D$7 -> *[_]CAN* | E13: ELCSOL | F13: NCAP,GROWTH | J13: 1.15 | K13: 1 | L13: 0 | M13: 5 | N13: ="Annual build rate (GW/Year) of ELESOL_"&$A$1 -> Annual build rate (GW/Year) of ELESOL_CAN
D14: ="EBldRateStep_Sol_2_"&$A$1&",EBldRateStep_Sol_3_"&$A$1 -> EBldRateStep_Sol_2_CAN,EBldRateStep_Sol_3_CAN | F14: ACT,NEWFLO | H14: UC_ACT | I14: 1
C15: ="UELC-Bld_ELESOL-step2_"&$A$1 -> UELC-Bld_ELESOL-step2_CAN | D15: =$D$7 -> *[_]CAN* | E15: ELCSOL | H15: UC_NCAP | I15: =I9 -> 0.85 | N15: ="step 2 relaxation of build rate - ELESOL_"&$A$1 -> step 2 relaxation of build rate - ELESOL_CAN
D16: ="EBldRateStep_Sol_2_"&$A$1 -> EBldRateStep_Sol_2_CAN | F16: ACT,NEWFLO | H16: UC_ACT | I16: -1 | L16: 0 | M16: 5
C17: ="UELC-Bld_ELESOL-step3_"&$A$1 -> UELC-Bld_ELESOL-step3_CAN | D17: =$D$7 -> *[_]CAN* | E17: ELCSOL | H17: UC_NCAP | I17: =I11 -> 1 | N17: ="step 3 relaxation of build rate - ELESOL_"&$A$1 -> step 3 relaxation of build rate - ELESOL_CAN
D18: ="EBldRateStep_Sol_3_"&$A$1 -> EBldRateStep_Sol_3_CAN | F18: ACT,NEWFLO | H18: UC_ACT | I18: -1 | L18: 0 | M18: 5
C19: ="UELC-Bld_ELEHYD_"&$A$1 -> UELC-Bld_ELEHYD_CAN | D19: =$D$7 -> *[_]CAN* | E19: ELCHYD | F19: NCAP,GROWTH | J19: 1.15 | K19: 1 | L19: 0 | M19: 5 | N19: ="Annual build rate (GW/Year) of ELEHYD_"&$A$1 -> Annual build rate (GW/Year) of ELEHYD_CAN
D20: ="EBldRateStep_Hyd_2_"&$A$1&",EBldRateStep_Hyd_3_"&$A$1 -> EBldRateStep_Hyd_2_CAN,EBldRateStep_Hyd_3_CAN | F20: ACT,NEWFLO | H20: UC_ACT | I20: 1
C21: ="UELC-Bld_ELEHYD-step2_"&$A$1 -> UELC-Bld_ELEHYD-step2_CAN | D21: =$D$7 -> *[_]CAN* | E21: ELCHYD | H21: UC_NCAP | I21: =I15 -> 0.85 | N21: ="step 2 relaxation of build rate - ELEHYD_"&$A$1 -> step 2 relaxation of build rate - ELEHYD_CAN
D22: ="EBldRateStep_Hyd_2_"&$A$1 -> EBldRateStep_Hyd_2_CAN | F22: ACT,NEWFLO | H22: UC_ACT | I22: -1 | L22: 0 | M22: 5
C23: ="UELC-Bld_ELEHYD-step3_"&$A$1 -> UELC-Bld_ELEHYD-step3_CAN | D23: =$D$7 -> *[_]CAN* | E23: ELCHYD | H23: UC_NCAP | I23: =I17 -> 1 | N23: ="step 3 relaxation of build rate - ELEHYD_"&$A$1 -> step 3 relaxation of build rate - ELEHYD_CAN
D24: ="EBldRateStep_Hyd_3_"&$A$1 -> EBldRateStep_Hyd_3_CAN | F24: ACT,NEWFLO | H24: UC_ACT | I24: -1 | L24: 0 | M24: 5
A25: wn | C25: ="UELC-Inv"&RIGHT(HistoricalBuilds!$N$1,2)&"_"&A25&"_"&$A$1 -> UELC-Inv19_wn_CAN | D25: =$D$7 -> *[_]CAN* | E25: ELCWIN | G25: UP | J25: 1 | L25: =SUMIFS(HistoricalBuilds!$C$2:$C$300,HistoricalBuilds!$A$2:$A$300,CAN!A$1,HistoricalBuilds!$B$2:$B$300,CAN!$A25)*$L$1 -> #REF! | M25: 4
A26: sl | C26: ="UELC-Inv"&RIGHT(HistoricalBuilds!$N$1,2)&"_"&A26&"_"&$A$1 -> UELC-Inv19_sl_CAN | D26: =$D$7 -> *[_]CAN* | E26: ELCSOL | G26: UP | J26: 1 | L26: =SUMIFS(HistoricalBuilds!$C$2:$C$300,HistoricalBuilds!$A$2:$A$300,CAN!A$1,HistoricalBuilds!$B$2:$B$300,CAN!$A26)*$L$1 -> #REF! | M26: 4
A27: he | C27: ="UELC-Inv"&RIGHT(HistoricalBuilds!$N$1,2)&"_"&A27&"_"&$A$1 -> UELC-Inv19_he_CAN | D27: =$D$7 -> *[_]CAN* | E27: ELCHYD | G27: UP | J27: 1 | L27: =SUMIFS(HistoricalBuilds!$C$2:$C$300,HistoricalBuilds!$A$2:$A$300,CAN!A$1,HistoricalBuilds!$B$2:$B$300,CAN!$A27)*$L$1 -> #REF! | M27: 4

Sheet CHI
A1: =MID(CELL( "filename",A1),FIND("]",CELL( "filename",A1))+1,10) -> CHI | L1: =AFR!$L$1 -> 1
C2: ~UC_Sets: R_S: AllRegions
C3: ~UC_Sets: T_E:
H5: ="~UC_T: UC_RHST~LO~"&HistoricalBuilds!$N$1 -> ~UC_T: UC_RHST~LO~2019
C6: UC_N | D6: PSET_PN | E6: Pset_CI | F6: UC_ATTR | G6: LimType | H6: Attribute | I6: LHS | J6: UC_NCAP | K6: UC_NCAP~RHS | L6: UC_RHST | M6: UC_RHST~0 | N6: UC_Desc
C7: ="UELC-Bld_ELEWIN_"&$A$1 -> UELC-Bld_ELEWIN_CHI | D7: =VLOOKUP("1"&$A$1,'WEPSReg-Countrymap'!$D$2:$E$232,2,FALSE) -> *[_]CHN* | E7: ELCWIN | F7: NCAP,GROWTH | J7: 1.15 | K7: 1 | L7: 0 | M7: 5 | N7: ="Annual build rate (GW/Year) of ELEWIN_"&$A$1 -> Annual build rate (GW/Year) of ELEWIN_CHI
D8: ="EBldRateStep_Win_2_"&$A$1&",EBldRateStep_Win_3_"&$A$1 -> EBldRateStep_Win_2_CHI,EBldRateStep_Win_3_CHI | F8: ACT,NEWFLO | H8: UC_ACT | I8: 1
C9: ="UELC-Bld_ELEWIN-step2_"&$A$1 -> UELC-Bld_ELEWIN-step2_CHI | D9: =$D$7 -> *[_]CHN* | E9: ELCWIN | H9: UC_NCAP | I9: 0.85 | N9: ="step 2 relaxation of build rate - ELEWIN_"&$A$1 -> step 2 relaxation of build rate - ELEWIN_CHI
D10: ="EBldRateStep_Win_2_"&$A$1 -> EBldRateStep_Win_2_CHI | F10: ACT,NEWFLO | H10: UC_ACT | I10: -1 | L10: 0 | M10: 5
C11: ="UELC-Bld_ELEWIN-step3_"&$A$1 -> UELC-Bld_ELEWIN-step3_CHI | D11: =$D$7 -> *[_]CHN* | E11: ELCWIN | H11: UC_NCAP | I11: 1 | N11: ="step 3 relaxation of build rate - ELEWIN_"&$A$1 -> step 3 relaxation of build rate - ELEWIN_CHI
D12: ="EBldRateStep_Win_3_"&$A$1 -> EBldRateStep_Win_3_CHI | F12: ACT,NEWFLO | H12: UC_ACT | I12: -1 | L12: 0 | M12: 5
C13: ="UELC-Bld_ELESOL_"&$A$1 -> UELC-Bld_ELESOL_CHI | D13: =$D$7 -> *[_]CHN* | E13: ELCSOL | F13: NCAP,GROWTH | J13: 1.15 | K13: 1 | L13: 0 | M13: 5 | N13: ="Annual build rate (GW/Year) of ELESOL_"&$A$1 -> Annual build rate (GW/Year) of ELESOL_CHI
D14: ="EBldRateStep_Sol_2_"&$A$1&",EBldRateStep_Sol_3_"&$A$1 -> EBldRateStep_Sol_2_CHI,EBldRateStep_Sol_3_CHI | F14: ACT,NEWFLO | H14: UC_ACT | I14: 1
C15: ="UELC-Bld_ELESOL-step2_"&$A$1 -> UELC-Bld_ELESOL-step2_CHI | D15: =$D$7 -> *[_]CHN* | E15: ELCSOL | H15: UC_NCAP | I15: =I9 -> 0.85 | N15: ="step 2 relaxation of build rate - ELESOL_"&$A$1 -> step 2 relaxation of build rate - ELESOL_CHI
D16: ="EBldRateStep_Sol_2_"&$A$1 -> EBldRateStep_Sol_2_CHI | F16: ACT,NEWFLO | H16: UC_ACT | I16: -1 | L16: 0 | M16: 5
C17: ="UELC-Bld_ELESOL-step3_"&$A$1 -> UELC-Bld_ELESOL-step3_CHI | D17: =$D$7 -> *[_]CHN* | E17: ELCSOL | H17: UC_NCAP | I17: =I11 -> 1 | N17: ="step 3 relaxation of build rate - ELESOL_"&$A$1 -> step 3 relaxation of build rate - ELESOL_CHI
D18: ="EBldRateStep_Sol_3_"&$A$1 -> EBldRateStep_Sol_3_CHI | F18: ACT,NEWFLO | H18: UC_ACT | I18: -1 | L18: 0 | M18: 5
C19: ="UELC-Bld_ELEHYD_"&$A$1 -> UELC-Bld_ELEHYD_CHI | D19: =$D$7 -> *[_]CHN* | E19: ELCHYD | F19: NCAP,GROWTH | J19: 1.15 | K19: 1 | L19: 0 | M19: 5 | N19: ="Annual build rate (GW/Year) of ELEHYD_"&$A$1 -> Annual build rate (GW/Year) of ELEHYD_CHI
D20: ="EBldRateStep_Hyd_2_"&$A$1&",EBldRateStep_Hyd_3_"&$A$1 -> EBldRateStep_Hyd_2_CHI,EBldRateStep_Hyd_3_CHI | F20: ACT,NEWFLO | H20: UC_ACT | I20: 1
C21: ="UELC-Bld_ELEHYD-step2_"&$A$1 -> UELC-Bld_ELEHYD-step2_CHI | D21: =$D$7 -> *[_]CHN* | E21: ELCHYD | H21: UC_NCAP | I21: =I15 -> 0.85 | N21: ="step 2 relaxation of build rate - ELEHYD_"&$A$1 -> step 2 relaxation of build rate - ELEHYD_CHI
D22: ="EBldRateStep_Hyd_2_"&$A$1 -> EBldRateStep_Hyd_2_CHI | F22: ACT,NEWFLO | H22: UC_ACT | I22: -1 | L22: 0 | M22: 5
C23: ="UELC-Bld_ELEHYD-step3_"&$A$1 -> UELC-Bld_ELEHYD-step3_CHI | D23: =$D$7 -> *[_]CHN* | E23: ELCHYD | H23: UC_NCAP | I23: =I17 -> 1 | N23: ="step 3 relaxation of build rate - ELEHYD_"&$A$1 -> step 3 relaxation of build rate - ELEHYD_CHI
D24: ="EBldRateStep_Hyd_3_"&$A$1 -> EBldRateStep_Hyd_3_CHI | F24: ACT,NEWFLO | H24: UC_ACT | I24: -1 | L24: 0 | M24: 5
A25: wn | C25: ="UELC-Inv"&RIGHT(HistoricalBuilds!$N$1,2)&"_"&A25&"_"&$A$1 -> UELC-Inv19_wn_CHI | D25: =$D$7 -> *[_]CHN* | E25: ELCWIN | G25: UP | J25: 1 | L25: =SUMIFS(HistoricalBuilds!$C$2:$C$300,HistoricalBuilds!$A$2:$A$300,CHI!A$1,HistoricalBuilds!$B$2:$B$300,CHI!$A25)*$L$1 -> 33 | M25: 4
A26: sl | C26: ="UELC-Inv"&RIGHT(HistoricalBuilds!$N$1,2)&"_"&A26&"_"&$A$1 -> UELC-Inv19_sl_CHI | D26: =$D$7 -> *[_]CHN* | E26: ELCSOL | G26: UP | J26: 1 | L26: =SUMIFS(HistoricalBuilds!$C$2:$C$300,HistoricalBuilds!$A$2:$A$300,CHI!A$1,HistoricalBuilds!$B$2:$B$300,CHI!$A26)*$L$1 -> 53 | M26: 4
A27: he | C27: ="UELC-Inv"&RIGHT(HistoricalBuilds!$N$1,2)&"_"&A27&"_"&$A$1 -> UELC-Inv19_he_CHI | D27: =$D$7 -> *[_]CHN* | E27: ELCHYD | G27: UP | J27: 1 | L27: =SUMIFS(HistoricalBuilds!$C$2:$C$300,HistoricalBuilds!$A$2:$A$300,CHI!A$1,HistoricalBuilds!$B$2:$B$300,CHI!$A27)*$L$1 -> 29.77 | M27: 4

Sheet IND
A1: =MID(CELL( "filename",A1),FIND("]",CELL( "filename",A1))+1,10) -> IND | L1: =AFR!$L$1 -> 1
C2: ~UC_Sets: R_S: AllRegions
C3: ~UC_Sets: T_E:
H5: ="~UC_T: UC_RHST~LO~"&HistoricalBuilds!$N$1 -> ~UC_T: UC_RHST~LO~2019
C6: UC_N | D6: PSET_PN | E6: Pset_CI | F6: UC_ATTR | G6: LimType | H6: Attribute | I6: LHS | J6: UC_NCAP | K6: UC_NCAP~RHS | L6: UC_RHST | M6: UC_RHST~0 | N6: UC_Desc
C7: ="UELC-Bld_ELEWIN_"&$A$1 -> UELC-Bld_ELEWIN_IND | D7: =VLOOKUP("1"&$A$1,'WEPSReg-Countrymap'!$D$2:$E$232,2,FALSE) -> *[_]IND* | E7: ELCWIN | F7: NCAP,GROWTH | J7: 1.15 | K7: 1 | L7: 0 | M7: 5 | N7: ="Annual build rate (GW/Year) of ELEWIN_"&$A$1 -> Annual build rate (GW/Year) of ELEWIN_IND
D8: ="EBldRateStep_Win_2_"&$A$1&",EBldRateStep_Win_3_"&$A$1 -> EBldRateStep_Win_2_IND,EBldRateStep_Win_3_IND | F8: ACT,NEWFLO | H8: UC_ACT | I8: 1
C9: ="UELC-Bld_ELEWIN-step2_"&$A$1 -> UELC-Bld_ELEWIN-step2_IND | D9: =$D$7 -> *[_]IND* | E9: ELCWIN | H9: UC_NCAP | I9: 0.85 | N9: ="step 2 relaxation of build rate - ELEWIN_"&$A$1 -> step 2 relaxation of build rate - ELEWIN_IND
D10: ="EBldRateStep_Win_2_"&$A$1 -> EBldRateStep_Win_2_IND | F10: ACT,NEWFLO | H10: UC_ACT | I10: -1 | L10: 0 | M10: 5
C11: ="UELC-Bld_ELEWIN-step3_"&$A$1 -> UELC-Bld_ELEWIN-step3_IND | D11: =$D$7 -> *[_]IND* | E11: ELCWIN | H11: UC_NCAP | I11: 1 | N11: ="step 3 relaxation of build rate - ELEWIN_"&$A$1 -> step 3 relaxation of build rate - ELEWIN_IND
D12: ="EBldRateStep_Win_3_"&$A$1 -> EBldRateStep_Win_3_IND | F12: ACT,NEWFLO | H12: UC_ACT | I12: -1 | L12: 0 | M12: 5
C13: ="UELC-Bld_ELESOL_"&$A$1 -> UELC-Bld_ELESOL_IND | D13: =$D$7 -> *[_]IND* | E13: ELCSOL | F13: NCAP,GROWTH | J13: 1.15 | K13: 1 | L13: 0 | M13: 5 | N13: ="Annual build rate (GW/Year) of ELESOL_"&$A$1 -> Annual build rate (GW/Year) of ELESOL_IND
D14: ="EBldRateStep_Sol_2_"&$A$1&",EBldRateStep_Sol_3_"&$A$1 -> EBldRateStep_Sol_2_IND,EBldRateStep_Sol_3_IND | F14: ACT,NEWFLO | H14: UC_ACT | I14: 1
C15: ="UELC-Bld_ELESOL-step2_"&$A$1 -> UELC-Bld_ELESOL-step2_IND | D15: =$D$7 -> *[_]IND* | E15: ELCSOL | H15: UC_NCAP | I15: =I9 -> 0.85 | N15: ="step 2 relaxation of build rate - ELESOL_"&$A$1 -> step 2 relaxation of build rate - ELESOL_IND
D16: ="EBldRateStep_Sol_2_"&$A$1 -> EBldRateStep_Sol_2_IND | F16: ACT,NEWFLO | H16: UC_ACT | I16: -1 | L16: 0 | M16: 5
C17: ="UELC-Bld_ELESOL-step3_"&$A$1 -> UELC-Bld_ELESOL-step3_IND | D17: =$D$7 -> *[_]IND* | E17: ELCSOL | H17: UC_NCAP | I17: =I11 -> 1 | N17: ="step 3 relaxation of build rate - ELESOL_"&$A$1 -> step 3 relaxation of build rate - ELESOL_IND
D18: ="EBldRateStep_Sol_3_"&$A$1 -> EBldRateStep_Sol_3_IND | F18: ACT,NEWFLO | H18: UC_ACT | I18: -1 | L18: 0 | M18: 5
C19: ="UELC-Bld_ELEHYD_"&$A$1 -> UELC-Bld_ELEHYD_IND | D19: =$D$7 -> *[_]IND* | E19: ELCHYD | F19: NCAP,GROWTH | J19: 1.15 | K19: 1 | L19: 0 | M19: 5 | N19: ="Annual build rate (GW/Year) of ELEHYD_"&$A$1 -> Annual build rate (GW/Year) of ELEHYD_IND
D20: ="EBldRateStep_Hyd_2_"&$A$1&",EBldRateStep_Hyd_3_"&$A$1 -> EBldRateStep_Hyd_2_IND,EBldRateStep_Hyd_3_IND | F20: ACT,NEWFLO | H20: UC_ACT | I20: 1
C21: ="UELC-Bld_ELEHYD-step2_"&$A$1 -> UELC-Bld_ELEHYD-step2_IND | D21: =$D$7 -> *[_]IND* | E21: ELCHYD | H21: UC_NCAP | I21: =I15 -> 0.85 | N21: ="step 2 relaxation of build rate - ELEHYD_"&$A$1 -> step 2 relaxation of build rate - ELEHYD_IND
D22: ="EBldRateStep_Hyd_2_"&$A$1 -> EBldRateStep_Hyd_2_IND | F22: ACT,NEWFLO | H22: UC_ACT | I22: -1 | L22: 0 | M22: 5
C23: ="UELC-Bld_ELEHYD-step3_"&$A$1 -> UELC-Bld_ELEHYD-step3_IND | D23: =$D$7 -> *[_]IND* | E23: ELCHYD | H23: UC_NCAP | I23: =I17 -> 1 | N23: ="step 3 relaxation of build rate - ELEHYD_"&$A$1 -> step 3 relaxation of build rate - ELEHYD_IND
D24: ="EBldRateStep_Hyd_3_"&$A$1 -> EBldRateStep_Hyd_3_IND | F24: ACT,NEWFLO | H24: UC_ACT | I24: -1 | L24: 0 | M24: 5
A25: wn | C25: ="UELC-Inv"&RIGHT(HistoricalBuilds!$N$1,2)&"_"&A25&"_"&$A$1 -> UELC-Inv19_wn_IND | D25: =$D$7 -> *[_]IND* | E25: ELCWIN | G25: UP | J25: 1 | L25: =SUMIFS(HistoricalBuilds!$C$2:$C$300,HistoricalBuilds!$A$2:$A$300,IND!A$1,HistoricalBuilds!$B$2:$B$300,IND!$A25)*$L$1 -> 4.6 | M25: 4
A26: sl | C26: ="UELC-Inv"&RIGHT(HistoricalBuilds!$N$1,2)&"_"&A26&"_"&$A$1 -> UELC-Inv19_sl_IND | D26: =$D$7 -> *[_]IND* | E26: ELCSOL | G26: UP | J26: 1 | L26: =SUMIFS(HistoricalBuilds!$C$2:$C$300,HistoricalBuilds!$A$2:$A$300,IND!A$1,HistoricalBuilds!$B$2:$B$300,IND!$A26)*$L$1 -> 9.203568 | M26: 4
A27: he | C27: ="UELC-Inv"&RIGHT(HistoricalBuilds!$N$1,2)&"_"&A27&"_"&$A$1 -> UELC-Inv19_he_IND | D27: =$D$7 -> *[_]IND* | E27: ELCHYD | G27: UP | J27: 1 | L27: =SUMIFS(HistoricalBuilds!$C$2:$C$300,HistoricalBuilds!$A$2:$A$300,IND!A$1,HistoricalBuilds!$B$2:$B$300,IND!$A27)*$L$1 -> 4.713 | M27: 4

Sheet JPN
A1: =MID(CELL( "filename",A1),FIND("]",CELL( "filename",A1))+1,10) -> JPN | L1: =AFR!$L$1 -> 1
C2: ~UC_Sets: R_S: AllRegions
C3: ~UC_Sets: T_E:
H5: ="~UC_T: UC_RHST~LO~"&HistoricalBuilds!$N$1 -> ~UC_T: UC_RHST~LO~2019
C6: UC_N | D6: PSET_PN | E6: Pset_CI | F6: UC_ATTR | G6: LimType | H6: Attribute | I6: LHS | J6: UC_NCAP | K6: UC_NCAP~RHS | L6: UC_RHST | M6: UC_RHST~0 | N6: UC_Desc
C7: ="UELC-Bld_ELEWIN_"&$A$1 -> UELC-Bld_ELEWIN_JPN | D7: =VLOOKUP("1"&$A$1,'WEPSReg-Countrymap'!$D$2:$E$232,2,FALSE) -> *[_]JPN* | E7: ELCWIN | F7: NCAP,GROWTH | J7: 1.15 | K7: 1 | L7: 0 | M7: 5 | N7: ="Annual build rate (GW/Year) of ELEWIN_"&$A$1 -> Annual build rate (GW/Year) of ELEWIN_JPN
D8: ="EBldRateStep_Win_2_"&$A$1&",EBldRateStep_Win_3_"&$A$1 -> EBldRateStep_Win_2_JPN,EBldRateStep_Win_3_JPN | F8: ACT,NEWFLO | H8: UC_ACT | I8: 1
C9: ="UELC-Bld_ELEWIN-step2_"&$A$1 -> UELC-Bld_ELEWIN-step2_JPN | D9: =$D$7 -> *[_]JPN* | E9: ELCWIN | H9: UC_NCAP | I9: 0.85 | N9: ="step 2 relaxation of build rate - ELEWIN_"&$A$1 -> step 2 relaxation of build rate - ELEWIN_JPN
D10: ="EBldRateStep_Win_2_"&$A$1 -> EBldRateStep_Win_2_JPN | F10: ACT,NEWFLO | H10: UC_ACT | I10: -1 | L10: 0 | M10: 5
C11: ="UELC-Bld_ELEWIN-step3_"&$A$1 -> UELC-Bld_ELEWIN-step3_JPN | D11: =$D$7 -> *[_]JPN* | E11: ELCWIN | H11: UC_NCAP | I11: 1 | N11: ="step 3 relaxation of build rate - ELEWIN_"&$A$1 -> step 3 relaxation of build rate - ELEWIN_JPN
D12: ="EBldRateStep_Win_3_"&$A$1 -> EBldRateStep_Win_3_JPN | F12: ACT,NEWFLO | H12: UC_ACT | I12: -1 | L12: 0 | M12: 5
C13: ="UELC-Bld_ELESOL_"&$A$1 -> UELC-Bld_ELESOL_JPN | D13: =$D$7 -> *[_]JPN* | E13: ELCSOL | F13: NCAP,GROWTH | J13: 1.15 | K13: 1 | L13: 0 | M13: 5 | N13: ="Annual build rate (GW/Year) of ELESOL_"&$A$1 -> Annual build rate (GW/Year) of ELESOL_JPN
D14: ="EBldRateStep_Sol_2_"&$A$1&",EBldRateStep_Sol_3_"&$A$1 -> EBldRateStep_Sol_2_JPN,EBldRateStep_Sol_3_JPN | F14: ACT,NEWFLO | H14: UC_ACT | I14: 1
C15: ="UELC-Bld_ELESOL-step2_"&$A$1 -> UELC-Bld_ELESOL-step2_JPN | D15: =$D$7 -> *[_]JPN* | E15: ELCSOL | H15: UC_NCAP | I15: =I9 -> 0.85 | N15: ="step 2 relaxation of build rate - ELESOL_"&$A$1 -> step 2 relaxation of build rate - ELESOL_JPN
D16: ="EBldRateStep_Sol_2_"&$A$1 -> EBldRateStep_Sol_2_JPN | F16: ACT,NEWFLO | H16: UC_ACT | I16: -1 | L16: 0 | M16: 5
C17: ="UELC-Bld_ELESOL-step3_"&$A$1 -> UELC-Bld_ELESOL-step3_JPN | D17: =$D$7 -> *[_]JPN* | E17: ELCSOL | H17: UC_NCAP | I17: =I11 -> 1 | N17: ="step 3 relaxation of build rate - ELESOL_"&$A$1 -> step 3 relaxation of build rate - ELESOL_JPN
D18: ="EBldRateStep_Sol_3_"&$A$1 -> EBldRateStep_Sol_3_JPN | F18: ACT,NEWFLO | H18: UC_ACT | I18: -1 | L18: 0 | M18: 5
C19: ="UELC-Bld_ELEHYD_"&$A$1 -> UELC-Bld_ELEHYD_JPN | D19: =$D$7 -> *[_]JPN* | E19: ELCHYD | F19: NCAP,GROWTH | J19: 1.15 | K19: 1 | L19: 0 | M19: 5 | N19: ="Annual build rate (GW/Year) of ELEHYD_"&$A$1 -> Annual build rate (GW/Year) of ELEHYD_JPN
D20: ="EBldRateStep_Hyd_2_"&$A$1&",EBldRateStep_Hyd_3_"&$A$1 -> EBldRateStep_Hyd_2_JPN,EBldRateStep_Hyd_3_JPN | F20: ACT,NEWFLO | H20: UC_ACT | I20: 1
C21: ="UELC-Bld_ELEHYD-step2_"&$A$1 -> UELC-Bld_ELEHYD-step2_JPN | D21: =$D$7 -> *[_]JPN* | E21: ELCHYD | H21: UC_NCAP | I21: =I15 -> 0.85 | N21: ="step 2 relaxation of build rate - ELEHYD_"&$A$1 -> step 2 relaxation of build rate - ELEHYD_JPN
D22: ="EBldRateStep_Hyd_2_"&$A$1 -> EBldRateStep_Hyd_2_JPN | F22: ACT,NEWFLO | H22: UC_ACT | I22: -1 | L22: 0 | M22: 5
C23: ="UELC-Bld_ELEHYD-step3_"&$A$1 -> UELC-Bld_ELEHYD-step3_JPN | D23: =$D$7 -> *[_]JPN* | E23: ELCHYD | H23: UC_NCAP | I23: =I17 -> 1 | N23: ="step 3 relaxation of build rate - ELEHYD_"&$A$1 -> step 3 relaxation of build rate - ELEHYD_JPN
D24: ="EBldRateStep_Hyd_3_"&$A$1 -> EBldRateStep_Hyd_3_JPN | F24: ACT,NEWFLO | H24: UC_ACT | I24: -1 | L24: 0 | M24: 5
A25: wn | C25: ="UELC-Inv"&RIGHT(HistoricalBuilds!$N$1,2)&"_"&A25&"_"&$A$1 -> UELC-Inv19_wn_JPN | D25: =$D$7 -> *[_]JPN* | E25: ELCWIN | G25: UP | J25: 1 | L25: =SUMIFS(HistoricalBuilds!$C$2:$C$300,HistoricalBuilds!$A$2:$A$300,JPN!A$1,HistoricalBuilds!$B$2:$B$300,JPN!$A25)*$L$1 -> 0.578 | M25: 4
A26: sl | C26: ="UELC-Inv"&RIGHT(HistoricalBuilds!$N$1,2)&"_"&A26&"_"&$A$1 -> UELC-Inv19_sl_JPN | D26: =$D$7 -> *[_]JPN* | E26: ELCSOL | G26: UP | J26: 1 | L26: =SUMIFS(HistoricalBuilds!$C$2:$C$300,HistoricalBuilds!$A$2:$A$300,JPN!A$1,HistoricalBuilds!$B$2:$B$300,JPN!$A26)*$L$1 -> 10.811 | M26: 4
A27: he | C27: ="UELC-Inv"&RIGHT(HistoricalBuilds!$N$1,2)&"_"&A27&"_"&$A$1 -> UELC-Inv19_he_JPN | D27: =$D$7 -> *[_]JPN* | E27: ELCHYD | G27: UP | J27: 1 | L27: =SUMIFS(HistoricalBuilds!$C$2:$C$300,HistoricalBuilds!$A$2:$A$300,JPN!A$1,HistoricalBuilds!$B$2:$B$300,JPN!$A27)*$L$1 -> 1.716 | M27: 4

Sheet MID
A1: =MID(CELL( "filename",A1),FIND("]",CELL( "filename",A1))+1,10) -> MID | L1: =AFR!$L$1 -> 1
C2: ~UC_Sets: R_S: AllRegions
C3: ~UC_Sets: T_E:
H5: ="~UC_T: UC_RHST~LO~"&HistoricalBuilds!$N$1 -> ~UC_T: UC_RHST~LO~2019
C6: UC_N | D6: PSET_PN | E6: Pset_CI | F6: UC_ATTR | G6: LimType | H6: Attribute | I6: LHS | J6: UC_NCAP | K6: UC_NCAP~RHS | L6: UC_RHST | M6: UC_RHST~0 | N6: UC_Desc
C7: ="UELC-Bld_ELEWIN_"&$A$1 -> UELC-Bld_ELEWIN_MID | D7: =VLOOKUP("1"&$A$1,'WEPSReg-Countrymap'!$D$2:$E$232,2,FALSE) -> *[_]ARE*,*[_]BHR*,*[_]CYP*,*[_]IRN*,*[_]IRQ*,*[_]JOR*,*[_]KWT*,*[_]LBN*,*[_]OMN*,*[_]PSE*,*[_]QAT*,*[_]SAU*,*[_]SYR*,*[_]YEM* | E7: ELCWIN | F7: NCAP,GROWTH | J7: 1.15 | K7: 1 | L7: 0 | M7: 5 | N7: ="Annual build rate (GW/Year) of ELEWIN_"&$A$1 -> Annual build rate (GW/Year) of ELEWIN_MID
D8: ="EBldRateStep_Win_2_"&$A$1&",EBldRateStep_Win_3_"&$A$1 -> EBldRateStep_Win_2_MID,EBldRateStep_Win_3_MID | F8: ACT,NEWFLO | H8: UC_ACT | I8: 1
C9: ="UELC-Bld_ELEWIN-step2_"&$A$1 -> UELC-Bld_ELEWIN-step2_MID | D9: =$D$7 -> *[_]ARE*,*[_]BHR*,*[_]CYP*,*[_]IRN*,*[_]IRQ*,*[_]JOR*,*[_]KWT*,*[_]LBN*,*[_]OMN*,*[_]PSE*,*[_]QAT*,*[_]SAU*,*[_]SYR*,*[_]YEM* | E9: ELCWIN | H9: UC_NCAP | I9: 0.85 | N9: ="step 2 relaxation of build rate - ELEWIN_"&$A$1 -> step 2 relaxation of build rate - ELEWIN_MID
D10: ="EBldRateStep_Win_2_"&$A$1 -> EBldRateStep_Win_2_MID | F10: ACT,NEWFLO | H10: UC_ACT | I10: -1 | L10: 0 | M10: 5
C11: ="UELC-Bld_ELEWIN-step3_"&$A$1 -> UELC-Bld_ELEWIN-step3_MID | D11: =$D$7 -> *[_]ARE*,*[_]BHR*,*[_]CYP*,*[_]IRN*,*[_]IRQ*,*[_]JOR*,*[_]KWT*,*[_]LBN*,*[_]OMN*,*[_]PSE*,*[_]QAT*,*[_]SAU*,*[_]SYR*,*[_]YEM* | E11: ELCWIN | H11: UC_NCAP | I11: 1 | N11: ="step 3 relaxation of build rate - ELEWIN_"&$A$1 -> step 3 relaxation of build rate - ELEWIN_MID
D12: ="EBldRateStep_Win_3_"&$A$1 -> EBldRateStep_Win_3_MID | F12: ACT,NEWFLO | H12: UC_ACT | I12: -1 | L12: 0 | M12: 5
C13: ="UELC-Bld_ELESOL_"&$A$1 -> UELC-Bld_ELESOL_MID | D13: =$D$7 -> *[_]ARE*,*[_]BHR*,*[_]CYP*,*[_]IRN*,*[_]IRQ*,*[_]JOR*,*[_]KWT*,*[_]LBN*,*[_]OMN*,*[_]PSE*,*[_]QAT*,*[_]SAU*,*[_]SYR*,*[_]YEM* | E13: ELCSOL | F13: NCAP,GROWTH | J13: 1.15 | K13: 1 | L13: 0 | M13: 5 | N13: ="Annual build rate (GW/Year) of ELESOL_"&$A$1 -> Annual build rate (GW/Year) of ELESOL_MID
D14: ="EBldRateStep_Sol_2_"&$A$1&",EBldRateStep_Sol_3_"&$A$1 -> EBldRateStep_Sol_2_MID,EBldRateStep_Sol_3_MID | F14: ACT,NEWFLO | H14: UC_ACT | I14: 1
C15: ="UELC-Bld_ELESOL-step2_"&$A$1 -> UELC-Bld_ELESOL-step2_MID | D15: =$D$7 -> *[_]ARE*,*[_]BHR*,*[_]CYP*,*[_]IRN*,*[_]IRQ*,*[_]JOR*,*[_]KWT*,*[_]LBN*,*[_]OMN*,*[_]PSE*,*[_]QAT*,*[_]SAU*,*[_]SYR*,*[_]YEM* | E15: ELCSOL | H15: UC_NCAP | I15: =I9 -> 0.85 | N15: ="step 2 relaxation of build rate - ELESOL_"&$A$1 -> step 2 relaxation of build rate - ELESOL_MID
D16: ="EBldRateStep_Sol_2_"&$A$1 -> EBldRateStep_Sol_2_MID | F16: ACT,NEWFLO | H16: UC_ACT | I16: -1 | L16: 0 | M16: 5
C17: ="UELC-Bld_ELESOL-step3_"&$A$1 -> UELC-Bld_ELESOL-step3_MID | D17: =$D$7 -> *[_]ARE*,*[_]BHR*,*[_]CYP*,*[_]IRN*,*[_]IRQ*,*[_]JOR*,*[_]KWT*,*[_]LBN*,*[_]OMN*,*[_]PSE*,*[_]QAT*,*[_]SAU*,*[_]SYR*,*[_]YEM* | E17: ELCSOL | H17: UC_NCAP | I17: =I11 -> 1 | N17: ="step 3 relaxation of build rate - ELESOL_"&$A$1 -> step 3 relaxation of build rate - ELESOL_MID
D18: ="EBldRateStep_Sol_3_"&$A$1 -> EBldRateStep_Sol_3_MID | F18: ACT,NEWFLO | H18: UC_ACT | I18: -1 | L18: 0 | M18: 5
C19: ="UELC-Bld_ELEHYD_"&$A$1 -> UELC-Bld_ELEHYD_MID | D19: =$D$7 -> *[_]ARE*,*[_]BHR*,*[_]CYP*,*[_]IRN*,*[_]IRQ*,*[_]JOR*,*[_]KWT*,*[_]LBN*,*[_]OMN*,*[_]PSE*,*[_]QAT*,*[_]SAU*,*[_]SYR*,*[_]YEM* | E19: ELCHYD | F19: NCAP,GROWTH | J19: 1.15 | K19: 1 | L19: 0 | M19: 5 | N19: ="Annual build rate (GW/Year) of ELEHYD_"&$A$1 -> Annual build rate (GW/Year) of ELEHYD_MID
D20: ="EBldRateStep_Hyd_2_"&$A$1&",EBldRateStep_Hyd_3_"&$A$1 -> EBldRateStep_Hyd_2_MID,EBldRateStep_Hyd_3_MID | F20: ACT,NEWFLO | H20: UC_ACT | I20: 1
C21: ="UELC-Bld_ELEHYD-step2_"&$A$1 -> UELC-Bld_ELEHYD-step2_MID | D21: =$D$7 -> *[_]ARE*,*[_]BHR*,*[_]CYP*,*[_]IRN*,*[_]IRQ*,*[_]JOR*,*[_]KWT*,*[_]LBN*,*[_]OMN*,*[_]PSE*,*[_]QAT*,*[_]SAU*,*[_]SYR*,*[_]YEM* | E21: ELCHYD | H21: UC_NCAP | I21: =I15 -> 0.85 | N21: ="step 2 relaxation of build rate - ELEHYD_"&$A$1 -> step 2 relaxation of build rate - ELEHYD_MID
D22: ="EBldRateStep_Hyd_2_"&$A$1 -> EBldRateStep_Hyd_2_MID | F22: ACT,NEWFLO | H22: UC_ACT | I22: -1 | L22: 0 | M22: 5
C23: ="UELC-Bld_ELEHYD-step3_"&$A$1 -> UELC-Bld_ELEHYD-step3_MID | D23: =$D$7 -> *[_]ARE*,*[_]BHR*,*[_]CYP*,*[_]IRN*,*[_]IRQ*,*[_]JOR*,*[_]KWT*,*[_]LBN*,*[_]OMN*,*[_]PSE*,*[_]QAT*,*[_]SAU*,*[_]SYR*,*[_]YEM* | E23: ELCHYD | H23: UC_NCAP | I23: =I17 -> 1 | N23: ="step 3 relaxation of build rate - ELEHYD_"&$A$1 -> step 3 relaxation of build rate - ELEHYD_MID
D24: ="EBldRateStep_Hyd_3_"&$A$1 -> EBldRateStep_Hyd_3_MID | F24: ACT,NEWFLO | H24: UC_ACT | I24: -1 | L24: 0 | M24: 5
A25: wn | C25: ="UELC-Inv"&RIGHT(HistoricalBuilds!$N$1,2)&"_"&A25&"_"&$A$1 -> UELC-Inv19_wn_MID | D25: =$D$7 -> *[_]ARE*,*[_]BHR*,*[_]CYP*,*[_]IRN*,*[_]IRQ*,*[_]JOR*,*[_]KWT*,*[_]LBN*,*[_]OMN*,*[_]PSE*,*[_]QAT*,*[_]SAU*,*[_]SYR*,*[_]YEM* | E25: ELCWIN | G25: UP | J25: 1 | L25: =SUMIFS(HistoricalBuilds!$C$2:$C$300,HistoricalBuilds!$A$2:$A$300,MID!A$1,HistoricalBuilds!$B$2:$B$300,MID!$A25)*$L$1 -> 0.1891 | M25: 4
A26: sl | C26: ="UELC-Inv"&RIGHT(HistoricalBuilds!$N$1,2)&"_"&A26&"_"&$A$1 -> UELC-Inv19_sl_MID | D26: =$D$7 -> *[_]ARE*,*[_]BHR*,*[_]CYP*,*[_]IRN*,*[_]IRQ*,*[_]JOR*,*[_]KWT*,*[_]LBN*,*[_]OMN*,*[_]PSE*,*[_]QAT*,*[_]SAU*,*[_]SYR*,*[_]YEM* | E26: ELCSOL | G26: UP | J26: 1 | L26: =SUMIFS(HistoricalBuilds!$C$2:$C$300,HistoricalBuilds!$A$2:$A$300,MID!A$1,HistoricalBuilds!$B$2:$B$300,MID!$A26)*$L$1 -> 1.2028 | M26: 4
A27: he | C27: ="UELC-Inv"&RIGHT(HistoricalBuilds!$N$1,2)&"_"&A27&"_"&$A$1 -> UELC-Inv19_he_MID | D27: =$D$7 -> *[_]ARE*,*[_]BHR*,*[_]CYP*,*[_]IRN*,*[_]IRQ*,*[_]JOR*,*[_]KWT*,*[_]LBN*,*[_]OMN*,*[_]PSE*,*[_]QAT*,*[_]SAU*,*[_]SYR*,*[_]YEM* | E27: ELCHYD | G27: UP | J27: 1 | L27: =SUMIFS(HistoricalBuilds!$C$2:$C$300,HistoricalBuilds!$A$2:$A$300,MID!A$1,HistoricalBuilds!$B$2:$B$300,MID!$A27)*$L$1 -> 1.567 | M27: 4

Sheet MXC
A1: =MID(CELL( "filename",A1),FIND("]",CELL( "filename",A1))+1,10) -> MXC | L1: =AFR!$L$1 -> 1
C2: ~UC_Sets: R_S: AllRegions
C3: ~UC_Sets: T_E:
H5: ="~UC_T: UC_RHST~LO~"&HistoricalBuilds!$N$1 -> ~UC_T: UC_RHST~LO~2019
C6: UC_N | D6: PSET_PN | E6: Pset_CI | F6: UC_ATTR | G6: LimType | H6: Attribute | I6: LHS | J6: UC_NCAP | K6: UC_NCAP~RHS | L6: UC_RHST | M6: UC_RHST~0 | N6: UC_Desc
C7: ="UELC-Bld_ELEWIN_"&$A$1 -> UELC-Bld_ELEWIN_MXC | D7: =VLOOKUP("1"&$A$1,'WEPSReg-Countrymap'!$D$2:$E$232,2,FALSE) -> *[_]MEX* | E7: ELCWIN | F7: NCAP,GROWTH | J7: 1.15 | K7: 1 | L7: 0 | M7: 5 | N7: ="Annual build rate (GW/Year) of ELEWIN_"&$A$1 -> Annual build rate (GW/Year) of ELEWIN_MXC
D8: ="EBldRateStep_Win_2_"&$A$1&",EBldRateStep_Win_3_"&$A$1 -> EBldRateStep_Win_2_MXC,EBldRateStep_Win_3_MXC | F8: ACT,NEWFLO | H8: UC_ACT | I8: 1
C9: ="UELC-Bld_ELEWIN-step2_"&$A$1 -> UELC-Bld_ELEWIN-step2_MXC | D9: =$D$7 -> *[_]MEX* | E9: ELCWIN | H9: UC_NCAP | I9: 0.85 | N9: ="step 2 relaxation of build rate - ELEWIN_"&$A$1 -> step 2 relaxation of build rate - ELEWIN_MXC
D10: ="EBldRateStep_Win_2_"&$A$1 -> EBldRateStep_Win_2_MXC | F10: ACT,NEWFLO | H10: UC_ACT | I10: -1 | L10: 0 | M10: 5
C11: ="UELC-Bld_ELEWIN-step3_"&$A$1 -> UELC-Bld_ELEWIN-step3_MXC | D11: =$D$7 -> *[_]MEX* | E11: ELCWIN | H11: UC_NCAP | I11: 1 | N11: ="step 3 relaxation of build rate - ELEWIN_"&$A$1 -> step 3 relaxation of build rate - ELEWIN_MXC
D12: ="EBldRateStep_Win_3_"&$A$1 -> EBldRateStep_Win_3_MXC | F12: ACT,NEWFLO | H12: UC_ACT | I12: -1 | L12: 0 | M12: 5
C13: ="UELC-Bld_ELESOL_"&$A$1 -> UELC-Bld_ELESOL_MXC | D13: =$D$7 -> *[_]MEX* | E13: ELCSOL | F13: NCAP,GROWTH | J13: 1.15 | K13: 1 | L13: 0 | M13: 5 | N13: ="Annual build rate (GW/Year) of ELESOL_"&$A$1 -> Annual build rate (GW/Year) of ELESOL_MXC
D14: ="EBldRateStep_Sol_2_"&$A$1&",EBldRateStep_Sol_3_"&$A$1 -> EBldRateStep_Sol_2_MXC,EBldRateStep_Sol_3_MXC | F14: ACT,NEWFLO | H14: UC_ACT | I14: 1
C15: ="UELC-Bld_ELESOL-step2_"&$A$1 -> UELC-Bld_ELESOL-step2_MXC | D15: =$D$7 -> *[_]MEX* | E15: ELCSOL | H15: UC_NCAP | I15: =I9 -> 0.85 | N15: ="step 2 relaxation of build rate - ELESOL_"&$A$1 -> step 2 relaxation of build rate - ELESOL_MXC
D16: ="EBldRateStep_Sol_2_"&$A$1 -> EBldRateStep_Sol_2_MXC | F16: ACT,NEWFLO | H16: UC_ACT | I16: -1 | L16: 0 | M16: 5
C17: ="UELC-Bld_ELESOL-step3_"&$A$1 -> UELC-Bld_ELESOL-step3_MXC | D17: =$D$7 -> *[_]MEX* | E17: ELCSOL | H17: UC_NCAP | I17: =I11 -> 1 | N17: ="step 3 relaxation of build rate - ELESOL_"&$A$1 -> step 3 relaxation of build rate - ELESOL_MXC
D18: ="EBldRateStep_Sol_3_"&$A$1 -> EBldRateStep_Sol_3_MXC | F18: ACT,NEWFLO | H18: UC_ACT | I18: -1 | L18: 0 | M18: 5
C19: ="UELC-Bld_ELEHYD_"&$A$1 -> UELC-Bld_ELEHYD_MXC | D19: =$D$7 -> *[_]MEX* | E19: ELCHYD | F19: NCAP,GROWTH | J19: 1.15 | K19: 1 | L19: 0 | M19: 5 | N19: ="Annual build rate (GW/Year) of ELEHYD_"&$A$1 -> Annual build rate (GW/Year) of ELEHYD_MXC
D20: ="EBldRateStep_Hyd_2_"&$A$1&",EBldRateStep_Hyd_3_"&$A$1 -> EBldRateStep_Hyd_2_MXC,EBldRateStep_Hyd_3_MXC | F20: ACT,NEWFLO | H20: UC_ACT | I20: 1
C21: ="UELC-Bld_ELEHYD-step2_"&$A$1 -> UELC-Bld_ELEHYD-step2_MXC | D21: =$D$7 -> *[_]MEX* | E21: ELCHYD | H21: UC_NCAP | I21: =I15 -> 0.85 | N21: ="step 2 relaxation of build rate - ELEHYD_"&$A$1 -> step 2 relaxation of build rate - ELEHYD_MXC
D22: ="EBldRateStep_Hyd_2_"&$A$1 -> EBldRateStep_Hyd_2_MXC | F22: ACT,NEWFLO | H22: UC_ACT | I22: -1 | L22: 0 | M22: 5
C23: ="UELC-Bld_ELEHYD-step3_"&$A$1 -> UELC-Bld_ELEHYD-step3_MXC | D23: =$D$7 -> *[_]MEX* | E23: ELCHYD | H23: UC_NCAP | I23: =I17 -> 1 | N23: ="step 3 relaxation of build rate - ELEHYD_"&$A$1 -> step 3 relaxation of build rate - ELEHYD_MXC
D24: ="EBldRateStep_Hyd_3_"&$A$1 -> EBldRateStep_Hyd_3_MXC | F24: ACT,NEWFLO | H24: UC_ACT | I24: -1 | L24: 0 | M24: 5
A25: wn | C25: ="UELC-Inv"&RIGHT(HistoricalBuilds!$N$1,2)&"_"&A25&"_"&$A$1 -> UELC-Inv19_wn_MXC | D25: =$D$7 -> *[_]MEX* | E25: ELCWIN | G25: UP | J25: 1 | L25: =SUMIFS(HistoricalBuilds!$C$2:$C$9999,HistoricalBuilds!$A$2:$A$9999,MXC!A$1,HistoricalBuilds!$B$2:$B$9999,MXC!$A25)*$L$1 -> 1.357 | M25: 4
A26: sl | C26: ="UELC-Inv"&RIGHT(HistoricalBuilds!$N$1,2)&"_"&A26&"_"&$A$1 -> UELC-Inv19_sl_MXC | D26: =$D$7 -> *[_]MEX* | E26: ELCSOL | G26: UP | J26: 1 | L26: =SUMIFS(HistoricalBuilds!$C$2:$C$9999,HistoricalBuilds!$A$2:$A$9999,MXC!A$1,HistoricalBuilds!$B$2:$B$9999,MXC!$A26)*$L$1 -> 2.471392 | M26: 4
A27: he | C27: ="UELC-Inv"&RIGHT(HistoricalBuilds!$N$1,2)&"_"&A27&"_"&$A$1 -> UELC-Inv19_he_MXC | D27: =$D$7 -> *[_]MEX* | E27: ELCHYD | G27: UP | J27: 1 | L27: =SUMIFS(HistoricalBuilds!$C$2:$C$9999,HistoricalBuilds!$A$2:$A$9999,MXC!A$1,HistoricalBuilds!$B$2:$B$9999,MXC!$A27)*$L$1 -> 2.714 | M27: 4

Sheet RUS
A1: =MID(CELL( "filename",A1),FIND("]",CELL( "filename",A1))+1,10) -> RUS | L1: =AFR!$L$1 -> 1
C2: ~UC_Sets: R_S: AllRegions
C3: ~UC_Sets: T_E:
H5: ="~UC_T: UC_RHST~LO~"&HistoricalBuilds!$N$1 -> ~UC_T: UC_RHST~LO~2019
C6: UC_N | D6: PSET_PN | E6: Pset_CI | F6: UC_ATTR | G6: LimType | H6: Attribute | I6: LHS | J6: UC_NCAP | K6: UC_NCAP~RHS | L6: UC_RHST | M6: UC_RHST~0 | N6: UC_Desc
C7: ="UELC-Bld_ELEWIN_"&$A$1 -> UELC-Bld_ELEWIN_RUS | D7: =VLOOKUP("1"&$A$1,'WEPSReg-Countrymap'!$D$2:$E$232,2,FALSE) -> *[_]RUS* | E7: ELCWIN | F7: NCAP,GROWTH | J7: 1.15 | K7: 1 | L7: 0 | M7: 5 | N7: ="Annual build rate (GW/Year) of ELEWIN_"&$A$1 -> Annual build rate (GW/Year) of ELEWIN_RUS
D8: ="EBldRateStep_Win_2_"&$A$1&",EBldRateStep_Win_3_"&$A$1 -> EBldRateStep_Win_2_RUS,EBldRateStep_Win_3_RUS | F8: ACT,NEWFLO | H8: UC_ACT | I8: 1
C9: ="UELC-Bld_ELEWIN-step2_"&$A$1 -> UELC-Bld_ELEWIN-step2_RUS | D9: =$D$7 -> *[_]RUS* | E9: ELCWIN | H9: UC_NCAP | I9: 0.85 | N9: ="step 2 relaxation of build rate - ELEWIN_"&$A$1 -> step 2 relaxation of build rate - ELEWIN_RUS
D10: ="EBldRateStep_Win_2_"&$A$1 -> EBldRateStep_Win_2_RUS | F10: ACT,NEWFLO | H10: UC_ACT | I10: -1 | L10: 0 | M10: 5
C11: ="UELC-Bld_ELEWIN-step3_"&$A$1 -> UELC-Bld_ELEWIN-step3_RUS | D11: =$D$7 -> *[_]RUS* | E11: ELCWIN | H11: UC_NCAP | I11: 1 | N11: ="step 3 relaxation of build rate - ELEWIN_"&$A$1 -> step 3 relaxation of build rate - ELEWIN_RUS
D12: ="EBldRateStep_Win_3_"&$A$1 -> EBldRateStep_Win_3_RUS | F12: ACT,NEWFLO | H12: UC_ACT | I12: -1 | L12: 0 | M12: 5
C13: ="UELC-Bld_ELESOL_"&$A$1 -> UELC-Bld_ELESOL_RUS | D13: =$D$7 -> *[_]RUS* | E13: ELCSOL | F13: NCAP,GROWTH | J13: 1.15 | K13: 1 | L13: 0 | M13: 5 | N13: ="Annual build rate (GW/Year) of ELESOL_"&$A$1 -> Annual build rate (GW/Year) of ELESOL_RUS
D14: ="EBldRateStep_Sol_2_"&$A$1&",EBldRateStep_Sol_3_"&$A$1 -> EBldRateStep_Sol_2_RUS,EBldRateStep_Sol_3_RUS | F14: ACT,NEWFLO | H14: UC_ACT | I14: 1
C15: ="UELC-Bld_ELESOL-step2_"&$A$1 -> UELC-Bld_ELESOL-step2_RUS | D15: =$D$7 -> *[_]RUS* | E15: ELCSOL | H15: UC_NCAP | I15: =I9 -> 0.85 | N15: ="step 2 relaxation of build rate - ELESOL_"&$A$1 -> step 2 relaxation of build rate - ELESOL_RUS
D16: ="EBldRateStep_Sol_2_"&$A$1 -> EBldRateStep_Sol_2_RUS | F16: ACT,NEWFLO | H16: UC_ACT | I16: -1 | L16: 0 | M16: 5
C17: ="UELC-Bld_ELESOL-step3_"&$A$1 -> UELC-Bld_ELESOL-step3_RUS | D17: =$D$7 -> *[_]RUS* | E17: ELCSOL | H17: UC_NCAP | I17: =I11 -> 1 | N17: ="step 3 relaxation of build rate - ELESOL_"&$A$1 -> step 3 relaxation of build rate - ELESOL_RUS
D18: ="EBldRateStep_Sol_3_"&$A$1 -> EBldRateStep_Sol_3_RUS | F18: ACT,NEWFLO | H18: UC_ACT | I18: -1 | L18: 0 | M18: 5
C19: ="UELC-Bld_ELEHYD_"&$A$1 -> UELC-Bld_ELEHYD_RUS | D19: =$D$7 -> *[_]RUS* | E19: ELCHYD | F19: NCAP,GROWTH | J19: 1.15 | K19: 1 | L19: 0 | M19: 5 | N19: ="Annual build rate (GW/Year) of ELEHYD_"&$A$1 -> Annual build rate (GW/Year) of ELEHYD_RUS
D20: ="EBldRateStep_Hyd_2_"&$A$1&",EBldRateStep_Hyd_3_"&$A$1 -> EBldRateStep_Hyd_2_RUS,EBldRateStep_Hyd_3_RUS | F20: ACT,NEWFLO | H20: UC_ACT | I20: 1
C21: ="UELC-Bld_ELEHYD-step2_"&$A$1 -> UELC-Bld_ELEHYD-step2_RUS | D21: =$D$7 -> *[_]RUS* | E21: ELCHYD | H21: UC_NCAP | I21: =I15 -> 0.85 | N21: ="step 2 relaxation of build rate - ELEHYD_"&$A$1 -> step 2 relaxation of build rate - ELEHYD_RUS
D22: ="EBldRateStep_Hyd_2_"&$A$1 -> EBldRateStep_Hyd_2_RUS | F22: ACT,NEWFLO | H22: UC_ACT | I22: -1 | L22: 0 | M22: 5
C23: ="UELC-Bld_ELEHYD-step3_"&$A$1 -> UELC-Bld_ELEHYD-step3_RUS | D23: =$D$7 -> *[_]RUS* | E23: ELCHYD | H23: UC_NCAP | I23: =I17 -> 1 | N23: ="step 3 relaxation of build rate - ELEHYD_"&$A$1 -> step 3 relaxation of build rate - ELEHYD_RUS
D24: ="EBldRateStep_Hyd_3_"&$A$1 -> EBldRateStep_Hyd_3_RUS | F24: ACT,NEWFLO | H24: UC_ACT | I24: -1 | L24: 0 | M24: 5
A25: wn | C25: ="UELC-Inv"&RIGHT(HistoricalBuilds!$N$1,2)&"_"&A25&"_"&$A$1 -> UELC-Inv19_wn_RUS | D25: =$D$7 -> *[_]RUS* | E25: ELCWIN | G25: UP | J25: 1 | L25: =SUMIFS(HistoricalBuilds!$C$2:$C$300,HistoricalBuilds!$A$2:$A$300,RUS!A$1,HistoricalBuilds!$B$2:$B$300,RUS!$A25)*$L$1 -> 0.671 | M25: 4
A26: sl | C26: ="UELC-Inv"&RIGHT(HistoricalBuilds!$N$1,2)&"_"&A26&"_"&$A$1 -> UELC-Inv19_sl_RUS | D26: =$D$7 -> *[_]RUS* | E26: ELCSOL | G26: UP | J26: 1 | L26: =SUMIFS(HistoricalBuilds!$C$2:$C$300,HistoricalBuilds!$A$2:$A$300,RUS!A$1,HistoricalBuilds!$B$2:$B$300,RUS!$A26)*$L$1 -> 0.26032 | M26: 4
A27: he | C27: ="UELC-Inv"&RIGHT(HistoricalBuilds!$N$1,2)&"_"&A27&"_"&$A$1 -> UELC-Inv19_he_RUS | D27: =$D$7 -> *[_]RUS* | E27: ELCHYD | G27: UP | J27: 1 | L27: =SUMIFS(HistoricalBuilds!$C$2:$C$300,HistoricalBuilds!$A$2:$A$300,RUS!A$1,HistoricalBuilds!$B$2:$B$300,RUS!$A27)*$L$1 -> 2.8871 | M27: 4

Sheet SKO
A1: =MID(CELL( "filename",A1),FIND("]",CELL( "filename",A1))+1,10) -> SKO | L1: =AFR!$L$1 -> 1
C2: ~UC_Sets: R_S: AllRegions
C3: ~UC_Sets: T_E:
H5: ="~UC_T: UC_RHST~LO~"&HistoricalBuilds!$N$1 -> ~UC_T: UC_RHST~LO~2019
C6: UC_N | D6: PSET_PN | E6: Pset_CI | F6: UC_ATTR | G6: LimType | H6: Attribute | I6: LHS | J6: UC_NCAP | K6: UC_NCAP~RHS | L6: UC_RHST | M6: UC_RHST~0 | N6: UC_Desc
C7: ="UELC-Bld_ELEWIN_"&$A$1 -> UELC-Bld_ELEWIN_SKO | D7: =VLOOKUP("1"&$A$1,'WEPSReg-Countrymap'!$D$2:$E$232,2,FALSE) -> *[_]KOR* | E7: ELCWIN | F7: NCAP,GROWTH | J7: 1.15 | K7: 1 | L7: 0 | M7: 5 | N7: ="Annual build rate (GW/Year) of ELEWIN_"&$A$1 -> Annual build rate (GW/Year) of ELEWIN_SKO
D8: ="EBldRateStep_Win_2_"&$A$1&",EBldRateStep_Win_3_"&$A$1 -> EBldRateStep_Win_2_SKO,EBldRateStep_Win_3_SKO | F8: ACT,NEWFLO | H8: UC_ACT | I8: 1
C9: ="UELC-Bld_ELEWIN-step2_"&$A$1 -> UELC-Bld_ELEWIN-step2_SKO | D9: =$D$7 -> *[_]KOR* | E9: ELCWIN | H9: UC_NCAP | I9: 0.85 | N9: ="step 2 relaxation of build rate - ELEWIN_"&$A$1 -> step 2 relaxation of build rate - ELEWIN_SKO
D10: ="EBldRateStep_Win_2_"&$A$1 -> EBldRateStep_Win_2_SKO | F10: ACT,NEWFLO | H10: UC_ACT | I10: -1 | L10: 0 | M10: 5
C11: ="UELC-Bld_ELEWIN-step3_"&$A$1 -> UELC-Bld_ELEWIN-step3_SKO | D11: =$D$7 -> *[_]KOR* | E11: ELCWIN | H11: UC_NCAP | I11: 1 | N11: ="step 3 relaxation of build rate - ELEWIN_"&$A$1 -> step 3 relaxation of build rate - ELEWIN_SKO
D12: ="EBldRateStep_Win_3_"&$A$1 -> EBldRateStep_Win_3_SKO | F12: ACT,NEWFLO | H12: UC_ACT | I12: -1 | L12: 0 | M12: 5
C13: ="UELC-Bld_ELESOL_"&$A$1 -> UELC-Bld_ELESOL_SKO | D13: =$D$7 -> *[_]KOR* | E13: ELCSOL | F13: NCAP,GROWTH | J13: 1.15 | K13: 1 | L13: 0 | M13: 5 | N13: ="Annual build rate (GW/Year) of ELESOL_"&$A$1 -> Annual build rate (GW/Year) of ELESOL_SKO
D14: ="EBldRateStep_Sol_2_"&$A$1&",EBldRateStep_Sol_3_"&$A$1 -> EBldRateStep_Sol_2_SKO,EBldRateStep_Sol_3_SKO | F14: ACT,NEWFLO | H14: UC_ACT | I14: 1
C15: ="UELC-Bld_ELESOL-step2_"&$A$1 -> UELC-Bld_ELESOL-step2_SKO | D15: =$D$7 -> *[_]KOR* | E15: ELCSOL | H15: UC_NCAP | I15: =I9 -> 0.85 | N15: ="step 2 relaxation of build rate - ELESOL_"&$A$1 -> step 2 relaxation of build rate - ELESOL_SKO
D16: ="EBldRateStep_Sol_2_"&$A$1 -> EBldRateStep_Sol_2_SKO | F16: ACT,NEWFLO | H16: UC_ACT | I16: -1 | L16: 0 | M16: 5
C17: ="UELC-Bld_ELESOL-step3_"&$A$1 -> UELC-Bld_ELESOL-step3_SKO | D17: =$D$7 -> *[_]KOR* | E17: ELCSOL | H17: UC_NCAP | I17: =I11 -> 1 | N17: ="step 3 relaxation of build rate - ELESOL_"&$A$1 -> step 3 relaxation of build rate - ELESOL_SKO
D18: ="EBldRateStep_Sol_3_"&$A$1 -> EBldRateStep_Sol_3_SKO | F18: ACT,NEWFLO | H18: UC_ACT | I18: -1 | L18: 0 | M18: 5
C19: ="UELC-Bld_ELEHYD_"&$A$1 -> UELC-Bld_ELEHYD_SKO | D19: =$D$7 -> *[_]KOR* | E19: ELCHYD | F19: NCAP,GROWTH | J19: 1.15 | K19: 1 | L19: 0 | M19: 5 | N19: ="Annual build rate (GW/Year) of ELEHYD_"&$A$1 -> Annual build rate (GW/Year) of ELEHYD_SKO
D20: ="EBldRateStep_Hyd_2_"&$A$1&",EBldRateStep_Hyd_3_"&$A$1 -> EBldRateStep_Hyd_2_SKO,EBldRateStep_Hyd_3_SKO | F20: ACT,NEWFLO | H20: UC_ACT | I20: 1
C21: ="UELC-Bld_ELEHYD-step2_"&$A$1 -> UELC-Bld_ELEHYD-step2_SKO | D21: =$D$7 -> *[_]KOR* | E21: ELCHYD | H21: UC_NCAP | I21: =I15 -> 0.85 | N21: ="step 2 relaxation of build rate - ELEHYD_"&$A$1 -> step 2 relaxation of build rate - ELEHYD_SKO
D22: ="EBldRateStep_Hyd_2_"&$A$1 -> EBldRateStep_Hyd_2_SKO | F22: ACT,NEWFLO | H22: UC_ACT | I22: -1 | L22: 0 | M22: 5
C23: ="UELC-Bld_ELEHYD-step3_"&$A$1 -> UELC-Bld_ELEHYD-step3_SKO | D23: =$D$7 -> *[_]KOR* | E23: ELCHYD | H23: UC_NCAP | I23: =I17 -> 1 | N23: ="step 3 relaxation of build rate - ELEHYD_"&$A$1 -> step 3 relaxation of build rate - ELEHYD_SKO
D24: ="EBldRateStep_Hyd_3_"&$A$1 -> EBldRateStep_Hyd_3_SKO | F24: ACT,NEWFLO | H24: UC_ACT | I24: -1 | L24: 0 | M24: 5
A25: wn | C25: ="UELC-Inv"&RIGHT(HistoricalBuilds!$N$1,2)&"_"&A25&"_"&$A$1 -> UELC-Inv19_wn_SKO | D25: =$D$7 -> *[_]KOR* | E25: ELCWIN | G25: UP | J25: 1 | L25: =SUMIFS(HistoricalBuilds!$C$2:$C$300,HistoricalBuilds!$A$2:$A$300,SKO!A$1,HistoricalBuilds!$B$2:$B$300,SKO!$A25)*$L$1 -> 0.235 | M25: 4
A26: sl | C26: ="UELC-Inv"&RIGHT(HistoricalBuilds!$N$1,2)&"_"&A26&"_"&$A$1 -> UELC-Inv19_sl_SKO | D26: =$D$7 -> *[_]KOR* | E26: ELCSOL | G26: UP | J26: 1 | L26: =SUMIFS(HistoricalBuilds!$C$2:$C$300,HistoricalBuilds!$A$2:$A$300,SKO!A$1,HistoricalBuilds!$B$2:$B$300,SKO!$A26)*$L$1 -> 2.265066 | M26: 4
A27: he | C27: ="UELC-Inv"&RIGHT(HistoricalBuilds!$N$1,2)&"_"&A27&"_"&$A$1 -> UELC-Inv19_he_SKO | D27: =$D$7 -> *[_]KOR* | E27: ELCHYD | G27: UP | J27: 1 | L27: =SUMIFS(HistoricalBuilds!$C$2:$C$300,HistoricalBuilds!$A$2:$A$300,SKO!A$1,HistoricalBuilds!$B$2:$B$300,SKO!$A27)*$L$1 -> 0.421 | M27: 4

Sheet URA
A1: =MID(CELL( "filename",A1),FIND("]",CELL( "filename",A1))+1,10) -> URA | L1: =AFR!$L$1 -> 1
C2: ~UC_Sets: R_S: AllRegions
C3: ~UC_Sets: T_E:
H5: ="~UC_T: UC_RHST~LO~"&HistoricalBuilds!$N$1 -> ~UC_T: UC_RHST~LO~2019
C6: UC_N | D6: PSET_PN | E6: Pset_CI | F6: UC_ATTR | G6: LimType | H6: Attribute | I6: LHS | J6: UC_NCAP | K6: UC_NCAP~RHS | L6: UC_RHST | M6: UC_RHST~0 | N6: UC_Desc
C7: ="UELC-Bld_ELEWIN_"&$A$1 -> UELC-Bld_ELEWIN_URA | D7: =VLOOKUP("1"&$A$1,'WEPSReg-Countrymap'!$D$2:$E$232,2,FALSE) -> *[_]ALB*,*[_]ARM*,*[_]AZE*,*[_]BGR*,*[_]BIH*,*[_]BLR*,*[_]FRO*,*[_]GEO*,*[_]HRV*,*[_]KAZ*,*[_]KGZ*,*[_]KSV*,*[_]LIE*,*[_]LTU*,*[_]LVA*,*[_]MDA*,*[_]MKD*,*[_]MLT*,*[_]MNE*,*[_]ROM*,*[_]SRB*,*[_]TJK*,*[_]TKM*,*[_]UKR*,*[_]UZB* | E7: ELCWIN | F7: NCAP,GROWTH | J7: 1.15 | K7: 1 | L7: 0 | M7: 5 | N7: ="Annual build rate (GW/Year) of ELEWIN_"&$A$1 -> Annual build rate (GW/Year) of ELEWIN_URA
D8: ="EBldRateStep_Win_2_"&$A$1&",EBldRateStep_Win_3_"&$A$1 -> EBldRateStep_Win_2_URA,EBldRateStep_Win_3_URA | F8: ACT,NEWFLO | H8: UC_ACT | I8: 1
C9: ="UELC-Bld_ELEWIN-step2_"&$A$1 -> UELC-Bld_ELEWIN-step2_URA | D9: =$D$7 -> *[_]ALB*,*[_]ARM*,*[_]AZE*,*[_]BGR*,*[_]BIH*,*[_]BLR*,*[_]FRO*,*[_]GEO*,*[_]HRV*,*[_]KAZ*,*[_]KGZ*,*[_]KSV*,*[_]LIE*,*[_]LTU*,*[_]LVA*,*[_]MDA*,*[_]MKD*,*[_]MLT*,*[_]MNE*,*[_]ROM*,*[_]SRB*,*[_]TJK*,*[_]TKM*,*[_]UKR*,*[_]UZB* | E9: ELCWIN | H9: UC_NCAP | I9: 0.85 | N9: ="step 2 relaxation of build rate - ELEWIN_"&$A$1 -> step 2 relaxation of build rate - ELEWIN_URA
D10: ="EBldRateStep_Win_2_"&$A$1 -> EBldRateStep_Win_2_URA | F10: ACT,NEWFLO | H10: UC_ACT | I10: -1 | L10: 0 | M10: 5
C11: ="UELC-Bld_ELEWIN-step3_"&$A$1 -> UELC-Bld_ELEWIN-step3_URA | D11: =$D$7 -> *[_]ALB*,*[_]ARM*,*[_]AZE*,*[_]BGR*,*[_]BIH*,*[_]BLR*,*[_]FRO*,*[_]GEO*,*[_]HRV*,*[_]KAZ*,*[_]KGZ*,*[_]KSV*,*[_]LIE*,*[_]LTU*,*[_]LVA*,*[_]MDA*,*[_]MKD*,*[_]MLT*,*[_]MNE*,*[_]ROM*,*[_]SRB*,*[_]TJK*,*[_]TKM*,*[_]UKR*,*[_]UZB* | E11: ELCWIN | H11: UC_NCAP | I11: 1 | N11: ="step 3 relaxation of build rate - ELEWIN_"&$A$1 -> step 3 relaxation of build rate - ELEWIN_URA
D12: ="EBldRateStep_Win_3_"&$A$1 -> EBldRateStep_Win_3_URA | F12: ACT,NEWFLO | H12: UC_ACT | I12: -1 | L12: 0 | M12: 5
C13: ="UELC-Bld_ELESOL_"&$A$1 -> UELC-Bld_ELESOL_URA | D13: =$D$7 -> *[_]ALB*,*[_]ARM*,*[_]AZE*,*[_]BGR*,*[_]BIH*,*[_]BLR*,*[_]FRO*,*[_]GEO*,*[_]HRV*,*[_]KAZ*,*[_]KGZ*,*[_]KSV*,*[_]LIE*,*[_]LTU*,*[_]LVA*,*[_]MDA*,*[_]MKD*,*[_]MLT*,*[_]MNE*,*[_]ROM*,*[_]SRB*,*[_]TJK*,*[_]TKM*,*[_]UKR*,*[_]UZB* | E13: ELCSOL | F13: NCAP,GROWTH | J13: 1.15 | K13: 1 | L13: 0 | M13: 5 | N13: ="Annual build rate (GW/Year) of ELESOL_"&$A$1 -> Annual build rate (GW/Year) of ELESOL_URA
D14: ="EBldRateStep_Sol_2_"&$A$1&",EBldRateStep_Sol_3_"&$A$1 -> EBldRateStep_Sol_2_URA,EBldRateStep_Sol_3_URA | F14: ACT,NEWFLO | H14: UC_ACT | I14: 1
C15: ="UELC-Bld_ELESOL-step2_"&$A$1 -> UELC-Bld_ELESOL-step2_URA | D15: =$D$7 -> *[_]ALB*,*[_]ARM*,*[_]AZE*,*[_]BGR*,*[_]BIH*,*[_]BLR*,*[_]FRO*,*[_]GEO*,*[_]HRV*,*[_]KAZ*,*[_]KGZ*,*[_]KSV*,*[_]LIE*,*[_]LTU*,*[_]LVA*,*[_]MDA*,*[_]MKD*,*[_]MLT*,*[_]MNE*,*[_]ROM*,*[_]SRB*,*[_]TJK*,*[_]TKM*,*[_]UKR*,*[_]UZB* | E15: ELCSOL | H15: UC_NCAP | I15: =I9 -> 0.85 | N15: ="step 2 relaxation of build rate - ELESOL_"&$A$1 -> step 2 relaxation of build rate - ELESOL_URA
D16: ="EBldRateStep_Sol_2_"&$A$1 -> EBldRateStep_Sol_2_URA | F16: ACT,NEWFLO | H16: UC_ACT | I16: -1 | L16: 0 | M16: 5
C17: ="UELC-Bld_ELESOL-step3_"&$A$1 -> UELC-Bld_ELESOL-step3_URA | D17: =$D$7 -> *[_]ALB*,*[_]ARM*,*[_]AZE*,*[_]BGR*,*[_]BIH*,*[_]BLR*,*[_]FRO*,*[_]GEO*,*[_]HRV*,*[_]KAZ*,*[_]KGZ*,*[_]KSV*,*[_]LIE*,*[_]LTU*,*[_]LVA*,*[_]MDA*,*[_]MKD*,*[_]MLT*,*[_]MNE*,*[_]ROM*,*[_]SRB*,*[_]TJK*,*[_]TKM*,*[_]UKR*,*[_]UZB* | E17: ELCSOL | H17: UC_NCAP | I17: =I11 -> 1 | N17: ="step 3 relaxation of build rate - ELESOL_"&$A$1 -> step 3 relaxation of build rate - ELESOL_URA
D18: ="EBldRateStep_Sol_3_"&$A$1 -> EBldRateStep_Sol_3_URA | F18: ACT,NEWFLO | H18: UC_ACT | I18: -1 | L18: 0 | M18: 5
C19: ="UELC-Bld_ELEHYD_"&$A$1 -> UELC-Bld_ELEHYD_URA | D19: =$D$7 -> *[_]ALB*,*[_]ARM*,*[_]AZE*,*[_]BGR*,*[_]BIH*,*[_]BLR*,*[_]FRO*,*[_]GEO*,*[_]HRV*,*[_]KAZ*,*[_]KGZ*,*[_]KSV*,*[_]LIE*,*[_]LTU*,*[_]LVA*,*[_]MDA*,*[_]MKD*,*[_]MLT*,*[_]MNE*,*[_]ROM*,*[_]SRB*,*[_]TJK*,*[_]TKM*,*[_]UKR*,*[_]UZB* | E19: ELCHYD | F19: NCAP,GROWTH | J19: 1.15 | K19: 1 | L19: 0 | M19: 5 | N19: ="Annual build rate (GW/Year) of ELEHYD_"&$A$1 -> Annual build rate (GW/Year) of ELEHYD_URA
D20: ="EBldRateStep_Hyd_2_"&$A$1&",EBldRateStep_Hyd_3_"&$A$1 -> EBldRateStep_Hyd_2_URA,EBldRateStep_Hyd_3_URA | F20: ACT,NEWFLO | H20: UC_ACT | I20: 1
C21: ="UELC-Bld_ELEHYD-step2_"&$A$1 -> UELC-Bld_ELEHYD-step2_URA | D21: =$D$7 -> *[_]ALB*,*[_]ARM*,*[_]AZE*,*[_]BGR*,*[_]BIH*,*[_]BLR*,*[_]FRO*,*[_]GEO*,*[_]HRV*,*[_]KAZ*,*[_]KGZ*,*[_]KSV*,*[_]LIE*,*[_]LTU*,*[_]LVA*,*[_]MDA*,*[_]MKD*,*[_]MLT*,*[_]MNE*,*[_]ROM*,*[_]SRB*,*[_]TJK*,*[_]TKM*,*[_]UKR*,*[_]UZB* | E21: ELCHYD | H21: UC_NCAP | I21: =I15 -> 0.85 | N21: ="step 2 relaxation of build rate - ELEHYD_"&$A$1 -> step 2 relaxation of build rate - ELEHYD_URA
D22: ="EBldRateStep_Hyd_2_"&$A$1 -> EBldRateStep_Hyd_2_URA | F22: ACT,NEWFLO | H22: UC_ACT | I22: -1 | L22: 0 | M22: 5
C23: ="UELC-Bld_ELEHYD-step3_"&$A$1 -> UELC-Bld_ELEHYD-step3_URA | D23: =$D$7 -> *[_]ALB*,*[_]ARM*,*[_]AZE*,*[_]BGR*,*[_]BIH*,*[_]BLR*,*[_]FRO*,*[_]GEO*,*[_]HRV*,*[_]KAZ*,*[_]KGZ*,*[_]KSV*,*[_]LIE*,*[_]LTU*,*[_]LVA*,*[_]MDA*,*[_]MKD*,*[_]MLT*,*[_]MNE*,*[_]ROM*,*[_]SRB*,*[_]TJK*,*[_]TKM*,*[_]UKR*,*[_]UZB* | E23: ELCHYD | H23: UC_NCAP | I23: =I17 -> 1 | N23: ="step 3 relaxation of build rate - ELEHYD_"&$A$1 -> step 3 relaxation of build rate - ELEHYD_URA
D24: ="EBldRateStep_Hyd_3_"&$A$1 -> EBldRateStep_Hyd_3_URA | F24: ACT,NEWFLO | H24: UC_ACT | I24: -1 | L24: 0 | M24: 5
A25: wn | C25: ="UELC-Inv"&RIGHT(HistoricalBuilds!$N$1,2)&"_"&A25&"_"&$A$1 -> UELC-Inv19_wn_URA | D25: =$D$7 -> *[_]ALB*,*[_]ARM*,*[_]AZE*,*[_]BGR*,*[_]BIH*,*[_]BLR*,*[_]FRO*,*[_]GEO*,*[_]HRV*,*[_]KAZ*,*[_]KGZ*,*[_]KSV*,*[_]LIE*,*[_]LTU*,*[_]LVA*,*[_]MDA*,*[_]MKD*,*[_]MLT*,*[_]MNE*,*[_]ROM*,*[_]SRB*,*[_]TJK*,*[_]TKM*,*[_]UKR*,*[_]UZB* | E25: ELCWIN | G25: UP | J25: 1 | L25: =SUMIFS(HistoricalBuilds!$C$2:$C$300,HistoricalBuilds!$A$2:$A$300,URA!A$1,HistoricalBuilds!$B$2:$B$300,URA!$A25)*$L$1 -> 1.17036 | M25: 4
A26: sl | C26: ="UELC-Inv"&RIGHT(HistoricalBuilds!$N$1,2)&"_"&A26&"_"&$A$1 -> UELC-Inv19_sl_URA | D26: =$D$7 -> *[_]ALB*,*[_]ARM*,*[_]AZE*,*[_]BGR*,*[_]BIH*,*[_]BLR*,*[_]FRO*,*[_]GEO*,*[_]HRV*,*[_]KAZ*,*[_]KGZ*,*[_]KSV*,*[_]LIE*,*[_]LTU*,*[_]LVA*,*[_]MDA*,*[_]MKD*,*[_]MLT*,*[_]MNE*,*[_]ROM*,*[_]SRB*,*[_]TJK*,*[_]TKM*,*[_]UKR*,*[_]UZB* | E26: ELCSOL | G26: UP | J26: 1 | L26: =SUMIFS(HistoricalBuilds!$C$2:$C$300,HistoricalBuilds!$A$2:$A$300,URA!A$1,HistoricalBuilds!$B$2:$B$300,URA!$A26)*$L$1 -> 1.168042 | M26: 4
A27: he | C27: ="UELC-Inv"&RIGHT(HistoricalBuilds!$N$1,2)&"_"&A27&"_"&$A$1 -> UELC-Inv19_he_URA | D27: =$D$7 -> *[_]ALB*,*[_]ARM*,*[_]AZE*,*[_]BGR*,*[_]BIH*,*[_]BLR*,*[_]FRO*,*[_]GEO*,*[_]HRV*,*[_]KAZ*,*[_]KGZ*,*[_]KSV*,*[_]LIE*,*[_]LTU*,*[_]LVA*,*[_]MDA*,*[_]MKD*,*[_]MLT*,*[_]MNE*,*[_]ROM*,*[_]SRB*,*[_]TJK*,*[_]TKM*,*[_]UKR*,*[_]UZB* | E27: ELCHYD | G27: UP | J27: 1 | L27: =SUMIFS(HistoricalBuilds!$C$2:$C$300,HistoricalBuilds!$A$2:$A$300,URA!A$1,HistoricalBuilds!$B$2:$B$300,URA!$A27)*$L$1 -> 23.348 | M27: 4

Sheet USA
A1: =MID(CELL( "filename",A1),FIND("]",CELL( "filename",A1))+1,10) -> USA | L1: =AFR!$L$1 -> 1
C2: ~UC_Sets: R_S: AllRegions
C3: ~UC_Sets: T_E:
H5: ="~UC_T: UC_RHST~LO~"&HistoricalBuilds!$N$1 -> ~UC_T: UC_RHST~LO~2019
C6: UC_N | D6: PSET_PN | E6: Pset_CI | F6: UC_ATTR | G6: LimType | H6: Attribute | I6: LHS | J6: UC_NCAP | K6: UC_NCAP~RHS | L6: UC_RHST | M6: UC_RHST~0 | N6: UC_Desc
C7: ="UELC-Bld_ELEWIN_"&$A$1 -> UELC-Bld_ELEWIN_USA | D7: =VLOOKUP("1"&$A$1,'WEPSReg-Countrymap'!$D$2:$E$232,2,FALSE) -> *[_]USA* | E7: ELCWIN | F7: NCAP,GROWTH | J7: 1.15 | K7: 1 | L7: 0 | M7: 5 | N7: ="Annual build rate (GW/Year) of ELEWIN_"&$A$1 -> Annual build rate (GW/Year) of ELEWIN_USA
D8: ="EBldRateStep_Win_2_"&$A$1&",EBldRateStep_Win_3_"&$A$1 -> EBldRateStep_Win_2_USA,EBldRateStep_Win_3_USA | F8: ACT,NEWFLO | H8: UC_ACT | I8: 1
C9: ="UELC-Bld_ELEWIN-step2_"&$A$1 -> UELC-Bld_ELEWIN-step2_USA | D9: =$D$7 -> *[_]USA* | E9: ELCWIN | H9: UC_NCAP | I9: 0.85 | N9: ="step 2 relaxation of build rate - ELEWIN_"&$A$1 -> step 2 relaxation of build rate - ELEWIN_USA
D10: ="EBldRateStep_Win_2_"&$A$1 -> EBldRateStep_Win_2_USA | F10: ACT,NEWFLO | H10: UC_ACT | I10: -1 | L10: 0 | M10: 5
C11: ="UELC-Bld_ELEWIN-step3_"&$A$1 -> UELC-Bld_ELEWIN-step3_USA | D11: =$D$7 -> *[_]USA* | E11: ELCWIN | H11: UC_NCAP | I11: 1 | N11: ="step 3 relaxation of build rate - ELEWIN_"&$A$1 -> step 3 relaxation of build rate - ELEWIN_USA
D12: ="EBldRateStep_Win_3_"&$A$1 -> EBldRateStep_Win_3_USA | F12: ACT,NEWFLO | H12: UC_ACT | I12: -1 | L12: 0 | M12: 5
C13: ="UELC-Bld_ELESOL_"&$A$1 -> UELC-Bld_ELESOL_USA | D13: =$D$7 -> *[_]USA* | E13: ELCSOL | F13: NCAP,GROWTH | J13: 1.15 | K13: 1 | L13: 0 | M13: 5 | N13: ="Annual build rate (GW/Year) of ELESOL_"&$A$1 -> Annual build rate (GW/Year) of ELESOL_USA
D14: ="EBldRateStep_Sol_2_"&$A$1&",EBldRateStep_Sol_3_"&$A$1 -> EBldRateStep_Sol_2_USA,EBldRateStep_Sol_3_USA | F14: ACT,NEWFLO | H14: UC_ACT | I14: 1
C15: ="UELC-Bld_ELESOL-step2_"&$A$1 -> UELC-Bld_ELESOL-step2_USA | D15: =$D$7 -> *[_]USA* | E15: ELCSOL | H15: UC_NCAP | I15: =I9 -> 0.85 | N15: ="step 2 relaxation of build rate - ELESOL_"&$A$1 -> step 2 relaxation of build rate - ELESOL_USA
D16: ="EBldRateStep_Sol_2_"&$A$1 -> EBldRateStep_Sol_2_USA | F16: ACT,NEWFLO | H16: UC_ACT | I16: -1 | L16: 0 | M16: 5
C17: ="UELC-Bld_ELESOL-step3_"&$A$1 -> UELC-Bld_ELESOL-step3_USA | D17: =$D$7 -> *[_]USA* | E17: ELCSOL | H17: UC_NCAP | I17: =I11 -> 1 | N17: ="step 3 relaxation of build rate - ELESOL_"&$A$1 -> step 3 relaxation of build rate - ELESOL_USA
D18: ="EBldRateStep_Sol_3_"&$A$1 -> EBldRateStep_Sol_3_USA | F18: ACT,NEWFLO | H18: UC_ACT | I18: -1 | L18: 0 | M18: 5
C19: ="UELC-Bld_ELEHYD_"&$A$1 -> UELC-Bld_ELEHYD_USA | D19: =$D$7 -> *[_]USA* | E19: ELCHYD | F19: NCAP,GROWTH | J19: 1.15 | K19: 1 | L19: 0 | M19: 5 | N19: ="Annual build rate (GW/Year) of ELEHYD_"&$A$1 -> Annual build rate (GW/Year) of ELEHYD_USA
D20: ="EBldRateStep_Hyd_2_"&$A$1&",EBldRateStep_Hyd_3_"&$A$1 -> EBldRateStep_Hyd_2_USA,EBldRateStep_Hyd_3_USA | F20: ACT,NEWFLO | H20: UC_ACT | I20: 1
C21: ="UELC-Bld_ELEHYD-step2_"&$A$1 -> UELC-Bld_ELEHYD-step2_USA | D21: =$D$7 -> *[_]USA* | E21: ELCHYD | H21: UC_NCAP | I21: =I15 -> 0.85 | N21: ="step 2 relaxation of build rate - ELEHYD_"&$A$1 -> step 2 relaxation of build rate - ELEHYD_USA
D22: ="EBldRateStep_Hyd_2_"&$A$1 -> EBldRateStep_Hyd_2_USA | F22: ACT,NEWFLO | H22: UC_ACT | I22: -1 | L22: 0 | M22: 5
C23: ="UELC-Bld_ELEHYD-step3_"&$A$1 -> UELC-Bld_ELEHYD-step3_USA | D23: =$D$7 -> *[_]USA* | E23: ELCHYD | H23: UC_NCAP | I23: =I17 -> 1 | N23: ="step 3 relaxation of build rate - ELEHYD_"&$A$1 -> step 3 relaxation of build rate - ELEHYD_USA
D24: ="EBldRateStep_Hyd_3_"&$A$1 -> EBldRateStep_Hyd_3_USA | F24: ACT,NEWFLO | H24: UC_ACT | I24: -1 | L24: 0 | M24: 5
A25: wn | C25: ="UELC-Inv"&RIGHT(HistoricalBuilds!$N$1,2)&"_"&A25&"_"&$A$1 -> UELC-Inv19_wn_USA | D25: =$D$7 -> *[_]USA* | E25: ELCWIN | G25: UP | J25: 1 | L25: =SUMIFS(HistoricalBuilds!$C$2:$C$300,HistoricalBuilds!$A$2:$A$300,USA!A$1,HistoricalBuilds!$B$2:$B$300,USA!$A25)*$L$1 -> 13.3989 | M25: 4
A26: sl | C26: ="UELC-Inv"&RIGHT(HistoricalBuilds!$N$1,2)&"_"&A26&"_"&$A$1 -> UELC-Inv19_sl_USA | D26: =$D$7 -> *[_]USA* | E26: ELCSOL | G26: UP | J26: 1 | L26: =SUMIFS(HistoricalBuilds!$C$2:$C$300,HistoricalBuilds!$A$2:$A$300,USA!A$1,HistoricalBuilds!$B$2:$B$300,USA!$A26)*$L$1 -> 11.2741 | M26: 4
A27: he | C27: ="UELC-Inv"&RIGHT(HistoricalBuilds!$N$1,2)&"_"&A27&"_"&$A$1 -> UELC-Inv19_he_USA | D27: =$D$7 -> *[_]USA* | E27: ELCHYD | G27: UP | J27: 1 | L27: =SUMIFS(HistoricalBuilds!$C$2:$C$300,HistoricalBuilds!$A$2:$A$300,USA!A$1,HistoricalBuilds!$B$2:$B$300,USA!$A27)*$L$1 -> 3.81298 | M27: 4

Sheet togetInvCosts
C4: ~TFM_FILL-R:w=Base_ELE_Costs
C5: Scenario | D5: Attribute | E5: PSET_CI | F5: Pset_PN | G5: AllRegions
C6: Solar-EIA-c | D6: INVCOST | F6: E_SPV* | G6: 1
C7: BaseExtra | D7: INVCOST | F7: E_WON* | G7: 1
C8: fossilelc,newhydro-c | D8: INVCOST | E8: ELCCOA,ELCHYD | G8: 1

Sheet HistoricalBuilds
A1: region | B1: Tech | C1: maxbuild | E1: this is written by the MIG | N1: =MAX(P2:P6)+1 -> 2019 | P1: year
A2: AFR | B2: bm | C2: 0.21498051 | P2: 2017 | R2: =MIN(P2:P5) -> 2017
A3: ANZ | B3: bm | C3: 0.099192273 | P3: 2018 | R3: =R2&","&P3 -> 2017,2018
A4: BRZ | B4: bm | C4: 1.764659
A5: CAN | B5: bm | C5: 0.28090513
A6: CHI | B6: bm | C6: 0.62678614
A7: CSA | B7: bm | C7: 0.80362345
A8: EUR | B8: bm | C8: 1.7888642
A9: IND | B9: bm | C9: 2.3801705
A10: JPN | B10: bm | C10: 0.30159667
A11: MID | B11: bm | C11: 0.0015687858
A12: MXC | B12: bm | C12: 0.33848469
A13: OAS | B13: bm | C13: 0.47294307
A14: RUS | B14: bm | C14: 0.04292895
A15: SKO | B15: bm | C15: 0.086709826
... A185: USA | B185: ws | C185: 0.94141324

Sheet Base_ELE_Costs
A1: scenario | B1: region | C1: attribute | D1: process | E1: commodity | F1: lim_type | G1: time_slice | H1: year | I1: commodity_group | J1: currency | K1: stage | L1: sow | M1: valfield
A2: BaseEXTRA | B2: AFR_N | C2: INVCOST | D2: E_WON_Far_C1_DZA | E2: - | F2: - | G2: - | H2: 2010 | I2: - | J2: USD10 | K2: - | L2: - | M2: 3823.75 | O2: =LEFT(B2,3) -> AFR | P2: =LEFT(D2,5) -> E_WON
A3: BaseEXTRA | B3: AFR_N | C3: INVCOST | D3: E_WON_Far_C1_EGY | E3: - | F3: - | G3: - | H3: 2010 | I3: - | J3: USD10 | K3: - | L3: - | M3: 3823.75 | O3: =LEFT(B3,3) -> AFR | P3: =LEFT(D3,5) -> E_WON
A4: BaseEXTRA | B4: AFR_N | C4: INVCOST | D4: E_WON_Far_C1_ERI | E4: - | F4: - | G4: - | H4: 2010 | I4: - | J4: USD10 | K4: - | L4: - | M4: 3823.75 | O4: =LEFT(B4,3) -> AFR | P4: =LEFT(D4,5) -> E_WON
A5: BaseEXTRA | B5: AFR_N | C5: INVCOST | D5: E_WON_Far_C1_MAR | E5: - | F5: - | G5: - | H5: 2010 | I5: - | J5: USD10 | K5: - | L5: - | M5: 3823.75 | O5: =LEFT(B5,3) -> AFR | P5: =LEFT(D5,5) -> E_WON
A6: BaseEXTRA | B6: AFR_N | C6: INVCOST | D6: E_WON_Far_C1_MLI | E6: - | F6: - | G6: - | H6: 2010 | I6: - | J6: USD10 | K6: - | L6: - | M6: 3823.75 | O6: =LEFT(B6,3) -> AFR | P6: =LEFT(D6,5) -> E_WON
A7: BaseEXTRA | B7: AFR_N | C7: INVCOST | D7: E_WON_Far_C1_NER | E7: - | F7: - | G7: - | H7: 2010 | I7: - | J7: USD10 | K7: - | L7: - | M7: 3823.75 | O7: =LEFT(B7,3) -> AFR | P7: =LEFT(D7,5) -> E_WON | T7: PSET_PN | U7: Attribute | V7: AFR | W7: ANZ | X7: BRZ | Y7: CAN | Z7: CHI | AA7: CSA | AB7: EUR | AC7: IND | AD7: JPN | AE7: MID | AF7: MXC | AG7: OAS | AH7: RUS | AI7: SKO | AJ7: URA | AK7: USA
A8: BaseEXTRA | B8: AFR_N | C8: INVCOST | D8: E_WON_Far_C1_SDN | E8: - | F8: - | G8: - | H8: 2010 | I8: - | J8: USD10 | K8: - | L8: - | M8: 3823.75 | O8: =LEFT(B8,3) -> AFR | P8: =LEFT(D8,5) -> E_WON | Q8: EN_ZC | R8: 0.42
A9: BaseEXTRA | B9: AFR_N | C9: INVCOST | D9: E_WON_Far_C1_TCD | E9: - | F9: - | G9: - | H9: 2010 | I9: - | J9: USD10 | K9: - | L9: - | M9: 3823.75 | O9: =LEFT(B9,3) -> AFR | P9: =LEFT(D9,5) -> E_WON | Q9: =Q8 -> EN_ZC | R9: 1.35
A10: BaseEXTRA | B10: AFR_N | C10: INVCOST | D10: E_WON_Far_C2_DZA | E10: - | F10: - | G10: - | H10: 2010 | I10: - | J10: USD10 | K10: - | L10: - | M10: 3823.75 | O10: =LEFT(B10,3) -> AFR | P10: =LEFT(D10,5) -> E_WON | Q10: EN_Hy | R10: =R8 -> 0.42 | T10: EBldRateStep_HYD_2 | U10: INVCOST | V10: =AVERAGEIFS($M$2:$M$9999,$O$2:$O$9999,V$7,$P$2:$P$9999,$Q10)*$R10 -> 2882.9323 | W10: =AVERAGEIFS($M$2:$M$9999,$O$2:$O$9999,W$7,$P$2:$P$9999,$Q10)*$R10 -> 1460.4687 | X10: =AVERAGEIFS($M$2:$M$9999,$O$2:$O$9999,X$7,$P$2:$P$9999,$Q10)*$R10 -> 1764.8544 | Y10: =AVERAGEIFS($M$2:$M$9999,$O$2:$O$9999,Y$7,$P$2:$P$9999,$Q10)*$R10 -> 3623.7345 | Z10: =AVERAGEIFS($M$2:$M$9999,$O$2:$O$9999,Z$7,$P$2:$P$9999,$Q10)*$R10 -> 1258.8624 | AA10: =AVERAGEIFS($M$2:$M$9999,$O$2:$O$9999,AA$7,$P$2:$P$9999,$Q10)*$R10 -> 1375.9613 | AB10: =AVERAGEIFS($M$2:$M$9999,$O$2:$O$9999,AB$7,$P$2:$P$9999,$Q10)*$R10 -> 2073.6972 | AC10: =AVERAGEIFS($M$2:$M$9999,$O$2:$O$9999,AC$7,$P$2:$P$9999,$Q10)*$R10 -> 846.35397 | ... AK10: =AVERAGEIFS($M$2:$M$9999,$O$2:$O$9999,AK$7,$P$2:$P$9999,$Q10)*$R10 -> 2843.7343
A11: BaseEXTRA | B11: AFR_N | C11: INVCOST | D11: E_WON_Far_C2_EGY | E11: - | F11: - | G11: - | H11: 2010 | I11: - | J11: USD10 | K11: - | L11: - | M11: 3823.75 | O11: =LEFT(B11,3) -> AFR | P11: =LEFT(D11,5) -> E_WON | Q11: =Q10 -> EN_Hy | R11: =R9 -> 1.35 | T11: EBldRateStep_HYD_3 | U11: INVCOST | V11: =AVERAGEIFS($M$2:$M$9999,$O$2:$O$9999,V$7,$P$2:$P$9999,$Q11)*$R11 -> 9266.568 | W11: =AVERAGEIFS($M$2:$M$9999,$O$2:$O$9999,W$7,$P$2:$P$9999,$Q11)*$R11 -> 4694.3638 | X11: =AVERAGEIFS($M$2:$M$9999,$O$2:$O$9999,X$7,$P$2:$P$9999,$Q11)*$R11 -> 5672.7462 | Y11: =AVERAGEIFS($M$2:$M$9999,$O$2:$O$9999,Y$7,$P$2:$P$9999,$Q11)*$R11 -> 11647.718 | Z11: =AVERAGEIFS($M$2:$M$9999,$O$2:$O$9999,Z$7,$P$2:$P$9999,$Q11)*$R11 -> 4046.3436 | AA11: =AVERAGEIFS($M$2:$M$9999,$O$2:$O$9999,AA$7,$P$2:$P$9999,$Q11)*$R11 -> 4422.7326 | AB11: =AVERAGEIFS($M$2:$M$9999,$O$2:$O$9999,AB$7,$P$2:$P$9999,$Q11)*$R11 -> 6665.4554 | AC11: =AVERAGEIFS($M$2:$M$9999,$O$2:$O$9999,AC$7,$P$2:$P$9999,$Q11)*$R11 -> 2720.4235 | ... AK11: =AVERAGEIFS($M$2:$M$9999,$O$2:$O$9999,AK$7,$P$2:$P$9999,$Q11)*$R11 -> 9140.5744
A12: BaseEXTRA | B12: AFR_N | C12: INVCOST | D12: E_WON_Far_C2_ERI | E12: - | F12: - | G12: - | H12: 2010 | I12: - | J12: USD10 | K12: - | L12: - | M12: 3823.75 | O12: =LEFT(B12,3) -> AFR | P12: =LEFT(D12,5) -> E_WON | Q12: E_SPV | R12: =R10 -> 0.42 | T12: EBldRateStep_Sol_2 | U12: INVCOST | V12: =AVERAGEIFS($M$2:$M$9999,$O$2:$O$9999,V$7,$P$2:$P$9999,$Q12)*$R12 -> 594.7411 | W12: =AVERAGEIFS($M$2:$M$9999,$O$2:$O$9999,W$7,$P$2:$P$9999,$Q12)*$R12 -> 540.54 | X12: =AVERAGEIFS($M$2:$M$9999,$O$2:$O$9999,X$7,$P$2:$P$9999,$Q12)*$R12 -> 578.76 | Y12: =AVERAGEIFS($M$2:$M$9999,$O$2:$O$9999,Y$7,$P$2:$P$9999,$Q12)*$R12 -> 535.08 | Z12: =AVERAGEIFS($M$2:$M$9999,$O$2:$O$9999,Z$7,$P$2:$P$9999,$Q12)*$R12 -> 475.02 | AA12: =AVERAGEIFS($M$2:$M$9999,$O$2:$O$9999,AA$7,$P$2:$P$9999,$Q12)*$R12 -> 882.91183 | AB12: =AVERAGEIFS($M$2:$M$9999,$O$2:$O$9999,AB$7,$P$2:$P$9999,$Q12)*$R12 -> 522.96412 | AC12: =AVERAGEIFS($M$2:$M$9999,$O$2:$O$9999,AC$7,$P$2:$P$9999,$Q12)*$R12 -> 327.6 | ... AK12: =AVERAGEIFS($M$2:$M$9999,$O$2:$O$9999,AK$7,$P$2:$P$9999,$Q12)*$R12 -> 595.14
A13: BaseEXTRA | B13: AFR_N | C13: INVCOST | D13: E_WON_Far_C2_LBY | E13: - | F13: - | G13: - | H13: 2010 | I13: - | J13: USD10 | K13: - | L13: - | M13: 3823.75 | O13: =LEFT(B13,3) -> AFR | P13: =LEFT(D13,5) -> E_WON | Q13: =Q12 -> E_SPV | R13: =R11 -> 1.35 | T13: EBldRateStep_Sol_3 | U13: INVCOST | V13: =AVERAGEIFS($M$2:$M$9999,$O$2:$O$9999,V$7,$P$2:$P$9999,$Q13)*$R13 -> 1911.6678 | W13: =AVERAGEIFS($M$2:$M$9999,$O$2:$O$9999,W$7,$P$2:$P$9999,$Q13)*$R13 -> 1737.45 | X13: =AVERAGEIFS($M$2:$M$9999,$O$2:$O$9999,X$7,$P$2:$P$9999,$Q13)*$R13 -> 1860.3 | Y13: =AVERAGEIFS($M$2:$M$9999,$O$2:$O$9999,Y$7,$P$2:$P$9999,$Q13)*$R13 -> 1719.9 | Z13: =AVERAGEIFS($M$2:$M$9999,$O$2:$O$9999,Z$7,$P$2:$P$9999,$Q13)*$R13 -> 1526.85 | AA13: =AVERAGEIFS($M$2:$M$9999,$O$2:$O$9999,AA$7,$P$2:$P$9999,$Q13)*$R13 -> 2837.9309 | AB13: =AVERAGEIFS($M$2:$M$9999,$O$2:$O$9999,AB$7,$P$2:$P$9999,$Q13)*$R13 -> 1680.9561 | AC13: =AVERAGEIFS($M$2:$M$9999,$O$2:$O$9999,AC$7,$P$2:$P$9999,$Q13)*$R13 -> 1053 | ... AK13: =AVERAGEIFS($M$2:$M$9999,$O$2:$O$9999,AK$7,$P$2:$P$9999,$Q13)*$R13 -> 1912.95
A14: BaseEXTRA | B14: AFR_N | C14: INVCOST | D14: E_WON_Far_C2_MAR | E14: - | F14: - | G14: - | H14: 2010 | I14: - | J14: USD10 | K14: - | L14: - | M14: 3823.75 | O14: =LEFT(B14,3) -> AFR | P14: =LEFT(D14,5) -> E_WON | Q14: E_WON | R14: =R12 -> 0.42 | T14: EBldRateStep_Win_2 | U14: INVCOST | V14: =AVERAGEIFS($M$2:$M$9999,$O$2:$O$9999,V$7,$P$2:$P$9999,$Q14)*$R14 -> 1289.0713 | W14: =AVERAGEIFS($M$2:$M$9999,$O$2:$O$9999,W$7,$P$2:$P$9999,$Q14)*$R14 -> 912.25658 | X14: =AVERAGEIFS($M$2:$M$9999,$O$2:$O$9999,X$7,$P$2:$P$9999,$Q14)*$R14 -> 741.426 | Y14: =AVERAGEIFS($M$2:$M$9999,$O$2:$O$9999,Y$7,$P$2:$P$9999,$Q14)*$R14 -> 950.15455 | Z14: =AVERAGEIFS($M$2:$M$9999,$O$2:$O$9999,Z$7,$P$2:$P$9999,$Q14)*$R14 -> 646.8 | AA14: =AVERAGEIFS($M$2:$M$9999,$O$2:$O$9999,AA$7,$P$2:$P$9999,$Q14)*$R14 -> 1123.8518 | AB14: =AVERAGEIFS($M$2:$M$9999,$O$2:$O$9999,AB$7,$P$2:$P$9999,$Q14)*$R14 -> 872.79664 | AC14: =AVERAGEIFS($M$2:$M$9999,$O$2:$O$9999,AC$7,$P$2:$P$9999,$Q14)*$R14 -> 538.24615 | ... AK14: =AVERAGEIFS($M$2:$M$9999,$O$2:$O$9999,AK$7,$P$2:$P$9999,$Q14)*$R14 -> 847.18421
A15: BaseEXTRA | B15: AFR_N | C15: INVCOST | D15: E_WON_Far_C2_MLI | E15: - | F15: - | G15: - | H15: 2010 | I15: - | J15: USD10 | K15: - | L15: - | M15: 3823.75 | O15: =LEFT(B15,3) -> AFR | P15: =LEFT(D15,5) -> E_WON | Q15: =Q14 -> E_WON | R15: =R13 -> 1.35 | T15: EBldRateStep_Win_3 | U15: INVCOST | V15: =AVERAGEIFS($M$2:$M$9999,$O$2:$O$9999,V$7,$P$2:$P$9999,$Q15)*$R15 -> 4143.4436 | W15: =AVERAGEIFS($M$2:$M$9999,$O$2:$O$9999,W$7,$P$2:$P$9999,$Q15)*$R15 -> 2932.2533 | X15: =AVERAGEIFS($M$2:$M$9999,$O$2:$O$9999,X$7,$P$2:$P$9999,$Q15)*$R15 -> 2383.155 | Y15: =AVERAGEIFS($M$2:$M$9999,$O$2:$O$9999,Y$7,$P$2:$P$9999,$Q15)*$R15 -> 3054.0682 | Z15: =AVERAGEIFS($M$2:$M$9999,$O$2:$O$9999,Z$7,$P$2:$P$9999,$Q15)*$R15 -> 2079 | AA15: =AVERAGEIFS($M$2:$M$9999,$O$2:$O$9999,AA$7,$P$2:$P$9999,$Q15)*$R15 -> 3612.3806 | AB15: =AVERAGEIFS($M$2:$M$9999,$O$2:$O$9999,AB$7,$P$2:$P$9999,$Q15)*$R15 -> 2805.4178 | AC15: =AVERAGEIFS($M$2:$M$9999,$O$2:$O$9999,AC$7,$P$2:$P$9999,$Q15)*$R15 -> 1730.0769 | ... AK15: =AVERAGEIFS($M$2:$M$9999,$O$2:$O$9999,AK$7,$P$2:$P$9999,$Q15)*$R15 -> 2723.0921
A16: BaseEXTRA | B16: AFR_N | C16: INVCOST | D16: E_WON_Far_C2_MRT | E16: - | F16: - | G16: - | H16: 2010 | I16: - | J16: USD10 | K16: - | L16: - | M16: 3823.75 | O16: =LEFT(B16,3) -> AFR | P16: =LEFT(D16,5) -> E_WON
A17: BaseEXTRA | B17: AFR_N | C17: INVCOST | D17: E_WON_Far_C2_NER | E17: - | F17: - | G17: - | H17: 2010 | I17: - | J17: USD10 | K17: - | L17: - | M17: 3823.75 | O17: =LEFT(B17,3) -> AFR | P17: =LEFT(D17,5) -> E_WON
A18: BaseEXTRA | B18: AFR_N | C18: INVCOST | D18: E_WON_Far_C2_SDN | E18: - | F18: - | G18: - | H18: 2010 | I18: - | J18: USD10 | K18: - | L18: - | M18: 3823.75 | O18: =LEFT(B18,3) -> AFR | P18: =LEFT(D18,5) -> E_WON | W18: ~TFM_DINS-TS: Curr=USD10
A19: BaseEXTRA | B19: AFR_N | C19: INVCOST | D19: E_WON_Far_C2_TCD | E19: - | F19: - | G19: - | H19: 2010 | I19: - | J19: USD10 | K19: - | L19: - | M19: 3823.75 | O19: =LEFT(B19,3) -> AFR | P19: =LEFT(D19,5) -> E_WON | W19: Attribute | X19: PSET_PN | Y19: 2015
A20: BaseEXTRA | B20: AFR_N | C20: INVCOST | D20: E_WON_Far_C3_DZA | E20: - | F20: - | G20: - | H20: 2010 | I20: - | J20: USD10 | K20: - | L20: - | M20: 3823.75 | O20: =LEFT(B20,3) -> AFR | P20: =LEFT(D20,5) -> E_WON | R20: 1 | T20: =T10 -> EBldRateStep_HYD_2 | W20: INVCOST | X20: =T20&"_"&OFFSET($U$7,0,R20) -> EBldRateStep_HYD_2_AFR | Y20: =VLOOKUP(T20,$T$7:$AK$15,R20+2,FALSE) -> 2882.9323
A21: BaseEXTRA | B21: AFR_N | C21: INVCOST | D21: E_WON_Far_C3_EGY | E21: - | F21: - | G21: - | H21: 2010 | I21: - | J21: USD10 | K21: - | L21: - | M21: 3823.75 | O21: =LEFT(B21,3) -> AFR | P21: =LEFT(D21,5) -> E_WON | R21: 1 | T21: =T11 -> EBldRateStep_HYD_3 | W21: INVCOST | X21: =T21&"_"&OFFSET($U$7,0,R21) -> EBldRateStep_HYD_3_AFR | Y21: =VLOOKUP(T21,$T$7:$AK$15,R21+2,FALSE) -> 9266.568
A22: BaseEXTRA | B22: AFR_N | C22: INVCOST | D22: E_WON_Far_C3_LBY | E22: - | F22: - | G22: - | H22: 2010 | I22: - | J22: USD10 | K22: - | L22: - | M22: 3823.75 | O22: =LEFT(B22,3) -> AFR | P22: =LEFT(D22,5) -> E_WON | R22: 1 | T22: =T12 -> EBldRateStep_Sol_2 | W22: INVCOST | X22: =T22&"_"&OFFSET($U$7,0,R22) -> EBldRateStep_Sol_2_AFR | Y22: =VLOOKUP(T22,$T$7:$AK$15,R22+2,FALSE) -> 594.7411
A23: BaseEXTRA | B23: AFR_N | C23: INVCOST | D23: E_WON_Far_C3_MAR | E23: - | F23: - | G23: - | H23: 2010 | I23: - | J23: USD10 | K23: - | L23: - | M23: 3823.75 | O23: =LEFT(B23,3) -> AFR | P23: =LEFT(D23,5) -> E_WON | R23: 1 | T23: =T13 -> EBldRateStep_Sol_3 | W23: INVCOST | X23: =T23&"_"&OFFSET($U$7,0,R23) -> EBldRateStep_Sol_3_AFR | Y23: =VLOOKUP(T23,$T$7:$AK$15,R23+2,FALSE) -> 1911.6678
A24: BaseEXTRA | B24: AFR_N | C24: INVCOST | D24: E_WON_Far_C3_MLI | E24: - | F24: - | G24: - | H24: 2010 | I24: - | J24: USD10 | K24: - | L24: - | M24: 3823.75 | O24: =LEFT(B24,3) -> AFR | P24: =LEFT(D24,5) -> E_WON | R24: 1 | T24: =T14 -> EBldRateStep_Win_2 | W24: INVCOST | X24: =T24&"_"&OFFSET($U$7,0,R24) -> EBldRateStep_Win_2_AFR | Y24: =VLOOKUP(T24,$T$7:$AK$15,R24+2,FALSE) -> 1289.0713
A25: BaseEXTRA | B25: AFR_N | C25: INVCOST | D25: E_WON_Far_C3_MRT | E25: - | F25: - | G25: - | H25: 2010 | I25: - | J25: USD10 | K25: - | L25: - | M25: 3823.75 | O25: =LEFT(B25,3) -> AFR | P25: =LEFT(D25,5) -> E_WON | R25: 1 | T25: =T15 -> EBldRateStep_Win_3 | W25: INVCOST | X25: =T25&"_"&OFFSET($U$7,0,R25) -> EBldRateStep_Win_3_AFR | Y25: =VLOOKUP(T25,$T$7:$AK$15,R25+2,FALSE) -> 4143.4436
A26: BaseEXTRA | B26: AFR_N | C26: INVCOST | D26: E_WON_Far_C3_NER | E26: - | F26: - | G26: - | H26: 2010 | I26: - | J26: USD10 | K26: - | L26: - | M26: 3823.75 | O26: =LEFT(B26,3) -> AFR | P26: =LEFT(D26,5) -> E_WON | R26: =R20+1 -> 2 | T26: =T20 -> EBldRateStep_HYD_2 | W26: INVCOST | X26: =T26&"_"&OFFSET($U$7,0,R26) -> EBldRateStep_HYD_2_ANZ | Y26: =VLOOKUP(T26,$T$7:$AK$15,R26+2,FALSE) -> 1460.4687
A27: BaseEXTRA | B27: AFR_N | C27: INVCOST | D27: E_WON_Far_C3_SDN | E27: - | F27: - | G27: - | H27: 2010 | I27: - | J27: USD10 | K27: - | L27: - | M27: 3823.75 | O27: =LEFT(B27,3) -> AFR | P27: =LEFT(D27,5) -> E_WON | R27: =R21+1 -> 2 | T27: =T21 -> EBldRateStep_HYD_3 | W27: INVCOST | X27: =T27&"_"&OFFSET($U$7,0,R27) -> EBldRateStep_HYD_3_ANZ | Y27: =VLOOKUP(T27,$T$7:$AK$15,R27+2,FALSE) -> 4694.3638
A28: BaseEXTRA | B28: AFR_N | C28: INVCOST | D28: E_WON_Far_C3_TCD | E28: - | F28: - | G28: - | H28: 2010 | I28: - | J28: USD10 | K28: - | L28: - | M28: 3823.75 | O28: =LEFT(B28,3) -> AFR | P28: =LEFT(D28,5) -> E_WON | R28: =R22+1 -> 2 | T28: =T22 -> EBldRateStep_Sol_2 | W28: INVCOST | X28: =T28&"_"&OFFSET($U$7,0,R28) -> EBldRateStep_Sol_2_ANZ | Y28: =VLOOKUP(T28,$T$7:$AK$15,R28+2,FALSE) -> 540.54
A29: BaseEXTRA | B29: AFR_N | C29: INVCOST | D29: E_WON_Far_C3_TUN | E29: - | F29: - | G29: - | H29: 2010 | I29: - | J29: USD10 | K29: - | L29: - | M29: 3823.75 | O29: =LEFT(B29,3) -> AFR | P29: =LEFT(D29,5) -> E_WON | R29: =R23+1 -> 2 | T29: =T23 -> EBldRateStep_Sol_3 | W29: INVCOST | X29: =T29&"_"&OFFSET($U$7,0,R29) -> EBldRateStep_Sol_3_ANZ | Y29: =VLOOKUP(T29,$T$7:$AK$15,R29+2,FALSE) -> 1737.45
A30: BaseEXTRA | B30: AFR_N | C30: INVCOST | D30: E_WON_Far_C4_DZA | E30: - | F30: - | G30: - | H30: 2010 | I30: - | J30: USD10 | K30: - | L30: - | M30: 3823.75 | O30: =LEFT(B30,3) -> AFR | P30: =LEFT(D30,5) -> E_WON | R30: =R24+1 -> 2 | T30: =T24 -> EBldRateStep_Win_2 | W30: INVCOST | X30: =T30&"_"&OFFSET($U$7,0,R30) -> EBldRateStep_Win_2_ANZ | Y30: =VLOOKUP(T30,$T$7:$AK$15,R30+2,FALSE) -> 912.25658
A31: BaseEXTRA | B31: AFR_N | C31: INVCOST | D31: E_WON_Far_C4_EGY | E31: - | F31: - | G31: - | H31: 2010 | I31: - | J31: USD10 | K31: - | L31: - | M31: 3823.75 | O31: =LEFT(B31,3) -> AFR | P31: =LEFT(D31,5) -> E_WON | R31: =R25+1 -> 2 | T31: =T25 -> EBldRateStep_Win_3 | W31: INVCOST | X31: =T31&"_"&OFFSET($U$7,0,R31) -> EBldRateStep_Win_3_ANZ | Y31: =VLOOKUP(T31,$T$7:$AK$15,R31+2,FALSE) -> 2932.2533
A32: BaseEXTRA | B32: AFR_N | C32: INVCOST | D32: E_WON_Far_C4_LBY | E32: - | F32: - | G32: - | H32: 2010 | I32: - | J32: USD10 | K32: - | L32: - | M32: 3823.75 | O32: =LEFT(B32,3) -> AFR | P32: =LEFT(D32,5) -> E_WON | R32: =R26+1 -> 3 | T32: =T26 -> EBldRateStep_HYD_2 | W32: INVCOST | X32: =T32&"_"&OFFSET($U$7,0,R32) -> EBldRateStep_HYD_2_BRZ | Y32: =VLOOKUP(T32,$T$7:$AK$15,R32+2,FALSE) -> 1764.8544
A33: BaseEXTRA | B33: AFR_N | C33: INVCOST | D33: E_WON_Far_C4_MAR | E33: - | F33: - | G33: - | H33: 2010 | I33: - | J33: USD10 | K33: - | L33: - | M33: 3823.75 | O33: =LEFT(B33,3) -> AFR | P33: =LEFT(D33,5) -> E_WON | R33: =R27+1 -> 3 | T33: =T27 -> EBldRateStep_HYD_3 | W33: INVCOST | X33: =T33&"_"&OFFSET($U$7,0,R33) -> EBldRateStep_HYD_3_BRZ | Y33: =VLOOKUP(T33,$T$7:$AK$15,R33+2,FALSE) -> 5672.7462
A34: BaseEXTRA | B34: AFR_N | C34: INVCOST | D34: E_WON_Far_C4_MRT | E34: - | F34: - | G34: - | H34: 2010 | I34: - | J34: USD10 | K34: - | L34: - | M34: 3823.75 | O34: =LEFT(B34,3) -> AFR | P34: =LEFT(D34,5) -> E_WON | R34: =R28+1 -> 3 | T34: =T28 -> EBldRateStep_Sol_2 | W34: INVCOST | X34: =T34&"_"&OFFSET($U$7,0,R34) -> EBldRateStep_Sol_2_BRZ | Y34: =VLOOKUP(T34,$T$7:$AK$15,R34+2,FALSE) -> 578.76
A35: BaseEXTRA | B35: AFR_N | C35: INVCOST | D35: E_WON_Far_C4_NER | E35: - | F35: - | G35: - | H35: 2010 | I35: - | J35: USD10 | K35: - | L35: - | M35: 3823.75 | O35: =LEFT(B35,3) -> AFR | P35: =LEFT(D35,5) -> E_WON | R35: =R29+1 -> 3 | T35: =T29 -> EBldRateStep_Sol_3 | W35: INVCOST | X35: =T35&"_"&OFFSET($U$7,0,R35) -> EBldRateStep_Sol_3_BRZ | Y35: =VLOOKUP(T35,$T$7:$AK$15,R35+2,FALSE) -> 1860.3
A36: BaseEXTRA | B36: AFR_N | C36: INVCOST | D36: E_WON_Far_C4_SDN | E36: - | F36: - | G36: - | H36: 2010 | I36: - | J36: USD10 | K36: - | L36: - | M36: 3823.75 | O36: =LEFT(B36,3) -> AFR | P36: =LEFT(D36,5) -> E_WON | R36: =R30+1 -> 3 | T36: =T30 -> EBldRateStep_Win_2 | W36: INVCOST | X36: =T36&"_"&OFFSET($U$7,0,R36) -> EBldRateStep_Win_2_BRZ | Y36: =VLOOKUP(T36,$T$7:$AK$15,R36+2,FALSE) -> 741.426
A37: BaseEXTRA | B37: AFR_N | C37: INVCOST | D37: E_WON_Far_C4_TCD | E37: - | F37: - | G37: - | H37: 2010 | I37: - | J37: USD10 | K37: - | L37: - | M37: 3823.75 | O37: =LEFT(B37,3) -> AFR | P37: =LEFT(D37,5) -> E_WON | R37: =R31+1 -> 3 | T37: =T31 -> EBldRateStep_Win_3 | W37: INVCOST | X37: =T37&"_"&OFFSET($U$7,0,R37) -> EBldRateStep_Win_3_BRZ | Y37: =VLOOKUP(T37,$T$7:$AK$15,R37+2,FALSE) -> 2383.155
... A115: BaseEXTRA | B115: AFR_N | C115: INVCOST | D115: E_WON_Trans_C2_ERI | E115: - | F115: - | G115: - | H115: 2010 | I115: - | J115: USD10 | K115: - | L115: - | M115: 3277.5 | O115: =LEFT(B115,3) -> AFR | P115: =LEFT(D115,5) -> E_WON | R115: =R109+1 -> 16 | T115: =T109 -> EBldRateStep_Win_3 | W115: INVCOST | X115: =T115&"_"&OFFSET($U$7,0,R115) -> EBldRateStep_Win_3_USA | Y115: =VLOOKUP(T115,$T$7:$AK$15,R115+2,FALSE) -> 2723.0921
A116: BaseEXTRA | B116: AFR_N | C116: INVCOST | D116: E_WON_Trans_C2_LBY | E116: - | F116: - | G116: - | H116: 2010 | I116: - | J116: USD10 | K116: - | L116: - | M116: 3277.5 | O116: =LEFT(B116,3) -> AFR | P116: =LEFT(D116,5) -> E_WON
A117: BaseEXTRA | B117: AFR_N | C117: INVCOST | D117: E_WON_Trans_C2_MAR | E117: - | F117: - | G117: - | H117: 2010 | I117: - | J117: USD10 | K117: - | L117: - | M117: 3277.5 | O117: =LEFT(B117,3) -> AFR | P117: =LEFT(D117,5) -> E_WON
A118: BaseEXTRA | B118: AFR_N | C118: INVCOST | D118: E_WON_Trans_C2_MLI | E118: - | F118: - | G118: - | H118: 2010 | I118: - | J118: USD10 | K118: - | L118: - | M118: 3277.5 | O118: =LEFT(B118,3) -> AFR | P118: =LEFT(D118,5) -> E_WON
A119: BaseEXTRA | B119: AFR_N | C119: INVCOST | D119: E_WON_Trans_C2_NER | E119: - | F119: - | G119: - | H119: 2010 | I119: - | J119: USD10 | K119: - | L119: - | M119: 3277.5 | O119: =LEFT(B119,3) -> AFR | P119: =LEFT(D119,5) -> E_WON
A120: BaseEXTRA | B120: AFR_N | C120: INVCOST | D120: E_WON_Trans_C2_SDN | E120: - | F120: - | G120: - | H120: 2010 | I120: - | J120: USD10 | K120: - | L120: - | M120: 3277.5 | O120: =LEFT(B120,3) -> AFR | P120: =LEFT(D120,5) -> E_WON
A121: BaseEXTRA | B121: AFR_N | C121: INVCOST | D121: E_WON_Trans_C2_TCD | E121: - | F121: - | G121: - | H121: 2010 | I121: - | J121: USD10 | K121: - | L121: - | M121: 3277.5 | O121: =LEFT(B121,3) -> AFR | P121: =LEFT(D121,5) -> E_WON
A122: BaseEXTRA | B122: AFR_N | C122: INVCOST | D122: E_WON_Trans_C2_TUN | E122: - | F122: - | G122: - | H122: 2010 | I122: - | J122: USD10 | K122: - | L122: - | M122: 3277.5 | O122: =LEFT(B122,3) -> AFR | P122: =LEFT(D122,5) -> E_WON
A123: BaseEXTRA | B123: AFR_N | C123: INVCOST | D123: E_WON_Trans_C3_DZA | E123: - | F123: - | G123: - | H123: 2010 | I123: - | J123: USD10 | K123: - | L123: - | M123: 3277.5 | O123: =LEFT(B123,3) -> AFR | P123: =LEFT(D123,5) -> E_WON
A124: BaseEXTRA | B124: AFR_N | C124: INVCOST | D124: E_WON_Trans_C3_EGY | E124: - | F124: - | G124: - | H124: 2010 | I124: - | J124: USD10 | K124: - | L124: - | M124: 3277.5 | O124: =LEFT(B124,3) -> AFR | P124: =LEFT(D124,5) -> E_WON
A125: BaseEXTRA | B125: AFR_N | C125: INVCOST | D125: E_WON_Trans_C3_ERI | E125: - | F125: - | G125: - | H125: 2010 | I125: - | J125: USD10 | K125: - | L125: - | M125: 3277.5 | O125: =LEFT(B125,3) -> AFR | P125: =LEFT(D125,5) -> E_WON
A126: BaseEXTRA | B126: AFR_N | C126: INVCOST | D126: E_WON_Trans_C3_LBY | E126: - | F126: - | G126: - | H126: 2010 | I126: - | J126: USD10 | K126: - | L126: - | M126: 3277.5 | O126: =LEFT(B126,3) -> AFR | P126: =LEFT(D126,5) -> E_WON
A127: BaseEXTRA | B127: AFR_N | C127: INVCOST | D127: E_WON_Trans_C3_MAR | E127: - | F127: - | G127: - | H127: 2010 | I127: - | J127: USD10 | K127: - | L127: - | M127: 3277.5 | O127: =LEFT(B127,3) -> AFR | P127: =LEFT(D127,5) -> E_WON
... A3477: Solar-EIA-C | B3477: USA | C3477: INVCOST | D3477: E_SPV_C08_USA | E3477: - | F3477: - | G3477: - | H3477: 2010 | I3477: - | J3477: USD10 | K3477: - | L3477: - | M3477: 1417 | O3477: =LEFT(B3477,3) -> USA | P3477: =LEFT(D3477,5) -> E_SPV
O3478: =LEFT(B3478,3) | P3478: =LEFT(D3478,5)
O3479: =LEFT(B3479,3) | P3479: =LEFT(D3479,5)
O3480: =LEFT(B3480,3) | P3480: =LEFT(D3480,5)
O3481: =LEFT(B3481,3) | P3481: =LEFT(D3481,5)
O3482: =LEFT(B3482,3) | P3482: =LEFT(D3482,5)
O3483: =LEFT(B3483,3) | P3483: =LEFT(D3483,5)
O3484: =LEFT(B3484,3) | P3484: =LEFT(D3484,5)
O3485: =LEFT(B3485,3) | P3485: =LEFT(D3485,5)
O3486: =LEFT(B3486,3) | P3486: =LEFT(D3486,5)
O3487: =LEFT(B3487,3) | P3487: =LEFT(D3487,5)
O3488: =LEFT(B3488,3) | P3488: =LEFT(D3488,5)
O3489: =LEFT(B3489,3) | P3489: =LEFT(D3489,5)
... O4998: =LEFT(B4998,3) | P4998: =LEFT(D4998,5)

Sheet WEPSReg-Countrymap
B1: WEPSReg | C1: Country
A2: =IF(B2=B3,0,1) -> 0 | B2: AFR | C2: AGO | D2: =A2&B2 -> 0AFR | E2: =IF(B2=B1,E1&","&"*[_]"&C2&"*","*[_]"&C2&"*") -> *[_]AGO*
A3: =IF(B3=B4,0,1) -> 0 | B3: AFR | C3: BDI | D3: =A3&B3 -> 0AFR | E3: =IF(B3=B2,E2&","&"*[_]"&C3&"*","*[_]"&C3&"*") -> *[_]AGO*,*[_]BDI*
A4: =IF(B4=B5,0,1) -> 0 | B4: AFR | C4: BEN | D4: =A4&B4 -> 0AFR | E4: =IF(B4=B3,E3&","&"*[_]"&C4&"*","*[_]"&C4&"*") -> *[_]AGO*,*[_]BDI*,*[_]BEN*
A5: =IF(B5=B6,0,1) -> 0 | B5: AFR | C5: BFA | D5: =A5&B5 -> 0AFR | E5: =IF(B5=B4,E4&","&"*[_]"&C5&"*","*[_]"&C5&"*") -> *[_]AGO*,*[_]BDI*,*[_]BEN*,*[_]BFA*
A6: =IF(B6=B7,0,1) -> 0 | B6: AFR | C6: BWA | D6: =A6&B6 -> 0AFR | E6: =IF(B6=B5,E5&","&"*[_]"&C6&"*","*[_]"&C6&"*") -> *[_]AGO*,*[_]BDI*,*[_]BEN*,*[_]BFA*,*[_]BWA*
A7: =IF(B7=B8,0,1) -> 0 | B7: AFR | C7: CAF | D7: =A7&B7 -> 0AFR | E7: =IF(B7=B6,E6&","&"*[_]"&C7&"*","*[_]"&C7&"*") -> *[_]AGO*,*[_]BDI*,*[_]BEN*,*[_]BFA*,*[_]BWA*,*[_]CAF*
A8: =IF(B8=B9,0,1) -> 0 | B8: AFR | C8: CIV | D8: =A8&B8 -> 0AFR | E8: =IF(B8=B7,E7&","&"*[_]"&C8&"*","*[_]"&C8&"*") -> *[_]AGO*,*[_]BDI*,*[_]BEN*,*[_]BFA*,*[_]BWA*,*[_]CAF*,*[_]CIV*
A9: =IF(B9=B10,0,1) -> 0 | B9: AFR | C9: CMR | D9: =A9&B9 -> 0AFR | E9: =IF(B9=B8,E8&","&"*[_]"&C9&"*","*[_]"&C9&"*") -> *[_]AGO*,*[_]BDI*,*[_]BEN*,*[_]BFA*,*[_]BWA*,*[_]CAF*,*[_]CIV*,*[_]CMR*
A10: =IF(B10=B11,0,1) -> 0 | B10: AFR | C10: COG | D10: =A10&B10 -> 0AFR | E10: =IF(B10=B9,E9&","&"*[_]"&C10&"*","*[_]"&C10&"*") -> *[_]AGO*,*[_]BDI*,*[_]BEN*,*[_]BFA*,*[_]BWA*,*[_]CAF*,*[_]CIV*,*[_]CMR*,*[_]COG*
A11: =IF(B11=B12,0,1) -> 0 | B11: AFR | C11: COM | D11: =A11&B11 -> 0AFR | E11: =IF(B11=B10,E10&","&"*[_]"&C11&"*","*[_]"&C11&"*") -> *[_]AGO*,*[_]BDI*,*[_]BEN*,*[_]BFA*,*[_]BWA*,*[_]CAF*,*[_]CIV*,*[_]CMR*,*[_]COG*,*[_]COM*
A12: =IF(B12=B13,0,1) -> 0 | B12: AFR | C12: CPV | D12: =A12&B12 -> 0AFR | E12: =IF(B12=B11,E11&","&"*[_]"&C12&"*","*[_]"&C12&"*") -> *[_]AGO*,*[_]BDI*,*[_]BEN*,*[_]BFA*,*[_]BWA*,*[_]CAF*,*[_]CIV*,*[_]CMR*,*[_]COG*,*[_]COM*,*[_]CPV*
A13: =IF(B13=B14,0,1) -> 0 | B13: AFR | C13: DJI | D13: =A13&B13 -> 0AFR | E13: =IF(B13=B12,E12&","&"*[_]"&C13&"*","*[_]"&C13&"*") -> *[_]AGO*,*[_]BDI*,*[_]BEN*,*[_]BFA*,*[_]BWA*,*[_]CAF*,*[_]CIV*,*[_]CMR*,*[_]COG*,*[_]COM*,*[_]CPV*,*[_]DJI*
... A68: =IF(B68=B69,0,1) -> 0 | B68: CSA | C68: BOL | D68: =A68&B68 -> 0CSA | E68: =IF(B68=B67,E67&","&"*[_]"&C68&"*","*[_]"&C68&"*") -> *[_]ABW*,*[_]ANT*,*[_]ARG*,*[_]ATG*,*[_]BHS*,*[_]BLZ*,*[_]BMU*,*[_]BOL*
A69: =IF(B69=B71,0,1) -> 0 | B69: CSA | C69: BRB | D69: =A69&B69 -> 0CSA | E69: =IF(B69=B68,E68&","&"*[_]"&C69&"*","*[_]"&C69&"*") -> *[_]ABW*,*[_]ANT*,*[_]ARG*,*[_]ATG*,*[_]BHS*,*[_]BLZ*,*[_]BMU*,*[_]BOL*,*[_]BRB*
A70: =IF(B70=B72,0,1) -> 0 | B70: CSA | C70: CHL | D70: =A70&B70 -> 0CSA | E70: =IF(B70=B69,E69&","&"*[_]"&C70&"*","*[_]"&C70&"*") -> *[_]ABW*,*[_]ANT*,*[_]ARG*,*[_]ATG*,*[_]BHS*,*[_]BLZ*,*[_]BMU*,*[_]BOL*,*[_]BRB*,*[_]CHL*
A71: =IF(B71=B72,0,1) -> 0 | B71: CSA | C71: CRI | D71: =A71&B71 -> 0CSA | E71: =IF(B71=B70,E70&","&"*[_]"&C71&"*","*[_]"&C71&"*") -> *[_]ABW*,*[_]ANT*,*[_]ARG*,*[_]ATG*,*[_]BHS*,*[_]BLZ*,*[_]BMU*,*[_]BOL*,*[_]BRB*,*[_]CHL*,*[_]CRI*
A72: =IF(B72=B73,0,1) -> 0 | B72: CSA | C72: CUB | D72: =A72&B72 -> 0CSA | E72: =IF(B72=B71,E71&","&"*[_]"&C72&"*","*[_]"&C72&"*") -> *[_]ABW*,*[_]ANT*,*[_]ARG*,*[_]ATG*,*[_]BHS*,*[_]BLZ*,*[_]BMU*,*[_]BOL*,*[_]BRB*,*[_]CHL*,*[_]CRI*,*[_]CUB*
A73: =IF(B73=B74,0,1) -> 0 | B73: CSA | C73: CUW | D73: =A73&B73 -> 0CSA | E73: =IF(B73=B72,E72&","&"*[_]"&C73&"*","*[_]"&C73&"*") -> *[_]ABW*,*[_]ANT*,*[_]ARG*,*[_]ATG*,*[_]BHS*,*[_]BLZ*,*[_]BMU*,*[_]BOL*,*[_]BRB*,*[_]CHL*,*[_]CRI*,*[_]CUB*,*[_]CUW*
A74: =IF(B74=B75,0,1) -> 0 | B74: CSA | C74: CYM | D74: =A74&B74 -> 0CSA | E74: =IF(B74=B73,E73&","&"*[_]"&C74&"*","*[_]"&C74&"*") -> *[_]ABW*,*[_]ANT*,*[_]ARG*,*[_]ATG*,*[_]BHS*,*[_]BLZ*,*[_]BMU*,*[_]BOL*,*[_]BRB*,*[_]CHL*,*[_]CRI*,*[_]CUB*,*[_]CUW*,*[_]CYM*
A75: =IF(B75=B76,0,1) -> 0 | B75: CSA | C75: DMA | D75: =A75&B75 -> 0CSA | E75: =IF(B75=B74,E74&","&"*[_]"&C75&"*","*[_]"&C75&"*") -> *[_]ABW*,*[_]ANT*,*[_]ARG*,*[_]ATG*,*[_]BHS*,*[_]BLZ*,*[_]BMU*,*[_]BOL*,*[_]BRB*,*[_]CHL*,*[_]CRI*,*[_]CUB*,*[_]CUW*,*[_]CYM*,*[_]DMA*
A76: =IF(B76=B77,0,1) -> 0 | B76: CSA | C76: DOM | D76: =A76&B76 -> 0CSA | E76: =IF(B76=B75,E75&","&"*[_]"&C76&"*","*[_]"&C76&"*") -> *[_]ABW*,*[_]ANT*,*[_]ARG*,*[_]ATG*,*[_]BHS*,*[_]BLZ*,*[_]BMU*,*[_]BOL*,*[_]BRB*,*[_]CHL*,*[_]CRI*,*[_]CUB*,*[_]CUW*,*[_]CYM*,*[_]DMA*,*[_]DOM*
A77: =IF(B77=B78,0,1) -> 0 | B77: CSA | C77: ECU | D77: =A77&B77 -> 0CSA | E77: =IF(B77=B76,E76&","&"*[_]"&C77&"*","*[_]"&C77&"*") -> *[_]ABW*,*[_]ANT*,*[_]ARG*,*[_]ATG*,*[_]BHS*,*[_]BLZ*,*[_]BMU*,*[_]BOL*,*[_]BRB*,*[_]CHL*,*[_]CRI*,*[_]CUB*,*[_]CUW*,*[_]CYM*,*[_]DMA*,*[_]DOM*,*[_]ECU*
A78: =IF(B78=B79,0,1) -> 0 | B78: CSA | C78: GRD | D78: =A78&B78 -> 0CSA | E78: =IF(B78=B77,E77&","&"*[_]"&C78&"*","*[_]"&C78&"*") -> *[_]ABW*,*[_]ANT*,*[_]ARG*,*[_]ATG*,*[_]BHS*,*[_]BLZ*,*[_]BMU*,*[_]BOL*,*[_]BRB*,*[_]CHL*,*[_]CRI*,*[_]CUB*,*[_]CUW*,*[_]CYM*,*[_]DMA*,*[_]DOM*,*[_]ECU*,*[_]GRD*
A79: =IF(B79=B80,0,1) -> 0 | B79: CSA | C79: GTM | D79: =A79&B79 -> 0CSA | E79: =IF(B79=B78,E78&","&"*[_]"&C79&"*","*[_]"&C79&"*") -> *[_]ABW*,*[_]ANT*,*[_]ARG*,*[_]ATG*,*[_]BHS*,*[_]BLZ*,*[_]BMU*,*[_]BOL*,*[_]BRB*,*[_]CHL*,*[_]CRI*,*[_]CUB*,*[_]CUW*,*[_]CYM*,*[_]DMA*,*[_]DOM*,*[_]ECU*,*[_]GRD*,*[_]GTM*
A80: =IF(B80=B81,0,1) -> 0 | B80: CSA | C80: GUF | D80: =A80&B80 -> 0CSA | E80: =IF(B80=B79,E79&","&"*[_]"&C80&"*","*[_]"&C80&"*") -> *[_]ABW*,*[_]ANT*,*[_]ARG*,*[_]ATG*,*[_]BHS*,*[_]BLZ*,*[_]BMU*,*[_]BOL*,*[_]BRB*,*[_]CHL*,*[_]CRI*,*[_]CUB*,*[_]CUW*,*[_]CYM*,*[_]DMA*,*[_]DOM*,*[_]ECU*,*[_]GRD*,*[_]GTM*,*[_]GUF*
A81: =IF(B81=B82,0,1) -> 0 | B81: CSA | C81: GUY | D81: =A81&B81 -> 0CSA | E81: =IF(B81=B80,E80&","&"*[_]"&C81&"*","*[_]"&C81&"*") -> *[_]ABW*,*[_]ANT*,*[_]ARG*,*[_]ATG*,*[_]BHS*,*[_]BLZ*,*[_]BMU*,*[_]BOL*,*[_]BRB*,*[_]CHL*,*[_]CRI*,*[_]CUB*,*[_]CUW*,*[_]CYM*,*[_]DMA*,*[_]DOM*,*[_]ECU*,*[_]GRD*,*[_]GTM*,*[_]GUF*,*[_]GUY*
A82: =IF(B82=B83,0,1) -> 0 | B82: CSA | C82: HND | D82: =A82&B82 -> 0CSA | E82: =IF(B82=B81,E81&","&"*[_]"&C82&"*","*[_]"&C82&"*") -> *[_]ABW*,*[_]ANT*,*[_]ARG*,*[_]ATG*,*[_]BHS*,*[_]BLZ*,*[_]BMU*,*[_]BOL*,*[_]BRB*,*[_]CHL*,*[_]CRI*,*[_]CUB*,*[_]CUW*,*[_]CYM*,*[_]DMA*,*[_]DOM*,*[_]ECU*,*[_]GRD*,*[_]GTM*,*[_]GUF*,*[_]GUY*,*[_]HND*
... A232: =IF(B232=B233,0,1) -> 1 | B232: USA | C232: USA | D232: =A232&B232 -> 1USA | E232: =IF(B232=B231,E231&","&"*[_]"&C232&"*","*[_]"&C232&"*") -> *[_]USA*
